filter/code.v
module mult(
    input clk,
    input reset,
    input [31:0] multipliable_1,
    input [31:0] multipliable_2,
    output reg [31:0] composition = 31'b0
);

reg [1:0][31:0] multipliables = 64'b0;

    always @(posedge clk) begin
        //checking reset
        if(!(reset)) begin 
            composition <= 31'b0;
            multipliables <= 64'b0;
        end
        else begin
            //first step of multiplication
            multipliables[0] <= multipliable_1;
            multipliables[1] <= multipliable_2;

            //second step of multiplication
            composition <= multipliables[0] * multipliables[1];
        end
    end
endmodule // mult

module addition(
    input [31:0] terms_1, 
    input [31:0] terms_2,
    output [31:0] additional_result
);

    assign additional_result = terms_1 + terms_2;

endmodule //addition

module filter(
    input clk,
    input reset,
    input [7:0] x,
    output [31:0] y
);

    //declare the coefficient
    reg [31:0] a = 2;
    reg [31:0] b = 3;

    //declare service signals

    //declare signal for multiplication bloks
    wire [1:0][31:0] mult_ay_input;
    wire [31:0] mult_ay_output;
    wire [1:0][31:0] mult_bx_input;
    wire [31:0] mult_bx_output;

    //link the multiplication signals
    assign mult_ay_input[0] = a;
    assign mult_ay_input[1] = y;

    assign mult_bx_input[0] = b;
    assign mult_bx_input[1] = x;

    //declare multiplication blocks
    mult MULT_AY(clk, reset, mult_ay_input[0], mult_ay_input[1], mult_ay_output);
    mult MULT_BX(clk, reset, mult_bx_input[0], mult_bx_input[1], mult_bx_output);

    //declare the additional block
    addition ADD(mult_ay_output, mult_bx_output, y);
endmodule // filter

filter/testbench.v
`timescale 10ps / 1ps
module filter_test;
    // дамп файла для GtkWave
    initial begin
        $dumpfile("filter_sim.vcd");
        $dumpvars(0, filter_test);
    end
    
    // входные сигналы
    reg clk = 0;
    always #5 clk = !clk;
    
    reg [7:0] x = 0;

    always @(posedge clk) begin
       x <= x + 1;
    end
    reg reset = 1'b1;
    initial begin
        #130 reset <= 1'b0;
        #93 reset <= 1'b1;
    end

    wire [31:0] out;
    // подключаем модуль
    filter DD1(clk, reset, x, out);

    // отслеживание сигналов
    initial begin
        $monitor("At time %t", $time);
        #1000 $finish;
    end
endmodule // filter_test

filter/filter_sim.vcd
$date
	Wed Oct  1 11:35:22 2025
$end
$version
	Icarus Verilog
$end
$timescale
	1ps
$end
$scope module filter_test $end
$var wire 32 ! out [31:0] $end
$var reg 1 " clk $end
$var reg 1 # reset $end
$var reg 8 $ x [7:0] $end
$scope module DD1 $end
$var wire 1 " clk $end
$var wire 1 # reset $end
$var wire 8 % x [7:0] $end
$var wire 32 & y [31:0] $end
$var wire 32 ' mult_bx_output [31:0] $end
$var wire 64 ( mult_bx_input [63:0] $end
$var wire 32 ) mult_ay_output [31:0] $end
$var wire 64 * mult_ay_input [63:0] $end
$var reg 32 + a [31:0] $end
$var reg 32 , b [31:0] $end
$scope module ADD $end
$var wire 32 - terms_2 [31:0] $end
$var wire 32 . terms_1 [31:0] $end
$var wire 32 / additional_result [31:0] $end
$upscope $end
$scope module MULT_AY $end
$var wire 1 " clk $end
$var wire 32 0 multipliable_1 [31:0] $end
$var wire 32 1 multipliable_2 [31:0] $end
$var wire 1 # reset $end
$var reg 32 2 composition [31:0] $end
$var reg 64 3 multipliables [63:0] $end
$upscope $end
$scope module MULT_BX $end
$var wire 1 " clk $end
$var wire 32 4 multipliable_1 [31:0] $end
$var wire 32 5 multipliable_2 [31:0] $end
$var wire 1 # reset $end
$var reg 32 6 composition [31:0] $end
$var reg 64 7 multipliables [63:0] $end
$upscope $end
$upscope $end
$upscope $end
$enddefinitions $end
$comment Show the parameter values. $end
$dumpall
$end
#0
$dumpvars
b0 7
b0 6
b0 5
b11 4
b0 3
b0 2
b0 1
b10 0
b0 /
b0 .
b0 -
b11 ,
b10 +
b10 *
b0 )
b11 (
b0 '
b0 &
b0 %
b0 $
1#
0"
b0 !
$end
#50
b1 5
b10 3
b11 7
b100000000000000000000000000000011 (
b1 $
b1 %
1"
#100
0"
#150
b10 5
b1000000000000000000000000000000011 (
b10 $
b10 %
b100000000000000000000000000000011 7
1"
#200
0"
#250
b11 1
b11 5
b1100000000000000000000000000000010 *
b11 !
b11 &
b11 /
b11 '
b11 -
b11 6
b1000000000000000000000000000000011 7
b1100000000000000000000000000000011 (
b11 $
b11 %
1"
#300
0"
#350
b100 5
b110 1
b10000000000000000000000000000000011 (
b100 $
b100 %
b11000000000000000000000000000000010 *
b110 !
b110 &
b110 /
b110 '
b110 -
b110 6
b1100000000000000000000000000000011 7
b1100000000000000000000000000000010 3
1"
#400
0"
#450
b1111 1
b101 5
b110 )
b110 .
b110 2
b11000000000000000000000000000000010 3
b111100000000000000000000000000000010 *
b1111 !
b1111 &
b1111 /
b1001 '
b1001 -
b1001 6
b10000000000000000000000000000000011 7
b10100000000000000000000000000000011 (
b101 $
b101 %
1"
#500
0"
#550
b110 5
b11000 1
b11000000000000000000000000000000011 (
b110 $
b110 %
b1100 '
b1100 -
b1100 6
b10100000000000000000000000000000011 7
b1100000000000000000000000000000000010 *
b11000 !
b11000 &
b11000 /
b1100 )
b1100 .
b1100 2
b111100000000000000000000000000000010 3
1"
#600
0"
#650
b101101 1
b111 5
b11110 )
b11110 .
b11110 2
b1100000000000000000000000000000000010 3
b10110100000000000000000000000000000010 *
b101101 !
b101101 &
b101101 /
b1111 '
b1111 -
b1111 6
b11000000000000000000000000000000011 7
b11100000000000000000000000000000011 (
b111 $
b111 %
1"
#700
0"
#750
b1000 5
b1000010 1
b100000000000000000000000000000000011 (
b1000 $
b1000 %
b10010 '
b10010 -
b10010 6
b11100000000000000000000000000000011 7
b100001000000000000000000000000000000010 *
b1000010 !
b1000010 &
b1000010 /
b110000 )
b110000 .
b110000 2
b10110100000000000000000000000000000010 3
1"
#800
0"
#850
b1101111 1
b1001 5
b1011010 )
b1011010 .
b1011010 2
b100001000000000000000000000000000000010 3
b110111100000000000000000000000000000010 *
b1101111 !
b1101111 &
b1101111 /
b10101 '
b10101 -
b10101 6
b100000000000000000000000000000000011 7
b100100000000000000000000000000000011 (
b1001 $
b1001 %
1"
#900
0"
#950
b1010 5
b10011100 1
b101000000000000000000000000000000011 (
b1010 $
b1010 %
b11000 '
b11000 -
b11000 6
b100100000000000000000000000000000011 7
b1001110000000000000000000000000000000010 *
b10011100 !
b10011100 &
b10011100 /
b10000100 )
b10000100 .
b10000100 2
b110111100000000000000000000000000000010 3
1"
#1000
0"
#1050
b11111001 1
b1011 5
b11011110 )
b11011110 .
b11011110 2
b1001110000000000000000000000000000000010 3
b1111100100000000000000000000000000000010 *
b11111001 !
b11111001 &
b11111001 /
b11011 '
b11011 -
b11011 6
b101000000000000000000000000000000011 7
b101100000000000000000000000000000011 (
b1011 $
b1011 %
1"
#1100
0"
#1150
b1100 5
b101010110 1
b110000000000000000000000000000000011 (
b1100 $
b1100 %
b11110 '
b11110 -
b11110 6
b101100000000000000000000000000000011 7
b10101011000000000000000000000000000000010 *
b101010110 !
b101010110 &
b101010110 /
b100111000 )
b100111000 .
b100111000 2
b1111100100000000000000000000000000000010 3
1"
#1200
0"
#1250
b1000010011 1
b1101 5
b111110010 )
b111110010 .
b111110010 2
b10101011000000000000000000000000000000010 3
b100001001100000000000000000000000000000010 *
b1000010011 !
b1000010011 &
b1000010011 /
b100001 '
b100001 -
b100001 6
b110000000000000000000000000000000011 7
b110100000000000000000000000000000011 (
b1101 $
b1101 %
1"
#1300
0#
0"
#1350
b1110 5
b0 1
b111000000000000000000000000000000011 (
b1110 $
b1110 %
b0 7
b0 '
b0 -
b0 6
b0 3
b10 *
b0 !
b0 &
b0 /
b0 )
b0 .
b0 2
1"
#1400
0"
#1450
b1111 5
b111100000000000000000000000000000011 (
b1111 $
b1111 %
1"
#1500
0"
#1550
b10000 5
b1000000000000000000000000000000000011 (
b10000 $
b10000 %
1"
#1600
0"
#1650
b10001 5
b1000100000000000000000000000000000011 (
b10001 $
b10001 %
1"
#1700
0"
#1750
b10010 5
b1001000000000000000000000000000000011 (
b10010 $
b10010 %
1"
#1800
0"
#1850
b10011 5
b1001100000000000000000000000000000011 (
b10011 $
b10011 %
1"
#1900
0"
#1950
b10100 5
b1010000000000000000000000000000000011 (
b10100 $
b10100 %
1"
#2000
0"
#2050
b10101 5
b1010100000000000000000000000000000011 (
b10101 $
b10101 %
1"
#2100
0"
#2150
b10110 5
b1011000000000000000000000000000000011 (
b10110 $
b10110 %
1"
#2200
0"
#2230
1#
#2250
b10111 5
b10 3
b1011000000000000000000000000000000011 7
b1011100000000000000000000000000000011 (
b10111 $
b10111 %
1"
#2300
0"
#2350
b11000 5
b1000010 1
b1100000000000000000000000000000000011 (
b11000 $
b11000 %
b100001000000000000000000000000000000010 *
b1000010 !
b1000010 &
b1000010 /
b1000010 '
b1000010 -
b1000010 6
b1011100000000000000000000000000000011 7
1"
#2400
0"
#2450
b1000101 1
b11001 5
b100001000000000000000000000000000000010 3
b100010100000000000000000000000000000010 *
b1000101 !
b1000101 &
b1000101 /
b1000101 '
b1000101 -
b1000101 6
b1100000000000000000000000000000000011 7
b1100100000000000000000000000000000011 (
b11001 $
b11001 %
1"
#2500
0"
#2550
b11010 5
b11001100 1
b1101000000000000000000000000000000011 (
b11010 $
b11010 %
b1001000 '
b1001000 -
b1001000 6
b1100100000000000000000000000000000011 7
b1100110000000000000000000000000000000010 *
b11001100 !
b11001100 &
b11001100 /
b10000100 )
b10000100 .
b10000100 2
b100010100000000000000000000000000000010 3
1"
#2600
0"
#2650
b11010101 1
b11011 5
b10001010 )
b10001010 .
b10001010 2
b1100110000000000000000000000000000000010 3
b1101010100000000000000000000000000000010 *
b11010101 !
b11010101 &
b11010101 /
b1001011 '
b1001011 -
b1001011 6
b1101000000000000000000000000000000011 7
b1101100000000000000000000000000000011 (
b11011 $
b11011 %
1"
#2700
0"
#2750
b11100 5
b111100110 1
b1110000000000000000000000000000000011 (
b11100 $
b11100 %
b1001110 '
b1001110 -
b1001110 6
b1101100000000000000000000000000000011 7
b11110011000000000000000000000000000000010 *
b111100110 !
b111100110 &
b111100110 /
b110011000 )
b110011000 .
b110011000 2
b1101010100000000000000000000000000000010 3
1"
#2800
0"
#2850
b111111011 1
b11101 5
b110101010 )
b110101010 .
b110101010 2
b11110011000000000000000000000000000000010 3
b11111101100000000000000000000000000000010 *
b111111011 !
b111111011 &
b111111011 /
b1010001 '
b1010001 -
b1010001 6
b1110000000000000000000000000000000011 7
b1110100000000000000000000000000000011 (
b11101 $
b11101 %
1"
#2900
0"
#2950
b11110 5
b10000100000 1
b1111000000000000000000000000000000011 (
b11110 $
b11110 %
b1010100 '
b1010100 -
b1010100 6
b1110100000000000000000000000000000011 7
b1000010000000000000000000000000000000000010 *
b10000100000 !
b10000100000 &
b10000100000 /
b1111001100 )
b1111001100 .
b1111001100 2
b11111101100000000000000000000000000000010 3
1"
#3000
0"
#3050
b10001001101 1
b11111 5
b1111110110 )
b1111110110 .
b1111110110 2
b1000010000000000000000000000000000000000010 3
b1000100110100000000000000000000000000000010 *
b10001001101 !
b10001001101 &
b10001001101 /
b1010111 '
b1010111 -
b1010111 6
b1111000000000000000000000000000000011 7
b1111100000000000000000000000000000011 (
b11111 $
b11111 %
1"
#3100
0"
#3150
b100000 5
b100010011010 1
b10000000000000000000000000000000000011 (
b100000 $
b100000 %
b1011010 '
b1011010 -
b1011010 6
b1111100000000000000000000000000000011 7
b10001001101000000000000000000000000000000010 *
b100010011010 !
b100010011010 &
b100010011010 /
b100001000000 )
b100001000000 .
b100001000000 2
b1000100110100000000000000000000000000000010 3
1"
#3200
0"
#3250
b100011110111 1
b100001 5
b100010011010 )
b100010011010 .
b100010011010 2
b10001001101000000000000000000000000000000010 3
b10001111011100000000000000000000000000000010 *
b100011110111 !
b100011110111 &
b100011110111 /
b1011101 '
b1011101 -
b1011101 6
b10000000000000000000000000000000000011 7
b10000100000000000000000000000000000011 (
b100001 $
b100001 %
1"
#3300
0"
#3350
b100010 5
b1000110010100 1
b10001000000000000000000000000000000011 (
b100010 $
b100010 %
b1100000 '
b1100000 -
b1100000 6
b10000100000000000000000000000000000011 7
b100011001010000000000000000000000000000000010 *
b1000110010100 !
b1000110010100 &
b1000110010100 /
b1000100110100 )
b1000100110100 .
b1000100110100 2
b10001111011100000000000000000000000000000010 3
1"
#3400
0"
#3450
b1001001010001 1
b100011 5
b1000111101110 )
b1000111101110 .
b1000111101110 2
b100011001010000000000000000000000000000000010 3
b100100101000100000000000000000000000000000010 *
b1001001010001 !
b1001001010001 &
b1001001010001 /
b1100011 '
b1100011 -
b1100011 6
b10001000000000000000000000000000000011 7
b10001100000000000000000000000000000011 (
b100011 $
b100011 %
1"
#3500
0"
#3550
b100100 5
b10001110001110 1
b10010000000000000000000000000000000011 (
b100100 $
b100100 %
b1100110 '
b1100110 -
b1100110 6
b10001100000000000000000000000000000011 7
b1000111000111000000000000000000000000000000010 *
b10001110001110 !
b10001110001110 &
b10001110001110 /
b10001100101000 )
b10001100101000 .
b10001100101000 2
b100100101000100000000000000000000000000000010 3
1"
#3600
0"
#3650
b10010100001011 1
b100101 5
b10010010100010 )
b10010010100010 .
b10010010100010 2
b1000111000111000000000000000000000000000000010 3
b1001010000101100000000000000000000000000000010 *
b10010100001011 !
b10010100001011 &
b10010100001011 /
b1101001 '
b1101001 -
b1101001 6
b10010000000000000000000000000000000011 7
b10010100000000000000000000000000000011 (
b100101 $
b100101 %
1"
#3700
0"
#3750
b100110 5
b100011110001000 1
b10011000000000000000000000000000000011 (
b100110 $
b100110 %
b1101100 '
b1101100 -
b1101100 6
b10010100000000000000000000000000000011 7
b10001111000100000000000000000000000000000000010 *
b100011110001000 !
b100011110001000 &
b100011110001000 /
b100011100011100 )
b100011100011100 .
b100011100011100 2
b1001010000101100000000000000000000000000000010 3
1"
#3800
0"
#3850
b100101010000101 1
b100111 5
b100101000010110 )
b100101000010110 .
b100101000010110 2
b10001111000100000000000000000000000000000000010 3
b10010101000010100000000000000000000000000000010 *
b100101010000101 !
b100101010000101 &
b100101010000101 /
b1101111 '
b1101111 -
b1101111 6
b10011000000000000000000000000000000011 7
b10011100000000000000000000000000000011 (
b100111 $
b100111 %
1"
#3900
0"
#3950
b101000 5
b1000111110000010 1
b10100000000000000000000000000000000011 (
b101000 $
b101000 %
b1110010 '
b1110010 -
b1110010 6
b10011100000000000000000000000000000011 7
b100011111000001000000000000000000000000000000010 *
b1000111110000010 !
b1000111110000010 &
b1000111110000010 /
b1000111100010000 )
b1000111100010000 .
b1000111100010000 2
b10010101000010100000000000000000000000000000010 3
1"
#4000
0"
#4050
b1001010101111111 1
b101001 5
b1001010100001010 )
b1001010100001010 .
b1001010100001010 2
b100011111000001000000000000000000000000000000010 3
b100101010111111100000000000000000000000000000010 *
b1001010101111111 !
b1001010101111111 &
b1001010101111111 /
b1110101 '
b1110101 -
b1110101 6
b10100000000000000000000000000000000011 7
b10100100000000000000000000000000000011 (
b101001 $
b101001 %
1"
#4100
0"
#4150
b101010 5
b10001111101111100 1
b10101000000000000000000000000000000011 (
b101010 $
b101010 %
b1111000 '
b1111000 -
b1111000 6
b10100100000000000000000000000000000011 7
b1000111110111110000000000000000000000000000000010 *
b10001111101111100 !
b10001111101111100 &
b10001111101111100 /
b10001111100000100 )
b10001111100000100 .
b10001111100000100 2
b100101010111111100000000000000000000000000000010 3
1"
#4200
0"
#4250
b10010101101111001 1
b101011 5
b10010101011111110 )
b10010101011111110 .
b10010101011111110 2
b1000111110111110000000000000000000000000000000010 3
b1001010110111100100000000000000000000000000000010 *
b10010101101111001 !
b10010101101111001 &
b10010101101111001 /
b1111011 '
b1111011 -
b1111011 6
b10101000000000000000000000000000000011 7
b10101100000000000000000000000000000011 (
b101011 $
b101011 %
1"
#4300
0"
#4350
b101100 5
b100011111101110110 1
b10110000000000000000000000000000000011 (
b101100 $
b101100 %
b1111110 '
b1111110 -
b1111110 6
b10101100000000000000000000000000000011 7
b10001111110111011000000000000000000000000000000010 *
b100011111101110110 !
b100011111101110110 &
b100011111101110110 /
b100011111011111000 )
b100011111011111000 .
b100011111011111000 2
b1001010110111100100000000000000000000000000000010 3
1"
#4400
0"
#4450
b100101011101110011 1
b101101 5
b100101011011110010 )
b100101011011110010 .
b100101011011110010 2
b10001111110111011000000000000000000000000000000010 3
b10010101110111001100000000000000000000000000000010 *
b100101011101110011 !
b100101011101110011 &
b100101011101110011 /
b10000001 '
b10000001 -
b10000001 6
b10110000000000000000000000000000000011 7
b10110100000000000000000000000000000011 (
b101101 $
b101101 %
1"
#4500
0"
#4550
b101110 5
b1000111111101110000 1
b10111000000000000000000000000000000011 (
b101110 $
b101110 %
b10000100 '
b10000100 -
b10000100 6
b10110100000000000000000000000000000011 7
b100011111110111000000000000000000000000000000000010 *
b1000111111101110000 !
b1000111111101110000 &
b1000111111101110000 /
b1000111111011101100 )
b1000111111011101100 .
b1000111111011101100 2
b10010101110111001100000000000000000000000000000010 3
1"
#4600
0"
#4650
b1001010111101101101 1
b101111 5
b1001010111011100110 )
b1001010111011100110 .
b1001010111011100110 2
b100011111110111000000000000000000000000000000000010 3
b100101011110110110100000000000000000000000000000010 *
b1001010111101101101 !
b1001010111101101101 &
b1001010111101101101 /
b10000111 '
b10000111 -
b10000111 6
b10111000000000000000000000000000000011 7
b10111100000000000000000000000000000011 (
b101111 $
b101111 %
1"
#4700
0"
#4750
b110000 5
b10001111111101101010 1
b11000000000000000000000000000000000011 (
b110000 $
b110000 %
b10001010 '
b10001010 -
b10001010 6
b10111100000000000000000000000000000011 7
b1000111111110110101000000000000000000000000000000010 *
b10001111111101101010 !
b10001111111101101010 &
b10001111111101101010 /
b10001111111011100000 )
b10001111111011100000 .
b10001111111011100000 2
b100101011110110110100000000000000000000000000000010 3
1"
#4800
0"
#4850
b10010101111101100111 1
b110001 5
b10010101111011011010 )
b10010101111011011010 .
b10010101111011011010 2
b1000111111110110101000000000000000000000000000000010 3
b1001010111110110011100000000000000000000000000000010 *
b10010101111101100111 !
b10010101111101100111 &
b10010101111101100111 /
b10001101 '
b10001101 -
b10001101 6
b11000000000000000000000000000000000011 7
b11000100000000000000000000000000000011 (
b110001 $
b110001 %
1"
#4900
0"
#4950
b110010 5
b100011111111101100100 1
b11001000000000000000000000000000000011 (
b110010 $
b110010 %
b10010000 '
b10010000 -
b10010000 6
b11000100000000000000000000000000000011 7
b10001111111110110010000000000000000000000000000000010 *
b100011111111101100100 !
b100011111111101100100 &
b100011111111101100100 /
b100011111111011010100 )
b100011111111011010100 .
b100011111111011010100 2
b1001010111110110011100000000000000000000000000000010 3
1"
#5000
0"
#5050
b100101011111101100001 1
b110011 5
b100101011111011001110 )
b100101011111011001110 .
b100101011111011001110 2
b10001111111110110010000000000000000000000000000000010 3
b10010101111110110000100000000000000000000000000000010 *
b100101011111101100001 !
b100101011111101100001 &
b100101011111101100001 /
b10010011 '
b10010011 -
b10010011 6
b11001000000000000000000000000000000011 7
b11001100000000000000000000000000000011 (
b110011 $
b110011 %
1"
#5100
0"
#5150
b110100 5
b1000111111111101011110 1
b11010000000000000000000000000000000011 (
b110100 $
b110100 %
b10010110 '
b10010110 -
b10010110 6
b11001100000000000000000000000000000011 7
b100011111111110101111000000000000000000000000000000010 *
b1000111111111101011110 !
b1000111111111101011110 &
b1000111111111101011110 /
b1000111111111011001000 )
b1000111111111011001000 .
b1000111111111011001000 2
b10010101111110110000100000000000000000000000000000010 3
1"
#5200
0"
#5250
b1001010111111101011011 1
b110101 5
b1001010111111011000010 )
b1001010111111011000010 .
b1001010111111011000010 2
b100011111111110101111000000000000000000000000000000010 3
b100101011111110101101100000000000000000000000000000010 *
b1001010111111101011011 !
b1001010111111101011011 &
b1001010111111101011011 /
b10011001 '
b10011001 -
b10011001 6
b11010000000000000000000000000000000011 7
b11010100000000000000000000000000000011 (
b110101 $
b110101 %
1"
#5300
0"
#5350
b110110 5
b10001111111111101011000 1
b11011000000000000000000000000000000011 (
b110110 $
b110110 %
b10011100 '
b10011100 -
b10011100 6
b11010100000000000000000000000000000011 7
b1000111111111110101100000000000000000000000000000000010 *
b10001111111111101011000 !
b10001111111111101011000 &
b10001111111111101011000 /
b10001111111111010111100 )
b10001111111111010111100 .
b10001111111111010111100 2
b100101011111110101101100000000000000000000000000000010 3
1"
#5400
0"
#5450
b10010101111111101010101 1
b110111 5
b10010101111111010110110 )
b10010101111111010110110 .
b10010101111111010110110 2
b1000111111111110101100000000000000000000000000000000010 3
b1001010111111110101010100000000000000000000000000000010 *
b10010101111111101010101 !
b10010101111111101010101 &
b10010101111111101010101 /
b10011111 '
b10011111 -
b10011111 6
b11011000000000000000000000000000000011 7
b11011100000000000000000000000000000011 (
b110111 $
b110111 %
1"
#5500
0"
#5550
b111000 5
b100011111111111101010010 1
b11100000000000000000000000000000000011 (
b111000 $
b111000 %
b10100010 '
b10100010 -
b10100010 6
b11011100000000000000000000000000000011 7
b10001111111111110101001000000000000000000000000000000010 *
b100011111111111101010010 !
b100011111111111101010010 &
b100011111111111101010010 /
b100011111111111010110000 )
b100011111111111010110000 .
b100011111111111010110000 2
b1001010111111110101010100000000000000000000000000000010 3
1"
#5600
0"
#5650
b100101011111111101001111 1
b111001 5
b100101011111111010101010 )
b100101011111111010101010 .
b100101011111111010101010 2
b10001111111111110101001000000000000000000000000000000010 3
b10010101111111110100111100000000000000000000000000000010 *
b100101011111111101001111 !
b100101011111111101001111 &
b100101011111111101001111 /
b10100101 '
b10100101 -
b10100101 6
b11100000000000000000000000000000000011 7
b11100100000000000000000000000000000011 (
b111001 $
b111001 %
1"
#5700
0"
#5750
b111010 5
b1000111111111111101001100 1
b11101000000000000000000000000000000011 (
b111010 $
b111010 %
b10101000 '
b10101000 -
b10101000 6
b11100100000000000000000000000000000011 7
b100011111111111110100110000000000000000000000000000000010 *
b1000111111111111101001100 !
b1000111111111111101001100 &
b1000111111111111101001100 /
b1000111111111111010100100 )
b1000111111111111010100100 .
b1000111111111111010100100 2
b10010101111111110100111100000000000000000000000000000010 3
1"
#5800
0"
#5850
b1001010111111111101001001 1
b111011 5
b1001010111111111010011110 )
b1001010111111111010011110 .
b1001010111111111010011110 2
b100011111111111110100110000000000000000000000000000000010 3
b100101011111111110100100100000000000000000000000000000010 *
b1001010111111111101001001 !
b1001010111111111101001001 &
b1001010111111111101001001 /
b10101011 '
b10101011 -
b10101011 6
b11101000000000000000000000000000000011 7
b11101100000000000000000000000000000011 (
b111011 $
b111011 %
1"
#5900
0"
#5950
b111100 5
b10001111111111111101000110 1
b11110000000000000000000000000000000011 (
b111100 $
b111100 %
b10101110 '
b10101110 -
b10101110 6
b11101100000000000000000000000000000011 7
b1000111111111111110100011000000000000000000000000000000010 *
b10001111111111111101000110 !
b10001111111111111101000110 &
b10001111111111111101000110 /
b10001111111111111010011000 )
b10001111111111111010011000 .
b10001111111111111010011000 2
b100101011111111110100100100000000000000000000000000000010 3
1"
#6000
0"
#6050
b10010101111111111101000011 1
b111101 5
b10010101111111111010010010 )
b10010101111111111010010010 .
b10010101111111111010010010 2
b1000111111111111110100011000000000000000000000000000000010 3
b1001010111111111110100001100000000000000000000000000000010 *
b10010101111111111101000011 !
b10010101111111111101000011 &
b10010101111111111101000011 /
b10110001 '
b10110001 -
b10110001 6
b11110000000000000000000000000000000011 7
b11110100000000000000000000000000000011 (
b111101 $
b111101 %
1"
#6100
0"
#6150
b111110 5
b100011111111111111101000000 1
b11111000000000000000000000000000000011 (
b111110 $
b111110 %
b10110100 '
b10110100 -
b10110100 6
b11110100000000000000000000000000000011 7
b10001111111111111110100000000000000000000000000000000000010 *
b100011111111111111101000000 !
b100011111111111111101000000 &
b100011111111111111101000000 /
b100011111111111111010001100 )
b100011111111111111010001100 .
b100011111111111111010001100 2
b1001010111111111110100001100000000000000000000000000000010 3
1"
#6200
0"
#6250
b100101011111111111100111101 1
b111111 5
b100101011111111111010000110 )
b100101011111111111010000110 .
b100101011111111111010000110 2
b10001111111111111110100000000000000000000000000000000000010 3
b10010101111111111110011110100000000000000000000000000000010 *
b100101011111111111100111101 !
b100101011111111111100111101 &
b100101011111111111100111101 /
b10110111 '
b10110111 -
b10110111 6
b11111000000000000000000000000000000011 7
b11111100000000000000000000000000000011 (
b111111 $
b111111 %
1"
#6300
0"
#6350
b1000000 5
b1000111111111111111100111010 1
b100000000000000000000000000000000000011 (
b1000000 $
b1000000 %
b10111010 '
b10111010 -
b10111010 6
b11111100000000000000000000000000000011 7
b100011111111111111110011101000000000000000000000000000000010 *
b1000111111111111111100111010 !
b1000111111111111111100111010 &
b1000111111111111111100111010 /
b1000111111111111111010000000 )
b1000111111111111111010000000 .
b1000111111111111111010000000 2
b10010101111111111110011110100000000000000000000000000000010 3
1"
#6400
0"
#6450
b1001010111111111111100110111 1
b1000001 5
b1001010111111111111001111010 )
b1001010111111111111001111010 .
b1001010111111111111001111010 2
b100011111111111111110011101000000000000000000000000000000010 3
b100101011111111111110011011100000000000000000000000000000010 *
b1001010111111111111100110111 !
b1001010111111111111100110111 &
b1001010111111111111100110111 /
b10111101 '
b10111101 -
b10111101 6
b100000000000000000000000000000000000011 7
b100000100000000000000000000000000000011 (
b1000001 $
b1000001 %
1"
#6500
0"
#6550
b1000010 5
b10001111111111111111100110100 1
b100001000000000000000000000000000000011 (
b1000010 $
b1000010 %
b11000000 '
b11000000 -
b11000000 6
b100000100000000000000000000000000000011 7
b1000111111111111111110011010000000000000000000000000000000010 *
b10001111111111111111100110100 !
b10001111111111111111100110100 &
b10001111111111111111100110100 /
b10001111111111111111001110100 )
b10001111111111111111001110100 .
b10001111111111111111001110100 2
b100101011111111111110011011100000000000000000000000000000010 3
1"
#6600
0"
#6650
b10010101111111111111100110001 1
b1000011 5
b10010101111111111111001101110 )
b10010101111111111111001101110 .
b10010101111111111111001101110 2
b1000111111111111111110011010000000000000000000000000000000010 3
b1001010111111111111110011000100000000000000000000000000000010 *
b10010101111111111111100110001 !
b10010101111111111111100110001 &
b10010101111111111111100110001 /
b11000011 '
b11000011 -
b11000011 6
b100001000000000000000000000000000000011 7
b100001100000000000000000000000000000011 (
b1000011 $
b1000011 %
1"
#6700
0"
#6750
b1000100 5
b100011111111111111111100101110 1
b100010000000000000000000000000000000011 (
b1000100 $
b1000100 %
b11000110 '
b11000110 -
b11000110 6
b100001100000000000000000000000000000011 7
b10001111111111111111110010111000000000000000000000000000000010 *
b100011111111111111111100101110 !
b100011111111111111111100101110 &
b100011111111111111111100101110 /
b100011111111111111111001101000 )
b100011111111111111111001101000 .
b100011111111111111111001101000 2
b1001010111111111111110011000100000000000000000000000000000010 3
1"
#6800
0"
#6850
b100101011111111111111100101011 1
b1000101 5
b100101011111111111111001100010 )
b100101011111111111111001100010 .
b100101011111111111111001100010 2
b10001111111111111111110010111000000000000000000000000000000010 3
b10010101111111111111110010101100000000000000000000000000000010 *
b100101011111111111111100101011 !
b100101011111111111111100101011 &
b100101011111111111111100101011 /
b11001001 '
b11001001 -
b11001001 6
b100010000000000000000000000000000000011 7
b100010100000000000000000000000000000011 (
b1000101 $
b1000101 %
1"
#6900
0"
#6950
b1000110 5
b1000111111111111111111100101000 1
b100011000000000000000000000000000000011 (
b1000110 $
b1000110 %
b11001100 '
b11001100 -
b11001100 6
b100010100000000000000000000000000000011 7
b100011111111111111111110010100000000000000000000000000000000010 *
b1000111111111111111111100101000 !
b1000111111111111111111100101000 &
b1000111111111111111111100101000 /
b1000111111111111111111001011100 )
b1000111111111111111111001011100 .
b1000111111111111111111001011100 2
b10010101111111111111110010101100000000000000000000000000000010 3
1"
#7000
0"
#7050
b1001010111111111111111100100101 1
b1000111 5
b1001010111111111111111001010110 )
b1001010111111111111111001010110 .
b1001010111111111111111001010110 2
b100011111111111111111110010100000000000000000000000000000000010 3
b100101011111111111111110010010100000000000000000000000000000010 *
b1001010111111111111111100100101 !
b1001010111111111111111100100101 &
b1001010111111111111111100100101 /
b11001111 '
b11001111 -
b11001111 6
b100011000000000000000000000000000000011 7
b100011100000000000000000000000000000011 (
b1000111 $
b1000111 %
1"
#7100
0"
#7150
b1001000 5
b10001111111111111111111100100010 1
b100100000000000000000000000000000000011 (
b1001000 $
b1001000 %
b11010010 '
b11010010 -
b11010010 6
b100011100000000000000000000000000000011 7
b1000111111111111111111110010001000000000000000000000000000000010 *
b10001111111111111111111100100010 !
b10001111111111111111111100100010 &
b10001111111111111111111100100010 /
b10001111111111111111111001010000 )
b10001111111111111111111001010000 .
b10001111111111111111111001010000 2
b100101011111111111111110010010100000000000000000000000000000010 3
1"
#7200
0"
#7250
b10010101111111111111111100011111 1
b1001001 5
b10010101111111111111111001001010 )
b10010101111111111111111001001010 .
b10010101111111111111111001001010 2
b1000111111111111111111110010001000000000000000000000000000000010 3
b1001010111111111111111110001111100000000000000000000000000000010 *
b10010101111111111111111100011111 !
b10010101111111111111111100011111 &
b10010101111111111111111100011111 /
b11010101 '
b11010101 -
b11010101 6
b100100000000000000000000000000000000011 7
b100100100000000000000000000000000000011 (
b1001001 $
b1001001 %
1"
#7300
0"
#7350
b1001010 5
b11111111111111111111100011100 1
b100101000000000000000000000000000000011 (
b1001010 $
b1001010 %
b11011000 '
b11011000 -
b11011000 6
b100100100000000000000000000000000000011 7
b1111111111111111111110001110000000000000000000000000000000010 *
b11111111111111111111100011100 !
b11111111111111111111100011100 &
b11111111111111111111100011100 /
b11111111111111111111001000100 )
b11111111111111111111001000100 .
b11111111111111111111001000100 2
b1001010111111111111111110001111100000000000000000000000000000010 3
1"
#7400
0"
