tasks/01_01_filter/code/mult_2t.v
// Умножитель с задержкой 2 такта
module mult_2t (
    input clk,
    input reset,
    input enable,
    input [31:0] multipliable_1,
    input [31:0] multipliable_2,
    output reg [31:0] mult_result = 32'b0
);
    reg [31:0] mult_delay = 32'b0;

    always @(posedge clk or negedge reset) begin
        // проверяем reset
        if (!reset) begin
            mult_delay <= 32'b0;
            mult_result <= 32'b0;
        end else begin
            // проверяем сигнал разрешения
            if (enable) begin
                // первый такт
                mult_delay <= multipliable_1 * multipliable_2;
            end                
            
            // второй такт
            mult_result <= mult_delay;
        end
    end
endmodule // mult_2t

tasks/01_01_filter/testbenches/mult_2t_tb.v
// задаём временную шкалу
`timescale 10ps / 1ps

module mult_2t_test;
    // дамп файла для GtkWave
    initial begin
        $dumpfile("mult_2t_simulation.vcd");
        $dumpvars(0, mult_2t_test);
    end
    
    // объявляем и задаём входные сигналы
    reg clk = 0;
    always #5 clk = !clk;
    
    reg [31:0] x = 32'b0;

    always @(posedge clk) begin
       x <= x + 1;
    end

    reg reset = 1'b1;
    initial begin
        #91 reset <= 1'b0;
    end
    
    reg enable = 1'b1;
    initial begin
        #50 enable <= 1'b0;
        #20 enable <= 1'b1;
    end
    // подключаем и задаём выходные сигналы
    wire [31:0] out;

    // подключаем модуль
    mult_2t MULT(
        .clk(clk), 
        .reset(reset),
        .enable(enable),
        .multipliable_1(x),
        .multipliable_2(x),
        .mult_result(out)
    );

    // отслеживание сигналов
    initial begin
        $monitor("At time %t, reset : %b, en : %b, in : %b, out %b", $time, reset, enable, x, out);
        #200 $finish;
    end

endmodule // mult_2t_test

tasks/01_01_filter/simulation/files/mult_2t_simulation.vcd
$date
	Mon Nov 10 18:25:16 2025
$end
$version
	Icarus Verilog
$end
$timescale
	1ps
$end
$scope module mult_2t_test $end
$var wire 32 ! out [31:0] $end
$var reg 1 " clk $end
$var reg 1 # enable $end
$var reg 1 $ reset $end
$var reg 32 % x [31:0] $end
$scope module MULT $end
$var wire 1 " clk $end
$var wire 1 # enable $end
$var wire 32 & multipliable_1 [31:0] $end
$var wire 32 ' multipliable_2 [31:0] $end
$var wire 1 $ reset $end
$var reg 32 ( mult_delay [31:0] $end
$var reg 32 ) mult_result [31:0] $end
$upscope $end
$upscope $end
$enddefinitions $end
$comment Show the parameter values. $end
$dumpall
$end
#0
$dumpvars
b0 )
b0 (
b0 '
b0 &
b0 %
1$
1#
0"
b0 !
$end
#50
b1 %
b1 &
b1 '
1"
#100
0"
#150
b1 (
b10 %
b10 &
b10 '
1"
#200
0"
#250
b1 !
b1 )
b100 (
b11 %
b11 &
b11 '
1"
#300
0"
#350
b100 !
b100 )
b1001 (
b100 %
b100 &
b100 '
1"
#400
0"
#450
b1001 !
b1001 )
b10000 (
b101 %
b101 &
b101 '
1"
#500
0#
0"
#550
b10000 !
b10000 )
b110 %
b110 &
b110 '
1"
#600
0"
#650
b111 %
b111 &
b111 '
1"
#700
1#
0"
#750
b110001 (
b1000 %
b1000 &
b1000 '
1"
#800
0"
#850
b110001 !
b110001 )
b1000000 (
b1001 %
b1001 &
b1001 '
1"
#900
0"
#910
b0 !
b0 )
b0 (
0$
#950
b1010 %
b1010 &
b1010 '
1"
#1000
0"
#1050
b1011 %
b1011 &
b1011 '
1"
#1100
0"
#1150
b1100 %
b1100 &
b1100 '
1"
#1200
0"
#1250
b1101 %
b1101 &
b1101 '
1"
#1300
0"
#1350
b1110 %
b1110 &
b1110 '
1"
#1400
0"
#1450
b1111 %
b1111 &
b1111 '
1"
#1500
0"
#1550
b10000 %
b10000 &
b10000 '
1"
#1600
0"
#1650
b10001 %
b10001 &
b10001 '
1"
#1700
0"
#1750
b10010 %
b10010 &
b10010 '
1"
#1800
0"
#1850
b10011 %
b10011 &
b10011 '
1"
#1900
0"
#1950
b10100 %
b10100 &
b10100 '
1"
