tasks/task_02_SPI/code/SPI_slave.v
module SPI_slave(
    input cs,
    input sck,
    input mosi,
    output reg [7:0] cmd = 8'b0,
    output reg [1:0][7:0] addr = 16'b0,
    output reg [3:0][7:0] data = 32'b0
);

// объявляем и задаём служебные регистры
reg [6:0][7:0] memory = 64'b0;
reg [2:0] counter_byte = 3'b0;
reg [2:0] counter_bit = 3'b0;
reg [7:0] temp_byte = 9'b0;
reg rf; // флаг наличия результата

always @(posedge sck) begin 
    // проверяем CS 
    if (!cs) begin
        // записываем значение
        temp_byte[counter_bit] = mosi;

        // увеличиваем счётчики
        if ((counter_byte == 3'b110) && (counter_bit == 3'b111)) begin
            memory[counter_byte] <= temp_byte;
            counter_byte <= 3'b0;
            counter_bit <= 3'b0;
            rf <= 1'b1;
        end else if (counter_bit == 3'b111) begin
            memory[counter_byte] <= temp_byte;
            counter_byte <= counter_byte +1;
            counter_bit <= 3'b0;
        end else counter_bit <= counter_bit + 1;
    end
end

//при установке флага выдаём на выход память
always @(posedge rf) begin
    cmd <= memory[0];
    addr <= memory[2:1];
    data <= memory [6:3];
    rf <= 1'b0;
end

endmodule // SPI_Slave

tasks/task_02_SPI/code/SPI_master.v
module SPI_master(
    input clk, 
    input reset,
    input en_transit,
    input [7:0] data,
    output reg sck = 1'b1,
    output reg mosi = 1'b1,
    output reg cs = 1'b1
);

// объявляем и задаём слкжебные регистры
reg [7:0] memory = 8'b0;
reg flag_transit = 1'b0;
reg flag_sck = 1'b0;
reg [2:0] counter_bit = 3'b111;

always @(posedge clk or negedge reset) begin
    //проверяем reset
    if (!reset) begin
        memory <= 8'b0;
        flag_transit <=1'b0;
        counter_bit <= 3'b111;
        sck <= 1'b1;
        mosi <= 1'b1;
        cs <= 1'b1;
    end else begin
        // если пришёл сигнал разрешения передачи - устанавливаем флаг
        if ((en_transit) && (!flag_transit)) begin 
            flag_transit <= 1'b1;
            cs <= 1'b0;
            sck <= 1'b0;
            mosi <= 1'b0;
            memory <= data;
            flag_sck <= 1'b1;
        end else begin
            if ((flag_transit) && (!flag_sck)) begin
                flag_transit <= 1'b0;
                sck <= 1'b0;
            end
            // если установлен флаг, начинаем тактировать sck
            if (flag_sck) begin
                sck <= ~sck;
                // начинаем передачу
                if (!sck) begin
                    mosi <= memory[counter_bit];

                    //проверяем счётчик бита
                    if (counter_bit == 3'b0) begin
                        flag_sck <= 1'b0;
                        counter_bit <= 3'b111;
                    end else counter_bit <= counter_bit - 1;
                end
            end  
            if (!flag_transit) begin
                sck <= 1'b1;
                mosi <=1'b1;
                cs <= 1'b1;
            end
        end
    end
end

endmodule // SPI_master

tasks/01_02_SPI/testbenches/SPI_slave_tb.v
//подключаем модуль master
`include "SPI_master.v"

// задаём временную шкалу
`timescale 10 ps/ 1 ps

module SPI_slave_test;

//dump для GTKWAVE
initial begin
    $dumpfile("SPI_slave_simulation.vcd");
    $dumpvars(0, SPI_slave_test);
end

//объявляем и задаём входные сигналы
reg clk = 1'b0;
always #5 clk <= ~clk;

reg reset = 1'b1;

reg [7:0] data = 8'b10101010;
initial begin 
    #1200 data = 8'b10000001;
end

reg en = 1'b0;
initial begin
    #19 en = 1'b1;
    #1150 en = 1'b0;
    #150 en = 1'b1;
    #30 en = 1'b0;
    #500 en = 1'b1;
end

// объявляем связывающие сигналы
wire sck, cs, mosi;

// объявляем выходные сигналы
wire [7:0] cmd;
wire [1:0][7:0] addr;
wire [3:0][7:0] data_out;
wire rf;

//подключаем модуль master
SPI_master SPI_MASTER(
    .clk(clk),
    .reset(reset),
    .en_transit(en),
    .data(data),
    .sck(sck),
    .mosi(mosi),
    .cs(cs)
);

//подключаем модул slave 
SPI_slave SPI_Slave(
    .cs(cs),
    .sck(sck),
    .mosi(mosi),
    .cmd(cmd),
    .addr(addr),
    .data(data_out)
);

//включаем мониторнг сигналов
initial  begin
    $monitor("At time %t, cs - %b, sck - %b, mosi - %b, outputs - %b, %b, %b, %b", $time, en, cs, sck, mosi, cmd, addr, data_out, rf);
    #5000 $finish;
end

endmodule // SPI_master_test

tasks/task_02_SPI/simulation/files/SPI_slave_simulation.vcd
$date
	Tue Nov 11 17:19:14 2025
$end
$version
	Icarus Verilog
$end
$timescale
	1ps
$end
$scope module SPI_slave_test $end
$var wire 1 ! rf $end
$var wire 1 " sck $end
$var wire 1 # mosi $end
$var wire 32 $ data_out [31:0] $end
$var wire 1 % cs $end
$var wire 8 & cmd [7:0] $end
$var wire 16 ' addr [15:0] $end
$var reg 1 ( clk $end
$var reg 8 ) data [7:0] $end
$var reg 1 * en $end
$var reg 1 + reset $end
$scope module SPI_MASTER $end
$var wire 1 ( clk $end
$var wire 8 , data [7:0] $end
$var wire 1 * en_transit $end
$var wire 1 + reset $end
$var reg 3 - counter_bit [2:0] $end
$var reg 1 % cs $end
$var reg 1 . flag_sck $end
$var reg 1 / flag_transit $end
$var reg 8 0 memory [7:0] $end
$var reg 1 # mosi $end
$var reg 1 " sck $end
$upscope $end
$scope module SPI_Slave $end
$var wire 1 % cs $end
$var wire 1 # mosi $end
$var wire 1 " sck $end
$var reg 16 1 addr [15:0] $end
$var reg 8 2 cmd [7:0] $end
$var reg 3 3 counter_bit [2:0] $end
$var reg 3 4 counter_byte [2:0] $end
$var reg 32 5 data [31:0] $end
$var reg 56 6 memory [55:0] $end
$var reg 1 7 rf $end
$var reg 8 8 temp_byte [7:0] $end
$upscope $end
$upscope $end
$enddefinitions $end
$comment Show the parameter values. $end
$dumpall
$end
#0
$dumpvars
b0 8
x7
b0 6
b0 5
b0 4
b0 3
b0 2
b0 1
b0 0
0/
0.
b111 -
b10101010 ,
1+
0*
b10101010 )
0(
b0 '
b0 &
1%
b0 $
1#
1"
z!
$end
#50
1(
#100
0(
#150
1(
#190
1*
#200
0(
#250
1.
b10101010 0
0#
0"
0%
1/
1(
#300
0(
#350
b1 3
b1 8
b110 -
1#
1"
1(
#400
0(
#450
0"
1(
#500
0(
#550
b10 3
b101 -
0#
1"
1(
#600
0(
#650
0"
1(
#700
0(
#750
b11 3
b101 8
b100 -
1#
1"
1(
#800
0(
#850
0"
1(
#900
0(
#950
b100 3
b11 -
0#
1"
1(
#1000
0(
#1050
0"
1(
#1100
0(
#1150
b101 3
b10101 8
b10 -
1#
1"
1(
#1200
0(
#1250
0"
1(
#1300
0(
#1350
b110 3
b1 -
0#
1"
1(
#1400
0(
#1450
0"
1(
#1500
0(
#1550
b111 3
b1010101 8
b0 -
1#
1"
1(
#1600
0(
#1650
0"
1(
#1700
0(
#1750
b0 3
b1 4
b1010101 6
b111 -
0.
0#
1"
1(
#1800
0(
#1850
0"
0/
1(
#1900
0(
#1950
1.
1/
1(
#2000
0(
#2050
b1 3
b110 -
1#
1"
1(
#2100
0(
#2150
0"
1(
#2200
0(
#2250
b10 3
b101 -
0#
1"
1(
#2300
0(
#2350
0"
1(
#2400
0(
#2450
b11 3
b100 -
1#
1"
1(
#2500
0(
#2550
0"
1(
#2600
0(
#2650
b100 3
b11 -
0#
1"
1(
#2700
0(
#2750
0"
1(
#2800
0(
#2850
b101 3
b10 -
1#
1"
1(
#2900
0(
#2950
0"
1(
#3000
0(
#3050
b110 3
b1 -
0#
1"
1(
#3100
0(
#3150
0"
1(
#3200
0(
#3250
b111 3
b0 -
1#
1"
1(
#3300
0(
#3350
0"
1(
#3400
0(
#3450
b0 3
b10 4
b101010101010101 6
b111 -
0.
0#
1"
1(
#3500
0(
#3550
0"
0/
1(
#3600
0(
#3650
1.
1/
1(
#3700
0(
#3750
b1 3
b110 -
1#
1"
1(
#3800
0(
#3850
0"
1(
#3900
0(
#3950
b10 3
b101 -
0#
1"
1(
#4000
0(
#4050
0"
1(
#4100
0(
#4150
b11 3
b100 -
1#
1"
1(
#4200
0(
#4250
0"
1(
#4300
0(
#4350
b100 3
b11 -
0#
1"
1(
#4400
0(
#4450
0"
1(
#4500
0(
#4550
b101 3
b10 -
1#
1"
1(
#4600
0(
#4650
0"
1(
#4700
0(
#4750
b110 3
b1 -
0#
1"
1(
#4800
0(
#4850
0"
1(
#4900
0(
#4950
b111 3
b0 -
1#
1"
1(
#5000
0(
#5050
0"
1(
#5100
0(
#5150
b0 3
b11 4
b10101010101010101010101 6
b111 -
0.
0#
1"
1(
#5200
0(
#5250
0"
0/
1(
#5300
0(
#5350
1.
1/
1(
#5400
0(
#5450
b1 3
b110 -
1#
1"
1(
#5500
0(
#5550
0"
1(
#5600
0(
#5650
b10 3
b101 -
0#
1"
1(
#5700
0(
#5750
0"
1(
#5800
0(
#5850
b11 3
b100 -
1#
1"
1(
#5900
0(
#5950
0"
1(
#6000
0(
#6050
b100 3
b11 -
0#
1"
1(
#6100
0(
#6150
0"
1(
#6200
0(
#6250
b101 3
b10 -
1#
1"
1(
#6300
0(
#6350
0"
1(
#6400
0(
#6450
b110 3
b1 -
0#
1"
1(
#6500
0(
#6550
0"
1(
#6600
0(
#6650
b111 3
b0 -
1#
1"
1(
#6700
0(
#6750
0"
1(
#6800
0(
#6850
b0 3
b100 4
b1010101010101010101010101010101 6
b111 -
0.
0#
1"
1(
#6900
0(
#6950
0"
0/
1(
#7000
0(
#7050
1.
1/
1(
#7100
0(
#7150
b1 3
b110 -
1#
1"
1(
#7200
0(
#7250
0"
1(
#7300
0(
#7350
b10 3
b101 -
0#
1"
1(
#7400
0(
#7450
0"
1(
#7500
0(
#7550
b11 3
b100 -
1#
1"
1(
#7600
0(
#7650
0"
1(
#7700
0(
#7750
b100 3
b11 -
0#
1"
1(
#7800
0(
#7850
0"
1(
#7900
0(
#7950
b101 3
b10 -
1#
1"
1(
#8000
0(
#8050
0"
1(
#8100
0(
#8150
b110 3
b1 -
0#
1"
1(
#8200
0(
#8250
0"
1(
#8300
0(
#8350
b111 3
b0 -
1#
1"
1(
#8400
0(
#8450
0"
1(
#8500
0(
#8550
b0 3
b101 4
b101010101010101010101010101010101010101 6
b111 -
0.
0#
1"
1(
#8600
0(
#8650
0"
0/
1(
#8700
0(
#8750
1.
1/
1(
#8800
0(
#8850
b1 3
b110 -
1#
1"
1(
#8900
0(
#8950
0"
1(
#9000
0(
#9050
b10 3
b101 -
0#
1"
1(
#9100
0(
#9150
0"
1(
#9200
0(
#9250
b11 3
b100 -
1#
1"
1(
#9300
0(
#9350
0"
1(
#9400
0(
#9450
b100 3
b11 -
0#
1"
1(
#9500
0(
#9550
0"
1(
#9600
0(
#9650
b101 3
b10 -
1#
1"
1(
#9700
0(
#9750
0"
1(
#9800
0(
#9850
b110 3
b1 -
0#
1"
1(
#9900
0(
#9950
0"
1(
#10000
0(
#10050
b111 3
b0 -
1#
1"
1(
#10100
0(
#10150
0"
1(
#10200
0(
#10250
b0 3
b110 4
b10101010101010101010101010101010101010101010101 6
b111 -
0.
0#
1"
1(
#10300
0(
#10350
0"
0/
1(
#10400
0(
#10450
1.
1/
1(
#10500
0(
#10550
b1 3
b110 -
1#
1"
1(
#10600
0(
#10650
0"
1(
#10700
0(
#10750
b10 3
b101 -
0#
1"
1(
#10800
0(
#10850
0"
1(
#10900
0(
#10950
b11 3
b100 -
1#
1"
1(
#11000
0(
#11050
0"
1(
#11100
0(
#11150
b100 3
b11 -
0#
1"
1(
#11200
0(
#11250
0"
1(
#11300
0(
#11350
b101 3
b10 -
1#
1"
1(
#11400
0(
#11450
0"
1(
#11500
0(
#11550
b110 3
b1 -
0#
1"
1(
#11600
0(
#11650
0"
1(
#11690
0*
#11700
0(
#11750
b111 3
b0 -
1#
1"
1(
#11800
0(
#11850
0"
1(
#11900
0(
#11950
b1010101010101010101010101010101 $
b1010101010101010101010101010101 5
b101010101010101 '
b101010101010101 1
b1010101 &
b1010101 2
07
b0 3
b0 4
b1010101010101010101010101010101010101010101010101010101 6
b111 -
0.
0#
1"
1(
#12000
0(
b10000001 )
b10000001 ,
#12050
0"
0/
1(
#12100
0(
#12150
1%
1#
1"
1(
#12200
0(
#12250
1(
#12300
0(
#12350
1(
#12400
0(
#12450
1(
#12500
0(
#12550
1(
#12600
0(
#12650
1(
#12700
0(
#12750
1(
#12800
0(
#12850
1(
#12900
0(
#12950
1(
#13000
0(
#13050
1(
#13100
0(
#13150
1(
#13190
1*
#13200
0(
#13250
1.
b10000001 0
0#
0"
0%
1/
1(
#13300
0(
#13350
b1 3
b110 -
1#
1"
1(
#13400
0(
#13450
0"
1(
#13490
0*
#13500
0(
#13550
b10 3
b101 -
0#
1"
1(
#13600
0(
#13650
0"
1(
#13700
0(
#13750
b11 3
b1010001 8
b100 -
1"
1(
#13800
0(
#13850
0"
1(
#13900
0(
#13950
b100 3
b11 -
1"
1(
#14000
0(
#14050
0"
1(
#14100
0(
#14150
b101 3
b1000001 8
b10 -
1"
1(
#14200
0(
#14250
0"
1(
#14300
0(
#14350
b110 3
b1 -
1"
1(
#14400
0(
#14450
0"
1(
#14500
0(
#14550
b111 3
b1 8
b0 -
1"
1(
#14600
0(
#14650
0"
1(
#14700
0(
#14750
b0 3
b1 4
b1010101010101010101010101010101010101010101010110000001 6
b10000001 8
b111 -
0.
1#
1"
1(
#14800
0(
#14850
0"
0/
1(
#14900
0(
#14950
1%
1"
1(
