tasks/01_03_LU_cache/code/NOR.v
module NOR #(
    parameter WIDTH = 8
)(
    input [WIDTH - 1:0] in,
    output out 
);

assign out = ~(|in) ? 1 : 0;

endmodule // NOR

tasks/task_03_LU_cache/code/XOR.v
module XOR #(
    parameter WIDTH = 8
)
(
    input [WIDTH - 1:0] in_1,
    input [WIDTH - 1:0] in_2,
    output [WIDTH - 1:0] out
);

assign out = in_1 ^ in_2;

endmodule // XOR

tasks/task_03_LU_cache/code/memory_cell.v
`include "XOR.v"
`include "NOR.v"

module memory_cell #(
    parameter CELL_SIZE = 8,
    parameter CELL_ADDR = 0,
    parameter ADDR_SIZE = 3
)(
    input clk,
    input reset,
    input wen,
    input priority_wen,
    input [CELL_SIZE - 1:0] input_data,
    input [CELL_SIZE - 1:0] check_data,
    input [ADDR_SIZE - 1:0] input_addr,
    output eq,
    output [ADDR_SIZE - 1:0] output_addr,
    output reg [CELL_SIZE - 1:0] output_data = 0
);

//объявляем и сохраняем адрес ячейки
reg [ADDR_SIZE - 1:0] cell_addr = CELL_ADDR;

//объявляем и задаём вспомагательные сигналы
wire [CELL_SIZE - 1:0] temp_data;

XOR #(
    .WIDTH(CELL_SIZE)
) DD1 (
    .in_1(check_data),
    .in_2(output_data),
    .out(temp_data)
);

NOR #(
    .WIDTH(CELL_SIZE)
) DD2 (
    .in(temp_data),
    .out(eq)
);

//передача адреса
assign output_addr = eq ? cell_addr : 0;

always @(posedge clk or negedge reset) begin 
    //проверяем reset
    if (!(reset)) output_data <= 0;
    else if (((wen) && (cell_addr <= input_addr)) || priority_wen) output_data <= input_data; 
end

endmodule // memory_cell

tasks/task_03_LU_cache/testbenches/memory_cell_tb.v
// задаём временную шкалу
`timescale 10 ps/ 1 ps

module memory_cell_test;

//dump для GTKWAVE
initial begin
    $dumpfile("memory_cell_simulation.vcd");
    $dumpvars(0, memory_cell_test);
end

//объявляем и задаём входные сигналы
reg clk = 1'b0;
always #5 clk <= ~clk;

reg wen = 1'b0;

reg reset = 1'b1;

reg [7:0] input_data = 8'b1111;
reg [7:0] check_data = 8'b0;
reg [7:0] addr_before = 8'b0;

always @(posedge clk) begin
    wen <= ~wen;
    input_data <= input_data - 1;
    check_data <= check_data + 1;
    addr_before <= addr_before + 1;
end


// объявляем выходные сигналы
wire eq;
wire [7:0] output_data, addr;

//подключаем модуль
memory_cell #(
    .CELL_SIZE(8),
    .CELL_ADDR(4),
    .ADDR_SIZE(8)
) CELL (
    .clk(clk),
    .reset(reset),
    .wen(wen),
    .priority_wen(wen),
    .input_data(input_data),
    .check_data(check_data),
    .input_addr(addr_before),
    .eq(eq),
    .output_addr(addr),
    .output_data(output_data)
);

//включаем мониторнг сигналов
initial  begin
    #5000 $finish;
end

endmodule // memory_cell_test

tasks/01_03_LU_cache/simulation/files/memory_cell_simulation.vcd
$date
	Tue Dec  2 00:00:55 2025
$end
$version
	Icarus Verilog
$end
$timescale
	1ps
$end
$scope module memory_cell_test $end
$var wire 8 ! output_data [7:0] $end
$var wire 1 " eq $end
$var wire 8 # addr [7:0] $end
$var reg 8 $ addr_before [7:0] $end
$var reg 8 % check_data [7:0] $end
$var reg 1 & clk $end
$var reg 8 ' input_data [7:0] $end
$var reg 1 ( reset $end
$var reg 1 ) wen $end
$scope module CELL $end
$var wire 8 * check_data [7:0] $end
$var wire 1 & clk $end
$var wire 8 + input_addr [7:0] $end
$var wire 8 , input_data [7:0] $end
$var wire 1 ) priority_wen $end
$var wire 1 ( reset $end
$var wire 1 ) wen $end
$var wire 8 - temp_data [7:0] $end
$var wire 8 . output_addr [7:0] $end
$var wire 1 " eq $end
$var parameter 32 / ADDR_SIZE $end
$var parameter 32 0 CELL_ADDR $end
$var parameter 32 1 CELL_SIZE $end
$var reg 8 2 cell_addr [7:0] $end
$var reg 8 3 output_data [7:0] $end
$scope module DD1 $end
$var wire 8 4 in_1 [7:0] $end
$var wire 8 5 in_2 [7:0] $end
$var wire 8 6 out [7:0] $end
$var parameter 32 7 WIDTH $end
$upscope $end
$scope module DD2 $end
$var wire 8 8 in [7:0] $end
$var wire 1 " out $end
$var parameter 32 9 WIDTH $end
$upscope $end
$upscope $end
$upscope $end
$enddefinitions $end
$comment Show the parameter values. $end
$dumpall
b1000 9
b1000 7
b1000 1
b100 0
b1000 /
$end
#0
$dumpvars
b0 8
b0 6
b0 5
b0 4
b0 3
b100 2
b100 .
b0 -
b1111 ,
b0 +
b0 *
0)
1(
b1111 '
0&
b0 %
b0 $
b100 #
1"
b0 !
$end
#50
b0 #
b0 .
0"
b1 -
b1 6
b1 8
b1 $
b1 +
b1 %
b1 *
b1 4
b1110 '
b1110 ,
1)
1&
#100
0&
#150
b1100 -
b1100 6
b1100 8
b1110 !
b1110 3
b1110 5
b10 $
b10 +
b10 %
b10 *
b10 4
b1101 '
b1101 ,
0)
1&
#200
0&
#250
b1101 -
b1101 6
b1101 8
b11 $
b11 +
b11 %
b11 *
b11 4
b1100 '
b1100 ,
1)
1&
#300
0&
#350
b1000 -
b1000 6
b1000 8
b1100 !
b1100 3
b1100 5
b100 $
b100 +
b100 %
b100 *
b100 4
b1011 '
b1011 ,
0)
1&
#400
0&
#450
b1001 -
b1001 6
b1001 8
b101 $
b101 +
b101 %
b101 *
b101 4
b1010 '
b1010 ,
1)
1&
#500
0&
#550
b1100 -
b1100 6
b1100 8
b1010 !
b1010 3
b1010 5
b110 $
b110 +
b110 %
b110 *
b110 4
b1001 '
b1001 ,
0)
1&
#600
0&
#650
b1101 -
b1101 6
b1101 8
b111 $
b111 +
b111 %
b111 *
b111 4
b1000 '
b1000 ,
1)
1&
#700
0&
#750
b100 #
b100 .
1"
b0 -
b0 6
b0 8
b1000 !
b1000 3
b1000 5
b1000 $
b1000 +
b1000 %
b1000 *
b1000 4
b111 '
b111 ,
0)
1&
#800
0&
#850
b0 #
b0 .
0"
b1 -
b1 6
b1 8
b1001 $
b1001 +
b1001 %
b1001 *
b1001 4
b110 '
b110 ,
1)
1&
#900
0&
#950
b1100 -
b1100 6
b1100 8
b110 !
b110 3
b110 5
b1010 $
b1010 +
b1010 %
b1010 *
b1010 4
b101 '
b101 ,
0)
1&
#1000
0&
#1050
b1101 -
b1101 6
b1101 8
b1011 $
b1011 +
b1011 %
b1011 *
b1011 4
b100 '
b100 ,
1)
1&
#1100
0&
#1150
b1000 -
b1000 6
b1000 8
b100 !
b100 3
b100 5
b1100 $
b1100 +
b1100 %
b1100 *
b1100 4
b11 '
b11 ,
0)
1&
#1200
0&
#1250
b1001 -
b1001 6
b1001 8
b1101 $
b1101 +
b1101 %
b1101 *
b1101 4
b10 '
b10 ,
1)
1&
#1300
0&
#1350
b1100 -
b1100 6
b1100 8
b10 !
b10 3
b10 5
b1110 $
b1110 +
b1110 %
b1110 *
b1110 4
b1 '
b1 ,
0)
1&
#1400
0&
#1450
b1101 -
b1101 6
b1101 8
b1111 $
b1111 +
b1111 %
b1111 *
b1111 4
b0 '
b0 ,
1)
1&
#1500
0&
#1550
b10000 -
b10000 6
b10000 8
b0 !
b0 3
b0 5
b10000 $
b10000 +
b10000 %
b10000 *
b10000 4
b11111111 '
b11111111 ,
0)
1&
#1600
0&
#1650
b10001 -
b10001 6
b10001 8
b10001 $
b10001 +
b10001 %
b10001 *
b10001 4
b11111110 '
b11111110 ,
1)
1&
#1700
0&
#1750
b11101100 -
b11101100 6
b11101100 8
b11111110 !
b11111110 3
b11111110 5
b10010 $
b10010 +
b10010 %
b10010 *
b10010 4
b11111101 '
b11111101 ,
0)
1&
#1800
0&
#1850
b11101101 -
b11101101 6
b11101101 8
b10011 $
b10011 +
b10011 %
b10011 *
b10011 4
b11111100 '
b11111100 ,
1)
1&
#1900
0&
#1950
b11101000 -
b11101000 6
b11101000 8
b11111100 !
b11111100 3
b11111100 5
b10100 $
b10100 +
b10100 %
b10100 *
b10100 4
b11111011 '
b11111011 ,
0)
1&
#2000
0&
#2050
b11101001 -
b11101001 6
b11101001 8
b10101 $
b10101 +
b10101 %
b10101 *
b10101 4
b11111010 '
b11111010 ,
1)
1&
#2100
0&
#2150
b11101100 -
b11101100 6
b11101100 8
b11111010 !
b11111010 3
b11111010 5
b10110 $
b10110 +
b10110 %
b10110 *
b10110 4
b11111001 '
b11111001 ,
0)
1&
#2200
0&
#2250
b11101101 -
b11101101 6
b11101101 8
b10111 $
b10111 +
b10111 %
b10111 *
b10111 4
b11111000 '
b11111000 ,
1)
1&
#2300
0&
#2350
b11100000 -
b11100000 6
b11100000 8
b11111000 !
b11111000 3
b11111000 5
b11000 $
b11000 +
b11000 %
b11000 *
b11000 4
b11110111 '
b11110111 ,
0)
1&
#2400
0&
#2450
b11100001 -
b11100001 6
b11100001 8
b11001 $
b11001 +
b11001 %
b11001 *
b11001 4
b11110110 '
b11110110 ,
1)
1&
#2500
0&
#2550
b11101100 -
b11101100 6
b11101100 8
b11110110 !
b11110110 3
b11110110 5
b11010 $
b11010 +
b11010 %
b11010 *
b11010 4
b11110101 '
b11110101 ,
0)
1&
#2600
0&
#2650
b11101101 -
b11101101 6
b11101101 8
b11011 $
b11011 +
b11011 %
b11011 *
b11011 4
b11110100 '
b11110100 ,
1)
1&
#2700
0&
#2750
b11101000 -
b11101000 6
b11101000 8
b11110100 !
b11110100 3
b11110100 5
b11100 $
b11100 +
b11100 %
b11100 *
b11100 4
b11110011 '
b11110011 ,
0)
1&
#2800
0&
#2850
b11101001 -
b11101001 6
b11101001 8
b11101 $
b11101 +
b11101 %
b11101 *
b11101 4
b11110010 '
b11110010 ,
1)
1&
#2900
0&
#2950
b11101100 -
b11101100 6
b11101100 8
b11110010 !
b11110010 3
b11110010 5
b11110 $
b11110 +
b11110 %
b11110 *
b11110 4
b11110001 '
b11110001 ,
0)
1&
#3000
0&
#3050
b11101101 -
b11101101 6
b11101101 8
b11111 $
b11111 +
b11111 %
b11111 *
b11111 4
b11110000 '
b11110000 ,
1)
1&
#3100
0&
#3150
b11010000 -
b11010000 6
b11010000 8
b11110000 !
b11110000 3
b11110000 5
b100000 $
b100000 +
b100000 %
b100000 *
b100000 4
b11101111 '
b11101111 ,
0)
1&
#3200
0&
#3250
b11010001 -
b11010001 6
b11010001 8
b100001 $
b100001 +
b100001 %
b100001 *
b100001 4
b11101110 '
b11101110 ,
1)
1&
#3300
0&
#3350
b11001100 -
b11001100 6
b11001100 8
b11101110 !
b11101110 3
b11101110 5
b100010 $
b100010 +
b100010 %
b100010 *
b100010 4
b11101101 '
b11101101 ,
0)
1&
#3400
0&
#3450
b11001101 -
b11001101 6
b11001101 8
b100011 $
b100011 +
b100011 %
b100011 *
b100011 4
b11101100 '
b11101100 ,
1)
1&
#3500
0&
#3550
b11001000 -
b11001000 6
b11001000 8
b11101100 !
b11101100 3
b11101100 5
b100100 $
b100100 +
b100100 %
b100100 *
b100100 4
b11101011 '
b11101011 ,
0)
1&
#3600
0&
#3650
b11001001 -
b11001001 6
b11001001 8
b100101 $
b100101 +
b100101 %
b100101 *
b100101 4
b11101010 '
b11101010 ,
1)
1&
#3700
0&
#3750
b11001100 -
b11001100 6
b11001100 8
b11101010 !
b11101010 3
b11101010 5
b100110 $
b100110 +
b100110 %
b100110 *
b100110 4
b11101001 '
b11101001 ,
0)
1&
#3800
0&
#3850
b11001101 -
b11001101 6
b11001101 8
b100111 $
b100111 +
b100111 %
b100111 *
b100111 4
b11101000 '
b11101000 ,
1)
1&
#3900
0&
#3950
b11000000 -
b11000000 6
b11000000 8
b11101000 !
b11101000 3
b11101000 5
b101000 $
b101000 +
b101000 %
b101000 *
b101000 4
b11100111 '
b11100111 ,
0)
1&
#4000
0&
#4050
b11000001 -
b11000001 6
b11000001 8
b101001 $
b101001 +
b101001 %
b101001 *
b101001 4
b11100110 '
b11100110 ,
1)
1&
#4100
0&
#4150
b11001100 -
b11001100 6
b11001100 8
b11100110 !
b11100110 3
b11100110 5
b101010 $
b101010 +
b101010 %
b101010 *
b101010 4
b11100101 '
b11100101 ,
0)
1&
#4200
0&
#4250
b11001101 -
b11001101 6
b11001101 8
b101011 $
b101011 +
b101011 %
b101011 *
b101011 4
b11100100 '
b11100100 ,
1)
1&
#4300
0&
#4350
b11001000 -
b11001000 6
b11001000 8
b11100100 !
b11100100 3
b11100100 5
b101100 $
b101100 +
b101100 %
b101100 *
b101100 4
b11100011 '
b11100011 ,
0)
1&
#4400
0&
#4450
b11001001 -
b11001001 6
b11001001 8
b101101 $
b101101 +
b101101 %
b101101 *
b101101 4
b11100010 '
b11100010 ,
1)
1&
#4500
0&
#4550
b11001100 -
b11001100 6
b11001100 8
b11100010 !
b11100010 3
b11100010 5
b101110 $
b101110 +
b101110 %
b101110 *
b101110 4
b11100001 '
b11100001 ,
0)
1&
#4600
0&
#4650
b11001101 -
b11001101 6
b11001101 8
b101111 $
b101111 +
b101111 %
b101111 *
b101111 4
b11100000 '
b11100000 ,
1)
1&
#4700
0&
#4750
b11010000 -
b11010000 6
b11010000 8
b11100000 !
b11100000 3
b11100000 5
b110000 $
b110000 +
b110000 %
b110000 *
b110000 4
b11011111 '
b11011111 ,
0)
1&
#4800
0&
#4850
b11010001 -
b11010001 6
b11010001 8
b110001 $
b110001 +
b110001 %
b110001 *
b110001 4
b11011110 '
b11011110 ,
1)
1&
#4900
0&
#4950
b11101100 -
b11101100 6
b11101100 8
b11011110 !
b11011110 3
b11011110 5
b110010 $
b110010 +
b110010 %
b110010 *
b110010 4
b11011101 '
b11011101 ,
0)
1&
#5000
0&
#5050
b11101101 -
b11101101 6
b11101101 8
b110011 $
b110011 +
b110011 %
b110011 *
b110011 4
b11011100 '
b11011100 ,
1)
1&
#5100
0&
#5150
b11101000 -
b11101000 6
b11101000 8
b11011100 !
b11011100 3
b11011100 5
b110100 $
b110100 +
b110100 %
b110100 *
b110100 4
b11011011 '
b11011011 ,
0)
1&
#5200
0&
#5250
b11101001 -
b11101001 6
b11101001 8
b110101 $
b110101 +
b110101 %
b110101 *
b110101 4
b11011010 '
b11011010 ,
1)
1&
#5300
0&
#5350
b11101100 -
b11101100 6
b11101100 8
b11011010 !
b11011010 3
b11011010 5
b110110 $
b110110 +
b110110 %
b110110 *
b110110 4
b11011001 '
b11011001 ,
0)
1&
#5400
0&
#5450
b11101101 -
b11101101 6
b11101101 8
b110111 $
b110111 +
b110111 %
b110111 *
b110111 4
b11011000 '
b11011000 ,
1)
1&
#5500
0&
#5550
b11100000 -
b11100000 6
b11100000 8
b11011000 !
b11011000 3
b11011000 5
b111000 $
b111000 +
b111000 %
b111000 *
b111000 4
b11010111 '
b11010111 ,
0)
1&
#5600
0&
#5650
b11100001 -
b11100001 6
b11100001 8
b111001 $
b111001 +
b111001 %
b111001 *
b111001 4
b11010110 '
b11010110 ,
1)
1&
#5700
0&
#5750
b11101100 -
b11101100 6
b11101100 8
b11010110 !
b11010110 3
b11010110 5
b111010 $
b111010 +
b111010 %
b111010 *
b111010 4
b11010101 '
b11010101 ,
0)
1&
#5800
0&
#5850
b11101101 -
b11101101 6
b11101101 8
b111011 $
b111011 +
b111011 %
b111011 *
b111011 4
b11010100 '
b11010100 ,
1)
1&
#5900
0&
#5950
b11101000 -
b11101000 6
b11101000 8
b11010100 !
b11010100 3
b11010100 5
b111100 $
b111100 +
b111100 %
b111100 *
b111100 4
b11010011 '
b11010011 ,
0)
1&
#6000
0&
#6050
b11101001 -
b11101001 6
b11101001 8
b111101 $
b111101 +
b111101 %
b111101 *
b111101 4
b11010010 '
b11010010 ,
1)
1&
#6100
0&
#6150
b11101100 -
b11101100 6
b11101100 8
b11010010 !
b11010010 3
b11010010 5
b111110 $
b111110 +
b111110 %
b111110 *
b111110 4
b11010001 '
b11010001 ,
0)
1&
#6200
0&
#6250
b11101101 -
b11101101 6
b11101101 8
b111111 $
b111111 +
b111111 %
b111111 *
b111111 4
b11010000 '
b11010000 ,
1)
1&
#6300
0&
#6350
b10010000 -
b10010000 6
b10010000 8
b11010000 !
b11010000 3
b11010000 5
b1000000 $
b1000000 +
b1000000 %
b1000000 *
b1000000 4
b11001111 '
b11001111 ,
0)
1&
#6400
0&
#6450
b10010001 -
b10010001 6
b10010001 8
b1000001 $
b1000001 +
b1000001 %
b1000001 *
b1000001 4
b11001110 '
b11001110 ,
1)
1&
#6500
0&
#6550
b10001100 -
b10001100 6
b10001100 8
b11001110 !
b11001110 3
b11001110 5
b1000010 $
b1000010 +
b1000010 %
b1000010 *
b1000010 4
b11001101 '
b11001101 ,
0)
1&
#6600
0&
#6650
b10001101 -
b10001101 6
b10001101 8
b1000011 $
b1000011 +
b1000011 %
b1000011 *
b1000011 4
b11001100 '
b11001100 ,
1)
1&
#6700
0&
#6750
b10001000 -
b10001000 6
b10001000 8
b11001100 !
b11001100 3
b11001100 5
b1000100 $
b1000100 +
b1000100 %
b1000100 *
b1000100 4
b11001011 '
b11001011 ,
0)
1&
#6800
0&
#6850
b10001001 -
b10001001 6
b10001001 8
b1000101 $
b1000101 +
b1000101 %
b1000101 *
b1000101 4
b11001010 '
b11001010 ,
1)
1&
#6900
0&
#6950
b10001100 -
b10001100 6
b10001100 8
b11001010 !
b11001010 3
b11001010 5
b1000110 $
b1000110 +
b1000110 %
b1000110 *
b1000110 4
b11001001 '
b11001001 ,
0)
1&
#7000
0&
#7050
b10001101 -
b10001101 6
b10001101 8
b1000111 $
b1000111 +
b1000111 %
b1000111 *
b1000111 4
b11001000 '
b11001000 ,
1)
1&
#7100
0&
#7150
b10000000 -
b10000000 6
b10000000 8
b11001000 !
b11001000 3
b11001000 5
b1001000 $
b1001000 +
b1001000 %
b1001000 *
b1001000 4
b11000111 '
b11000111 ,
0)
1&
#7200
0&
#7250
b10000001 -
b10000001 6
b10000001 8
b1001001 $
b1001001 +
b1001001 %
b1001001 *
b1001001 4
b11000110 '
b11000110 ,
1)
1&
#7300
0&
#7350
b10001100 -
b10001100 6
b10001100 8
b11000110 !
b11000110 3
b11000110 5
b1001010 $
b1001010 +
b1001010 %
b1001010 *
b1001010 4
b11000101 '
b11000101 ,
0)
1&
#7400
0&
#7450
b10001101 -
b10001101 6
b10001101 8
b1001011 $
b1001011 +
b1001011 %
b1001011 *
b1001011 4
b11000100 '
b11000100 ,
1)
1&
#7500
0&
#7550
b10001000 -
b10001000 6
b10001000 8
b11000100 !
b11000100 3
b11000100 5
b1001100 $
b1001100 +
b1001100 %
b1001100 *
b1001100 4
b11000011 '
b11000011 ,
0)
1&
#7600
0&
#7650
b10001001 -
b10001001 6
b10001001 8
b1001101 $
b1001101 +
b1001101 %
b1001101 *
b1001101 4
b11000010 '
b11000010 ,
1)
1&
#7700
0&
#7750
b10001100 -
b10001100 6
b10001100 8
b11000010 !
b11000010 3
b11000010 5
b1001110 $
b1001110 +
b1001110 %
b1001110 *
b1001110 4
b11000001 '
b11000001 ,
0)
1&
#7800
0&
#7850
b10001101 -
b10001101 6
b10001101 8
b1001111 $
b1001111 +
b1001111 %
b1001111 *
b1001111 4
b11000000 '
b11000000 ,
1)
1&
#7900
0&
#7950
b10010000 -
b10010000 6
b10010000 8
b11000000 !
b11000000 3
b11000000 5
b1010000 $
b1010000 +
b1010000 %
b1010000 *
b1010000 4
b10111111 '
b10111111 ,
0)
1&
#8000
0&
#8050
b10010001 -
b10010001 6
b10010001 8
b1010001 $
b1010001 +
b1010001 %
b1010001 *
b1010001 4
b10111110 '
b10111110 ,
1)
1&
#8100
0&
#8150
b11101100 -
b11101100 6
b11101100 8
b10111110 !
b10111110 3
b10111110 5
b1010010 $
b1010010 +
b1010010 %
b1010010 *
b1010010 4
b10111101 '
b10111101 ,
0)
1&
#8200
0&
#8250
b11101101 -
b11101101 6
b11101101 8
b1010011 $
b1010011 +
b1010011 %
b1010011 *
b1010011 4
b10111100 '
b10111100 ,
1)
1&
#8300
0&
#8350
b11101000 -
b11101000 6
b11101000 8
b10111100 !
b10111100 3
b10111100 5
b1010100 $
b1010100 +
b1010100 %
b1010100 *
b1010100 4
b10111011 '
b10111011 ,
0)
1&
#8400
0&
#8450
b11101001 -
b11101001 6
b11101001 8
b1010101 $
b1010101 +
b1010101 %
b1010101 *
b1010101 4
b10111010 '
b10111010 ,
1)
1&
#8500
0&
#8550
b11101100 -
b11101100 6
b11101100 8
b10111010 !
b10111010 3
b10111010 5
b1010110 $
b1010110 +
b1010110 %
b1010110 *
b1010110 4
b10111001 '
b10111001 ,
0)
1&
#8600
0&
#8650
b11101101 -
b11101101 6
b11101101 8
b1010111 $
b1010111 +
b1010111 %
b1010111 *
b1010111 4
b10111000 '
b10111000 ,
1)
1&
#8700
0&
#8750
b11100000 -
b11100000 6
b11100000 8
b10111000 !
b10111000 3
b10111000 5
b1011000 $
b1011000 +
b1011000 %
b1011000 *
b1011000 4
b10110111 '
b10110111 ,
0)
1&
#8800
0&
#8850
b11100001 -
b11100001 6
b11100001 8
b1011001 $
b1011001 +
b1011001 %
b1011001 *
b1011001 4
b10110110 '
b10110110 ,
1)
1&
#8900
0&
#8950
b11101100 -
b11101100 6
b11101100 8
b10110110 !
b10110110 3
b10110110 5
b1011010 $
b1011010 +
b1011010 %
b1011010 *
b1011010 4
b10110101 '
b10110101 ,
0)
1&
#9000
0&
#9050
b11101101 -
b11101101 6
b11101101 8
b1011011 $
b1011011 +
b1011011 %
b1011011 *
b1011011 4
b10110100 '
b10110100 ,
1)
1&
#9100
0&
#9150
b11101000 -
b11101000 6
b11101000 8
b10110100 !
b10110100 3
b10110100 5
b1011100 $
b1011100 +
b1011100 %
b1011100 *
b1011100 4
b10110011 '
b10110011 ,
0)
1&
#9200
0&
#9250
b11101001 -
b11101001 6
b11101001 8
b1011101 $
b1011101 +
b1011101 %
b1011101 *
b1011101 4
b10110010 '
b10110010 ,
1)
1&
#9300
0&
#9350
b11101100 -
b11101100 6
b11101100 8
b10110010 !
b10110010 3
b10110010 5
b1011110 $
b1011110 +
b1011110 %
b1011110 *
b1011110 4
b10110001 '
b10110001 ,
0)
1&
#9400
0&
#9450
b11101101 -
b11101101 6
b11101101 8
b1011111 $
b1011111 +
b1011111 %
b1011111 *
b1011111 4
b10110000 '
b10110000 ,
1)
1&
#9500
0&
#9550
b11010000 -
b11010000 6
b11010000 8
b10110000 !
b10110000 3
b10110000 5
b1100000 $
b1100000 +
b1100000 %
b1100000 *
b1100000 4
b10101111 '
b10101111 ,
0)
1&
#9600
0&
#9650
b11010001 -
b11010001 6
b11010001 8
b1100001 $
b1100001 +
b1100001 %
b1100001 *
b1100001 4
b10101110 '
b10101110 ,
1)
1&
#9700
0&
#9750
b11001100 -
b11001100 6
b11001100 8
b10101110 !
b10101110 3
b10101110 5
b1100010 $
b1100010 +
b1100010 %
b1100010 *
b1100010 4
b10101101 '
b10101101 ,
0)
1&
#9800
0&
#9850
b11001101 -
b11001101 6
b11001101 8
b1100011 $
b1100011 +
b1100011 %
b1100011 *
b1100011 4
b10101100 '
b10101100 ,
1)
1&
#9900
0&
#9950
b11001000 -
b11001000 6
b11001000 8
b10101100 !
b10101100 3
b10101100 5
b1100100 $
b1100100 +
b1100100 %
b1100100 *
b1100100 4
b10101011 '
b10101011 ,
0)
1&
#10000
0&
#10050
b11001001 -
b11001001 6
b11001001 8
b1100101 $
b1100101 +
b1100101 %
b1100101 *
b1100101 4
b10101010 '
b10101010 ,
1)
1&
#10100
0&
#10150
b11001100 -
b11001100 6
b11001100 8
b10101010 !
b10101010 3
b10101010 5
b1100110 $
b1100110 +
b1100110 %
b1100110 *
b1100110 4
b10101001 '
b10101001 ,
0)
1&
#10200
0&
#10250
b11001101 -
b11001101 6
b11001101 8
b1100111 $
b1100111 +
b1100111 %
b1100111 *
b1100111 4
b10101000 '
b10101000 ,
1)
1&
#10300
0&
#10350
b11000000 -
b11000000 6
b11000000 8
b10101000 !
b10101000 3
b10101000 5
b1101000 $
b1101000 +
b1101000 %
b1101000 *
b1101000 4
b10100111 '
b10100111 ,
0)
1&
#10400
0&
#10450
b11000001 -
b11000001 6
b11000001 8
b1101001 $
b1101001 +
b1101001 %
b1101001 *
b1101001 4
b10100110 '
b10100110 ,
1)
1&
#10500
0&
#10550
b11001100 -
b11001100 6
b11001100 8
b10100110 !
b10100110 3
b10100110 5
b1101010 $
b1101010 +
b1101010 %
b1101010 *
b1101010 4
b10100101 '
b10100101 ,
0)
1&
#10600
0&
#10650
b11001101 -
b11001101 6
b11001101 8
b1101011 $
b1101011 +
b1101011 %
b1101011 *
b1101011 4
b10100100 '
b10100100 ,
1)
1&
#10700
0&
#10750
b11001000 -
b11001000 6
b11001000 8
b10100100 !
b10100100 3
b10100100 5
b1101100 $
b1101100 +
b1101100 %
b1101100 *
b1101100 4
b10100011 '
b10100011 ,
0)
1&
#10800
0&
#10850
b11001001 -
b11001001 6
b11001001 8
b1101101 $
b1101101 +
b1101101 %
b1101101 *
b1101101 4
b10100010 '
b10100010 ,
1)
1&
#10900
0&
#10950
b11001100 -
b11001100 6
b11001100 8
b10100010 !
b10100010 3
b10100010 5
b1101110 $
b1101110 +
b1101110 %
b1101110 *
b1101110 4
b10100001 '
b10100001 ,
0)
1&
#11000
0&
#11050
b11001101 -
b11001101 6
b11001101 8
b1101111 $
b1101111 +
b1101111 %
b1101111 *
b1101111 4
b10100000 '
b10100000 ,
1)
1&
#11100
0&
#11150
b11010000 -
b11010000 6
b11010000 8
b10100000 !
b10100000 3
b10100000 5
b1110000 $
b1110000 +
b1110000 %
b1110000 *
b1110000 4
b10011111 '
b10011111 ,
0)
1&
#11200
0&
#11250
b11010001 -
b11010001 6
b11010001 8
b1110001 $
b1110001 +
b1110001 %
b1110001 *
b1110001 4
b10011110 '
b10011110 ,
1)
1&
#11300
0&
#11350
b11101100 -
b11101100 6
b11101100 8
b10011110 !
b10011110 3
b10011110 5
b1110010 $
b1110010 +
b1110010 %
b1110010 *
b1110010 4
b10011101 '
b10011101 ,
0)
1&
#11400
0&
#11450
b11101101 -
b11101101 6
b11101101 8
b1110011 $
b1110011 +
b1110011 %
b1110011 *
b1110011 4
b10011100 '
b10011100 ,
1)
1&
#11500
0&
#11550
b11101000 -
b11101000 6
b11101000 8
b10011100 !
b10011100 3
b10011100 5
b1110100 $
b1110100 +
b1110100 %
b1110100 *
b1110100 4
b10011011 '
b10011011 ,
0)
1&
#11600
0&
#11650
b11101001 -
b11101001 6
b11101001 8
b1110101 $
b1110101 +
b1110101 %
b1110101 *
b1110101 4
b10011010 '
b10011010 ,
1)
1&
#11700
0&
#11750
b11101100 -
b11101100 6
b11101100 8
b10011010 !
b10011010 3
b10011010 5
b1110110 $
b1110110 +
b1110110 %
b1110110 *
b1110110 4
b10011001 '
b10011001 ,
0)
1&
#11800
0&
#11850
b11101101 -
b11101101 6
b11101101 8
b1110111 $
b1110111 +
b1110111 %
b1110111 *
b1110111 4
b10011000 '
b10011000 ,
1)
1&
#11900
0&
#11950
b11100000 -
b11100000 6
b11100000 8
b10011000 !
b10011000 3
b10011000 5
b1111000 $
b1111000 +
b1111000 %
b1111000 *
b1111000 4
b10010111 '
b10010111 ,
0)
1&
#12000
0&
#12050
b11100001 -
b11100001 6
b11100001 8
b1111001 $
b1111001 +
b1111001 %
b1111001 *
b1111001 4
b10010110 '
b10010110 ,
1)
1&
#12100
0&
#12150
b11101100 -
b11101100 6
b11101100 8
b10010110 !
b10010110 3
b10010110 5
b1111010 $
b1111010 +
b1111010 %
b1111010 *
b1111010 4
b10010101 '
b10010101 ,
0)
1&
#12200
0&
#12250
b11101101 -
b11101101 6
b11101101 8
b1111011 $
b1111011 +
b1111011 %
b1111011 *
b1111011 4
b10010100 '
b10010100 ,
1)
1&
#12300
0&
#12350
b11101000 -
b11101000 6
b11101000 8
b10010100 !
b10010100 3
b10010100 5
b1111100 $
b1111100 +
b1111100 %
b1111100 *
b1111100 4
b10010011 '
b10010011 ,
0)
1&
#12400
0&
#12450
b11101001 -
b11101001 6
b11101001 8
b1111101 $
b1111101 +
b1111101 %
b1111101 *
b1111101 4
b10010010 '
b10010010 ,
1)
1&
#12500
0&
#12550
b11101100 -
b11101100 6
b11101100 8
b10010010 !
b10010010 3
b10010010 5
b1111110 $
b1111110 +
b1111110 %
b1111110 *
b1111110 4
b10010001 '
b10010001 ,
0)
1&
#12600
0&
#12650
b11101101 -
b11101101 6
b11101101 8
b1111111 $
b1111111 +
b1111111 %
b1111111 *
b1111111 4
b10010000 '
b10010000 ,
1)
1&
#12700
0&
#12750
b10000 -
b10000 6
b10000 8
b10010000 !
b10010000 3
b10010000 5
b10000000 $
b10000000 +
b10000000 %
b10000000 *
b10000000 4
b10001111 '
b10001111 ,
0)
1&
#12800
0&
#12850
b10001 -
b10001 6
b10001 8
b10000001 $
b10000001 +
b10000001 %
b10000001 *
b10000001 4
b10001110 '
b10001110 ,
1)
1&
#12900
0&
#12950
b1100 -
b1100 6
b1100 8
b10001110 !
b10001110 3
b10001110 5
b10000010 $
b10000010 +
b10000010 %
b10000010 *
b10000010 4
b10001101 '
b10001101 ,
0)
1&
#13000
0&
#13050
b1101 -
b1101 6
b1101 8
b10000011 $
b10000011 +
b10000011 %
b10000011 *
b10000011 4
b10001100 '
b10001100 ,
1)
1&
#13100
0&
#13150
b1000 -
b1000 6
b1000 8
b10001100 !
b10001100 3
b10001100 5
b10000100 $
b10000100 +
b10000100 %
b10000100 *
b10000100 4
b10001011 '
b10001011 ,
0)
1&
#13200
0&
#13250
b1001 -
b1001 6
b1001 8
b10000101 $
b10000101 +
b10000101 %
b10000101 *
b10000101 4
b10001010 '
b10001010 ,
1)
1&
#13300
0&
#13350
b1100 -
b1100 6
b1100 8
b10001010 !
b10001010 3
b10001010 5
b10000110 $
b10000110 +
b10000110 %
b10000110 *
b10000110 4
b10001001 '
b10001001 ,
0)
1&
#13400
0&
