fan-examples/Ttrigger/Ttrigger.v
module Ttrigger(T, Q, nQ);
	//объявляем входы
	input T;

	//объявляем выходы
	output Q, nQ;
	reg Q, nQ;
	reg tmp_Q = 1;

	always @(posedge T) begin
		tmp_Q = !tmp_Q;
		Q <= tmp_Q;
		nQ <= !tmp_Q;
	end
endmodule // Ttrigger

fan-examples/Ttrigger/Ttrigger_tb.v
`timescale 1ns / 10ps
module Ttrigger_test;
    // дамп файла для GtkWave
    initial begin
        $dumpfile("Ttrigger_sim.vcd");
        $dumpvars(0, Ttrigger_test);
    end
    
    // входные сигналы
    reg T = 0;
    always #5 T = !T;

    // выходные сигналы
    wire Q, nQ;

    // подключаем модуль
    Ttrigger T1(T, Q, nQ);

    // отслеживание сигналов
    initial begin
        $monitor("At time %t, out1=%b, out2=%b", $time, Q, nQ);
        #500 $finish;
    end
endmodule // Ttrigger_test

fan-examples/Ttrigger/Ttrigger_sim.vcd
$date
	Wed Sep 10 12:02:11 2025
$end
$version
	Icarus Verilog
$end
$timescale
	10ps
$end
$scope module Ttrigger_test $end
$var wire 1 ! nQ $end
$var wire 1 " Q $end
$var reg 1 # T $end
$scope module T1 $end
$var wire 1 # T $end
$var reg 1 " Q $end
$var reg 1 ! nQ $end
$var reg 1 $ tmp_Q $end
$upscope $end
$upscope $end
$enddefinitions $end
$comment Show the parameter values. $end
$dumpall
$end
#0
$dumpvars
1$
0#
x"
x!
$end
#500
1!
0"
0$
1#
#1000
0#
#1500
0!
1"
1$
1#
#2000
0#
#2500
1!
0"
0$
1#
#3000
0#
#3500
0!
1"
1$
1#
#4000
0#
#4500
1!
0"
0$
1#
#5000
0#
#5500
0!
1"
1$
1#
#6000
0#
#6500
1!
0"
0$
1#
#7000
0#
#7500
0!
1"
1$
1#
#8000
0#
#8500
1!
0"
0$
1#
#9000
0#
#9500
0!
1"
1$
1#
#10000
0#
#10500
1!
0"
0$
1#
#11000
0#
#11500
0!
1"
1$
1#
#12000
0#
#12500
1!
0"
0$
1#
#13000
0#
#13500
0!
1"
1$
1#
#14000
0#
#14500
1!
0"
0$
1#
#15000
0#
#15500
0!
1"
1$
1#
#16000
0#
#16500
1!
0"
0$
1#
#17000
0#
#17500
0!
1"
1$
1#
#18000
0#
#18500
1!
0"
0$
1#
#19000
0#
#19500
0!
1"
1$
1#
#20000
0#
#20500
1!
0"
0$
1#
#21000
0#
#21500
0!
1"
1$
1#
#22000
0#
#22500
1!
0"
0$
1#
#23000
0#
#23500
0!
1"
1$
1#
#24000
0#
#24500
1!
0"
0$
1#
#25000
0#
#25500
0!
1"
1$
1#
#26000
0#
#26500
1!
0"
0$
1#
#27000
0#
#27500
0!
1"
1$
1#
#28000
0#
#28500
1!
0"
0$
1#
#29000
0#
#29500
0!
1"
1$
1#
#30000
0#
#30500
1!
0"
0$
1#
#31000
0#
#31500
0!
1"
1$
1#
#32000
0#
#32500
1!
0"
0$
1#
#33000
0#
#33500
0!
1"
1$
1#
#34000
0#
#34500
1!
0"
0$
1#
#35000
0#
#35500
0!
1"
1$
1#
#36000
0#
#36500
1!
0"
0$
1#
#37000
0#
#37500
0!
1"
1$
1#
#38000
0#
#38500
1!
0"
0$
1#
#39000
0#
#39500
0!
1"
1$
1#
#40000
0#
#40500
1!
0"
0$
1#
#41000
0#
#41500
0!
1"
1$
1#
#42000
0#
#42500
1!
0"
0$
1#
#43000
0#
#43500
0!
1"
1$
1#
#44000
0#
#44500
1!
0"
0$
1#
#45000
0#
#45500
0!
1"
1$
1#
#46000
0#
#46500
1!
0"
0$
1#
#47000
0#
#47500
0!
1"
1$
1#
#48000
0#
#48500
1!
0"
0$
1#
#49000
0#
#49500
0!
1"
1$
1#
#50000
0#
