seminar-2/mul/multiplication.v
module multiplication(clk, a, b, c, F);
    //входные сигналы
    input clk;
    input [7:0] a, b, c;

    //выходные сигналы
    output [15:0] F;
    reg [15:0] F;
    
    //служебные сигналы
    reg [15:0] F_1, F_2;
    reg [7:0] c_2, c_1;

    always @(posedge clk) begin
        F_2 <= a * b;
        c_2 <= c;
        F_1 <= F_2;
        c_1 <= c_2;
        F <= F_1 + c_1;
    end
endmodule // multiplication

module multiplication_c(clk, a, b, c, out);
    //входные сигнал
    input clk;
    input [7:0] a, b, c;

    //выход
    output [16:0] out;
    reg [16:0] out;

    //служебные сигналы
    wire [15:0] F;

    multiplication DD1(clk, a, b, c, F);
    
    always @(posedge clk) begin
        out <= F;
    end
endmodule // multiplication_c

seminar-2/mul/multiplication_tb.v
`timescale 1ns / 10ps
module multiplication_c_test;
    // дамп файла для GtkWave
    initial begin
        $dumpfile("multiplication_c_sim.vcd");
        $dumpvars(0, multiplication_c_test);
    end
    
    // входные сигналы
    reg clk = 0;
    always #5 clk = !clk;
    
    reg [7:0] a, b, c;
    initial begin
        a = 0;
        b = 0;
        c = 0;
    end
    always #5 a = a + 1;
    always #5 b = b + 1;
    always #5 c = c + 1;
    // выходные сигналы
    wire [16:0] out;

    // подключаем модуль
    multiplication_c DD1(clk, a, b, c, out);

    // отслеживание сигналов
    initial begin
        $monitor("At time %t", $time);
        #500 $finish;
    end
endmodule // multiplication_c_test

seminar-2/mul/multiplication_c_sim.vcd
$date
	Tue Sep 16 18:32:47 2025
$end
$version
	Icarus Verilog
$end
$timescale
	10ps
$end
$scope module multiplication_c_test $end
$var wire 17 ! out [16:0] $end
$var reg 8 " a [7:0] $end
$var reg 8 # b [7:0] $end
$var reg 8 $ c [7:0] $end
$var reg 1 % clk $end
$scope module DD1 $end
$var wire 8 & a [7:0] $end
$var wire 8 ' b [7:0] $end
$var wire 8 ( c [7:0] $end
$var wire 1 % clk $end
$var wire 16 ) F [15:0] $end
$var reg 17 * out [16:0] $end
$scope module DD1 $end
$var wire 8 + a [7:0] $end
$var wire 8 , b [7:0] $end
$var wire 8 - c [7:0] $end
$var wire 1 % clk $end
$var reg 16 . F [15:0] $end
$var reg 16 / F_1 [15:0] $end
$var reg 16 0 F_2 [15:0] $end
$var reg 8 1 c_1 [7:0] $end
$var reg 8 2 c_2 [7:0] $end
$upscope $end
$upscope $end
$upscope $end
$enddefinitions $end
$comment Show the parameter values. $end
$dumpall
$end
#0
$dumpvars
bx 2
bx 1
bx 0
bx /
bx .
b0 -
b0 ,
b0 +
bx *
bx )
b0 (
b0 '
b0 &
0%
b0 $
b0 #
b0 "
bx !
$end
#500
b1 2
b1 0
b0xxxxxxxxxxxxxxxx !
b0xxxxxxxxxxxxxxxx *
b1 $
b1 (
b1 -
b1 #
b1 '
b1 ,
b1 "
b1 &
b1 +
1%
#1000
b10 $
b10 (
b10 -
b10 #
b10 '
b10 ,
b10 "
b10 &
b10 +
0%
#1500
b1 1
b1 /
b11 2
b1001 0
b11 $
b11 (
b11 -
b11 #
b11 '
b11 ,
b11 "
b11 &
b11 +
1%
#2000
b100 $
b100 (
b100 -
b100 #
b100 '
b100 ,
b100 "
b100 &
b100 +
0%
#2500
b10 )
b10 .
b11 1
b1001 /
b101 2
b11001 0
b101 $
b101 (
b101 -
b101 #
b101 '
b101 ,
b101 "
b101 &
b101 +
1%
#3000
b110 $
b110 (
b110 -
b110 #
b110 '
b110 ,
b110 "
b110 &
b110 +
0%
#3500
b10 !
b10 *
b1100 )
b1100 .
b101 1
b11001 /
b111 2
b110001 0
b111 $
b111 (
b111 -
b111 #
b111 '
b111 ,
b111 "
b111 &
b111 +
1%
#4000
b1000 $
b1000 (
b1000 -
b1000 #
b1000 '
b1000 ,
b1000 "
b1000 &
b1000 +
0%
#4500
b11110 )
b11110 .
b111 1
b110001 /
b1001 2
b1010001 0
b1100 !
b1100 *
b1001 $
b1001 (
b1001 -
b1001 #
b1001 '
b1001 ,
b1001 "
b1001 &
b1001 +
1%
#5000
b1010 $
b1010 (
b1010 -
b1010 #
b1010 '
b1010 ,
b1010 "
b1010 &
b1010 +
0%
#5500
b11110 !
b11110 *
b111000 )
b111000 .
b1001 1
b1010001 /
b1011 2
b1111001 0
b1011 $
b1011 (
b1011 -
b1011 #
b1011 '
b1011 ,
b1011 "
b1011 &
b1011 +
1%
#6000
b1100 $
b1100 (
b1100 -
b1100 #
b1100 '
b1100 ,
b1100 "
b1100 &
b1100 +
0%
#6500
b1011010 )
b1011010 .
b1011 1
b1111001 /
b1101 2
b10101001 0
b111000 !
b111000 *
b1101 $
b1101 (
b1101 -
b1101 #
b1101 '
b1101 ,
b1101 "
b1101 &
b1101 +
1%
#7000
b1110 $
b1110 (
b1110 -
b1110 #
b1110 '
b1110 ,
b1110 "
b1110 &
b1110 +
0%
#7500
b1011010 !
b1011010 *
b10000100 )
b10000100 .
b1101 1
b10101001 /
b1111 2
b11100001 0
b1111 $
b1111 (
b1111 -
b1111 #
b1111 '
b1111 ,
b1111 "
b1111 &
b1111 +
1%
#8000
b10000 $
b10000 (
b10000 -
b10000 #
b10000 '
b10000 ,
b10000 "
b10000 &
b10000 +
0%
#8500
b10110110 )
b10110110 .
b1111 1
b11100001 /
b10001 2
b100100001 0
b10000100 !
b10000100 *
b10001 $
b10001 (
b10001 -
b10001 #
b10001 '
b10001 ,
b10001 "
b10001 &
b10001 +
1%
#9000
b10010 $
b10010 (
b10010 -
b10010 #
b10010 '
b10010 ,
b10010 "
b10010 &
b10010 +
0%
#9500
b10110110 !
b10110110 *
b11110000 )
b11110000 .
b10001 1
b100100001 /
b10011 2
b101101001 0
b10011 $
b10011 (
b10011 -
b10011 #
b10011 '
b10011 ,
b10011 "
b10011 &
b10011 +
1%
#10000
b10100 $
b10100 (
b10100 -
b10100 #
b10100 '
b10100 ,
b10100 "
b10100 &
b10100 +
0%
#10500
b100110010 )
b100110010 .
b10011 1
b101101001 /
b10101 2
b110111001 0
b11110000 !
b11110000 *
b10101 $
b10101 (
b10101 -
b10101 #
b10101 '
b10101 ,
b10101 "
b10101 &
b10101 +
1%
#11000
b10110 $
b10110 (
b10110 -
b10110 #
b10110 '
b10110 ,
b10110 "
b10110 &
b10110 +
0%
#11500
b100110010 !
b100110010 *
b101111100 )
b101111100 .
b10101 1
b110111001 /
b10111 2
b1000010001 0
b10111 $
b10111 (
b10111 -
b10111 #
b10111 '
b10111 ,
b10111 "
b10111 &
b10111 +
1%
#12000
b11000 $
b11000 (
b11000 -
b11000 #
b11000 '
b11000 ,
b11000 "
b11000 &
b11000 +
0%
#12500
b111001110 )
b111001110 .
b10111 1
b1000010001 /
b11001 2
b1001110001 0
b101111100 !
b101111100 *
b11001 $
b11001 (
b11001 -
b11001 #
b11001 '
b11001 ,
b11001 "
b11001 &
b11001 +
1%
#13000
b11010 $
b11010 (
b11010 -
b11010 #
b11010 '
b11010 ,
b11010 "
b11010 &
b11010 +
0%
#13500
b111001110 !
b111001110 *
b1000101000 )
b1000101000 .
b11001 1
b1001110001 /
b11011 2
b1011011001 0
b11011 $
b11011 (
b11011 -
b11011 #
b11011 '
b11011 ,
b11011 "
b11011 &
b11011 +
1%
#14000
b11100 $
b11100 (
b11100 -
b11100 #
b11100 '
b11100 ,
b11100 "
b11100 &
b11100 +
0%
#14500
b1010001010 )
b1010001010 .
b11011 1
b1011011001 /
b11101 2
b1101001001 0
b1000101000 !
b1000101000 *
b11101 $
b11101 (
b11101 -
b11101 #
b11101 '
b11101 ,
b11101 "
b11101 &
b11101 +
1%
#15000
b11110 $
b11110 (
b11110 -
b11110 #
b11110 '
b11110 ,
b11110 "
b11110 &
b11110 +
0%
#15500
b1010001010 !
b1010001010 *
b1011110100 )
b1011110100 .
b11101 1
b1101001001 /
b11111 2
b1111000001 0
b11111 $
b11111 (
b11111 -
b11111 #
b11111 '
b11111 ,
b11111 "
b11111 &
b11111 +
1%
#16000
b100000 $
b100000 (
b100000 -
b100000 #
b100000 '
b100000 ,
b100000 "
b100000 &
b100000 +
0%
#16500
b1101100110 )
b1101100110 .
b11111 1
b1111000001 /
b100001 2
b10001000001 0
b1011110100 !
b1011110100 *
b100001 $
b100001 (
b100001 -
b100001 #
b100001 '
b100001 ,
b100001 "
b100001 &
b100001 +
1%
#17000
b100010 $
b100010 (
b100010 -
b100010 #
b100010 '
b100010 ,
b100010 "
b100010 &
b100010 +
0%
#17500
b1101100110 !
b1101100110 *
b1111100000 )
b1111100000 .
b100001 1
b10001000001 /
b100011 2
b10011001001 0
b100011 $
b100011 (
b100011 -
b100011 #
b100011 '
b100011 ,
b100011 "
b100011 &
b100011 +
1%
#18000
b100100 $
b100100 (
b100100 -
b100100 #
b100100 '
b100100 ,
b100100 "
b100100 &
b100100 +
0%
#18500
b10001100010 )
b10001100010 .
b100011 1
b10011001001 /
b100101 2
b10101011001 0
b1111100000 !
b1111100000 *
b100101 $
b100101 (
b100101 -
b100101 #
b100101 '
b100101 ,
b100101 "
b100101 &
b100101 +
1%
#19000
b100110 $
b100110 (
b100110 -
b100110 #
b100110 '
b100110 ,
b100110 "
b100110 &
b100110 +
0%
#19500
b10001100010 !
b10001100010 *
b10011101100 )
b10011101100 .
b100101 1
b10101011001 /
b100111 2
b10111110001 0
b100111 $
b100111 (
b100111 -
b100111 #
b100111 '
b100111 ,
b100111 "
b100111 &
b100111 +
1%
#20000
b101000 $
b101000 (
b101000 -
b101000 #
b101000 '
b101000 ,
b101000 "
b101000 &
b101000 +
0%
#20500
b10101111110 )
b10101111110 .
b100111 1
b10111110001 /
b101001 2
b11010010001 0
b10011101100 !
b10011101100 *
b101001 $
b101001 (
b101001 -
b101001 #
b101001 '
b101001 ,
b101001 "
b101001 &
b101001 +
1%
#21000
b101010 $
b101010 (
b101010 -
b101010 #
b101010 '
b101010 ,
b101010 "
b101010 &
b101010 +
0%
#21500
b10101111110 !
b10101111110 *
b11000011000 )
b11000011000 .
b101001 1
b11010010001 /
b101011 2
b11100111001 0
b101011 $
b101011 (
b101011 -
b101011 #
b101011 '
b101011 ,
b101011 "
b101011 &
b101011 +
1%
#22000
b101100 $
b101100 (
b101100 -
b101100 #
b101100 '
b101100 ,
b101100 "
b101100 &
b101100 +
0%
#22500
b11010111010 )
b11010111010 .
b101011 1
b11100111001 /
b101101 2
b11111101001 0
b11000011000 !
b11000011000 *
b101101 $
b101101 (
b101101 -
b101101 #
b101101 '
b101101 ,
b101101 "
b101101 &
b101101 +
1%
#23000
b101110 $
b101110 (
b101110 -
b101110 #
b101110 '
b101110 ,
b101110 "
b101110 &
b101110 +
0%
#23500
b11010111010 !
b11010111010 *
b11101100100 )
b11101100100 .
b101101 1
b11111101001 /
b101111 2
b100010100001 0
b101111 $
b101111 (
b101111 -
b101111 #
b101111 '
b101111 ,
b101111 "
b101111 &
b101111 +
1%
#24000
b110000 $
b110000 (
b110000 -
b110000 #
b110000 '
b110000 ,
b110000 "
b110000 &
b110000 +
0%
#24500
b100000010110 )
b100000010110 .
b101111 1
b100010100001 /
b110001 2
b100101100001 0
b11101100100 !
b11101100100 *
b110001 $
b110001 (
b110001 -
b110001 #
b110001 '
b110001 ,
b110001 "
b110001 &
b110001 +
1%
#25000
b110010 $
b110010 (
b110010 -
b110010 #
b110010 '
b110010 ,
b110010 "
b110010 &
b110010 +
0%
#25500
b100000010110 !
b100000010110 *
b100011010000 )
b100011010000 .
b110001 1
b100101100001 /
b110011 2
b101000101001 0
b110011 $
b110011 (
b110011 -
b110011 #
b110011 '
b110011 ,
b110011 "
b110011 &
b110011 +
1%
#26000
b110100 $
b110100 (
b110100 -
b110100 #
b110100 '
b110100 ,
b110100 "
b110100 &
b110100 +
0%
#26500
b100110010010 )
b100110010010 .
b110011 1
b101000101001 /
b110101 2
b101011111001 0
b100011010000 !
b100011010000 *
b110101 $
b110101 (
b110101 -
b110101 #
b110101 '
b110101 ,
b110101 "
b110101 &
b110101 +
1%
#27000
b110110 $
b110110 (
b110110 -
b110110 #
b110110 '
b110110 ,
b110110 "
b110110 &
b110110 +
0%
#27500
b100110010010 !
b100110010010 *
b101001011100 )
b101001011100 .
b110101 1
b101011111001 /
b110111 2
b101111010001 0
b110111 $
b110111 (
b110111 -
b110111 #
b110111 '
b110111 ,
b110111 "
b110111 &
b110111 +
1%
#28000
b111000 $
b111000 (
b111000 -
b111000 #
b111000 '
b111000 ,
b111000 "
b111000 &
b111000 +
0%
#28500
b101100101110 )
b101100101110 .
b110111 1
b101111010001 /
b111001 2
b110010110001 0
b101001011100 !
b101001011100 *
b111001 $
b111001 (
b111001 -
b111001 #
b111001 '
b111001 ,
b111001 "
b111001 &
b111001 +
1%
#29000
b111010 $
b111010 (
b111010 -
b111010 #
b111010 '
b111010 ,
b111010 "
b111010 &
b111010 +
0%
#29500
b101100101110 !
b101100101110 *
b110000001000 )
b110000001000 .
b111001 1
b110010110001 /
b111011 2
b110110011001 0
b111011 $
b111011 (
b111011 -
b111011 #
b111011 '
b111011 ,
b111011 "
b111011 &
b111011 +
1%
#30000
b111100 $
b111100 (
b111100 -
b111100 #
b111100 '
b111100 ,
b111100 "
b111100 &
b111100 +
0%
#30500
b110011101010 )
b110011101010 .
b111011 1
b110110011001 /
b111101 2
b111010001001 0
b110000001000 !
b110000001000 *
b111101 $
b111101 (
b111101 -
b111101 #
b111101 '
b111101 ,
b111101 "
b111101 &
b111101 +
1%
#31000
b111110 $
b111110 (
b111110 -
b111110 #
b111110 '
b111110 ,
b111110 "
b111110 &
b111110 +
0%
#31500
b110011101010 !
b110011101010 *
b110111010100 )
b110111010100 .
b111101 1
b111010001001 /
b111111 2
b111110000001 0
b111111 $
b111111 (
b111111 -
b111111 #
b111111 '
b111111 ,
b111111 "
b111111 &
b111111 +
1%
#32000
b1000000 $
b1000000 (
b1000000 -
b1000000 #
b1000000 '
b1000000 ,
b1000000 "
b1000000 &
b1000000 +
0%
#32500
b111011000110 )
b111011000110 .
b111111 1
b111110000001 /
b1000001 2
b1000010000001 0
b110111010100 !
b110111010100 *
b1000001 $
b1000001 (
b1000001 -
b1000001 #
b1000001 '
b1000001 ,
b1000001 "
b1000001 &
b1000001 +
1%
#33000
b1000010 $
b1000010 (
b1000010 -
b1000010 #
b1000010 '
b1000010 ,
b1000010 "
b1000010 &
b1000010 +
0%
#33500
b111011000110 !
b111011000110 *
b111111000000 )
b111111000000 .
b1000001 1
b1000010000001 /
b1000011 2
b1000110001001 0
b1000011 $
b1000011 (
b1000011 -
b1000011 #
b1000011 '
b1000011 ,
b1000011 "
b1000011 &
b1000011 +
1%
#34000
b1000100 $
b1000100 (
b1000100 -
b1000100 #
b1000100 '
b1000100 ,
b1000100 "
b1000100 &
b1000100 +
0%
#34500
b1000011000010 )
b1000011000010 .
b1000011 1
b1000110001001 /
b1000101 2
b1001010011001 0
b111111000000 !
b111111000000 *
b1000101 $
b1000101 (
b1000101 -
b1000101 #
b1000101 '
b1000101 ,
b1000101 "
b1000101 &
b1000101 +
1%
#35000
b1000110 $
b1000110 (
b1000110 -
b1000110 #
b1000110 '
b1000110 ,
b1000110 "
b1000110 &
b1000110 +
0%
#35500
b1000011000010 !
b1000011000010 *
b1000111001100 )
b1000111001100 .
b1000101 1
b1001010011001 /
b1000111 2
b1001110110001 0
b1000111 $
b1000111 (
b1000111 -
b1000111 #
b1000111 '
b1000111 ,
b1000111 "
b1000111 &
b1000111 +
1%
#36000
b1001000 $
b1001000 (
b1001000 -
b1001000 #
b1001000 '
b1001000 ,
b1001000 "
b1001000 &
b1001000 +
0%
#36500
b1001011011110 )
b1001011011110 .
b1000111 1
b1001110110001 /
b1001001 2
b1010011010001 0
b1000111001100 !
b1000111001100 *
b1001001 $
b1001001 (
b1001001 -
b1001001 #
b1001001 '
b1001001 ,
b1001001 "
b1001001 &
b1001001 +
1%
#37000
b1001010 $
b1001010 (
b1001010 -
b1001010 #
b1001010 '
b1001010 ,
b1001010 "
b1001010 &
b1001010 +
0%
#37500
b1001011011110 !
b1001011011110 *
b1001111111000 )
b1001111111000 .
b1001001 1
b1010011010001 /
b1001011 2
b1010111111001 0
b1001011 $
b1001011 (
b1001011 -
b1001011 #
b1001011 '
b1001011 ,
b1001011 "
b1001011 &
b1001011 +
1%
#38000
b1001100 $
b1001100 (
b1001100 -
b1001100 #
b1001100 '
b1001100 ,
b1001100 "
b1001100 &
b1001100 +
0%
#38500
b1010100011010 )
b1010100011010 .
b1001011 1
b1010111111001 /
b1001101 2
b1011100101001 0
b1001111111000 !
b1001111111000 *
b1001101 $
b1001101 (
b1001101 -
b1001101 #
b1001101 '
b1001101 ,
b1001101 "
b1001101 &
b1001101 +
1%
#39000
b1001110 $
b1001110 (
b1001110 -
b1001110 #
b1001110 '
b1001110 ,
b1001110 "
b1001110 &
b1001110 +
0%
#39500
b1010100011010 !
b1010100011010 *
b1011001000100 )
b1011001000100 .
b1001101 1
b1011100101001 /
b1001111 2
b1100001100001 0
b1001111 $
b1001111 (
b1001111 -
b1001111 #
b1001111 '
b1001111 ,
b1001111 "
b1001111 &
b1001111 +
1%
#40000
b1010000 $
b1010000 (
b1010000 -
b1010000 #
b1010000 '
b1010000 ,
b1010000 "
b1010000 &
b1010000 +
0%
#40500
b1011101110110 )
b1011101110110 .
b1001111 1
b1100001100001 /
b1010001 2
b1100110100001 0
b1011001000100 !
b1011001000100 *
b1010001 $
b1010001 (
b1010001 -
b1010001 #
b1010001 '
b1010001 ,
b1010001 "
b1010001 &
b1010001 +
1%
#41000
b1010010 $
b1010010 (
b1010010 -
b1010010 #
b1010010 '
b1010010 ,
b1010010 "
b1010010 &
b1010010 +
0%
#41500
b1011101110110 !
b1011101110110 *
b1100010110000 )
b1100010110000 .
b1010001 1
b1100110100001 /
b1010011 2
b1101011101001 0
b1010011 $
b1010011 (
b1010011 -
b1010011 #
b1010011 '
b1010011 ,
b1010011 "
b1010011 &
b1010011 +
1%
#42000
b1010100 $
b1010100 (
b1010100 -
b1010100 #
b1010100 '
b1010100 ,
b1010100 "
b1010100 &
b1010100 +
0%
#42500
b1100111110010 )
b1100111110010 .
b1010011 1
b1101011101001 /
b1010101 2
b1110000111001 0
b1100010110000 !
b1100010110000 *
b1010101 $
b1010101 (
b1010101 -
b1010101 #
b1010101 '
b1010101 ,
b1010101 "
b1010101 &
b1010101 +
1%
#43000
b1010110 $
b1010110 (
b1010110 -
b1010110 #
b1010110 '
b1010110 ,
b1010110 "
b1010110 &
b1010110 +
0%
#43500
b1100111110010 !
b1100111110010 *
b1101100111100 )
b1101100111100 .
b1010101 1
b1110000111001 /
b1010111 2
b1110110010001 0
b1010111 $
b1010111 (
b1010111 -
b1010111 #
b1010111 '
b1010111 ,
b1010111 "
b1010111 &
b1010111 +
1%
#44000
b1011000 $
b1011000 (
b1011000 -
b1011000 #
b1011000 '
b1011000 ,
b1011000 "
b1011000 &
b1011000 +
0%
#44500
b1110010001110 )
b1110010001110 .
b1010111 1
b1110110010001 /
b1011001 2
b1111011110001 0
b1101100111100 !
b1101100111100 *
b1011001 $
b1011001 (
b1011001 -
b1011001 #
b1011001 '
b1011001 ,
b1011001 "
b1011001 &
b1011001 +
1%
#45000
b1011010 $
b1011010 (
b1011010 -
b1011010 #
b1011010 '
b1011010 ,
b1011010 "
b1011010 &
b1011010 +
0%
#45500
b1110010001110 !
b1110010001110 *
b1110111101000 )
b1110111101000 .
b1011001 1
b1111011110001 /
b1011011 2
b10000001011001 0
b1011011 $
b1011011 (
b1011011 -
b1011011 #
b1011011 '
b1011011 ,
b1011011 "
b1011011 &
b1011011 +
1%
#46000
b1011100 $
b1011100 (
b1011100 -
b1011100 #
b1011100 '
b1011100 ,
b1011100 "
b1011100 &
b1011100 +
0%
#46500
b1111101001010 )
b1111101001010 .
b1011011 1
b10000001011001 /
b1011101 2
b10000111001001 0
b1110111101000 !
b1110111101000 *
b1011101 $
b1011101 (
b1011101 -
b1011101 #
b1011101 '
b1011101 ,
b1011101 "
b1011101 &
b1011101 +
1%
#47000
b1011110 $
b1011110 (
b1011110 -
b1011110 #
b1011110 '
b1011110 ,
b1011110 "
b1011110 &
b1011110 +
0%
#47500
b1111101001010 !
b1111101001010 *
b10000010110100 )
b10000010110100 .
b1011101 1
b10000111001001 /
b1011111 2
b10001101000001 0
b1011111 $
b1011111 (
b1011111 -
b1011111 #
b1011111 '
b1011111 ,
b1011111 "
b1011111 &
b1011111 +
1%
#48000
b1100000 $
b1100000 (
b1100000 -
b1100000 #
b1100000 '
b1100000 ,
b1100000 "
b1100000 &
b1100000 +
0%
#48500
b10001000100110 )
b10001000100110 .
b1011111 1
b10001101000001 /
b1100001 2
b10010011000001 0
b10000010110100 !
b10000010110100 *
b1100001 $
b1100001 (
b1100001 -
b1100001 #
b1100001 '
b1100001 ,
b1100001 "
b1100001 &
b1100001 +
1%
#49000
b1100010 $
b1100010 (
b1100010 -
b1100010 #
b1100010 '
b1100010 ,
b1100010 "
b1100010 &
b1100010 +
0%
#49500
b10001000100110 !
b10001000100110 *
b10001110100000 )
b10001110100000 .
b1100001 1
b10010011000001 /
b1100011 2
b10011001001001 0
b1100011 $
b1100011 (
b1100011 -
b1100011 #
b1100011 '
b1100011 ,
b1100011 "
b1100011 &
b1100011 +
1%
#50000
b1100100 $
b1100100 (
b1100100 -
b1100100 #
b1100100 '
b1100100 ,
b1100100 "
b1100100 &
b1100100 +
0%
