seminar-2/mod3/mod3.v
module mod3(
    input clk,
    input in,
    input start,
    input finish,
    output reg out = 0
);

    // Внутренние регистры
    reg [1:0] mod = 2'b00;  // 2-битный регистр для хранения остатка от деления на 3
    reg active = 0;         // Флаг активности обработки
    
    always @(posedge clk) begin
        if (start) begin
            // Начало передачи - сброс состояния
            mod <= 2'b00;
            active <= 1'b1;
            out <= 1'b0;
        end
        else if (finish && active) begin
            // Конец передачи - проверка результата
            active <= 1'b0;
            out <= (mod == 2'b00) ? 1'b1 : 1'b0;
        end
        else if (active) begin
            // Обработка очередного бита
            case (mod)
                2'b00: mod <= (in == 1'b1) ? 2'b01 : 2'b00;
                2'b01: mod <= (in == 1'b1) ? 2'b11 : 2'b10;
                2'b10: mod <= (in == 1'b1) ? 2'b00 : 2'b01;
                2'b11: mod <= (in == 1'b1) ? 2'b10 : 2'b11;
            endcase
        end
    end

endmodule

seminar-2/mod3/mod3_tb.v
`timescale 1ns / 10ps
module mod3_test;
    // дамп файла для GtkWave
    initial begin
        $dumpfile("mod3_sim.vcd");
        $dumpvars(0, mod3_test);
    end
    
    // входные сигналы
    reg clk = 0;
    always #5 clk = !clk;
    reg clk1;
    always @(posedge clk) begin
        clk1 = 1;
        #4 clk1 = 0;
    end
    
    reg [7:0] a = 231;
    reg start, finish, in;
    reg [4:0] i = 0;

    always @(posedge clk1) begin
        i <= i + 1;
        case (i)
            0: start <= 1;
            1: begin
                start <= 0;
                in <= a[7];
            end
            2: in <= a[6];
            3: in <= a[5];
            4: in <= a[4];
            5: in <= a[3];
            6: in <= a[2];
            7: in <= a[1];
            8: in <= a[0];
            9: begin 
                finish <= 1;
                in <=0;
            end
            10: finish <= 0;
            11: i <= 0;
        endcase
    end
    
    wire out;
    // подключаем модуль
    mod3 DD1(clk, in, start, finish, out);

    // отслеживание сигналов
    initial begin
        $monitor("At time %t", $time);
        #500 $finish;
    end
endmodule // mod3_test

seminar-2/mod3/mod3_sim.vcd
$date
	Fri Sep 19 08:59:39 2025
$end
$version
	Icarus Verilog
$end
$timescale
	10ps
$end
$scope module mod3_test $end
$var wire 1 ! out $end
$var reg 8 " a [7:0] $end
$var reg 1 # clk $end
$var reg 1 $ clk1 $end
$var reg 1 % finish $end
$var reg 5 & i [4:0] $end
$var reg 1 ' in $end
$var reg 1 ( start $end
$scope module DD1 $end
$var wire 1 # clk $end
$var wire 1 % finish $end
$var wire 1 ' in $end
$var wire 1 ( start $end
$var reg 1 ) active $end
$var reg 2 * mod [1:0] $end
$var reg 1 ! out $end
$upscope $end
$upscope $end
$enddefinitions $end
$comment Show the parameter values. $end
$dumpall
$end
#0
$dumpvars
b0 *
0)
x(
x'
b0 &
x%
x$
0#
b11100111 "
0!
$end
#500
1(
b1 &
1$
1#
#900
0$
#1000
0#
#1500
1'
0(
b10 &
1)
1$
1#
#1900
0$
#2000
0#
#2500
b11 &
b1 *
1$
1#
#2900
0$
#3000
0#
#3500
b100 &
b11 *
1$
1#
#3900
0$
#4000
0#
#4500
0'
b101 &
b10 *
1$
1#
#4900
0$
#5000
0#
#5500
b110 &
b1 *
1$
1#
#5900
0$
#6000
0#
#6500
1'
b111 &
b10 *
1$
1#
#6900
0$
#7000
0#
#7500
b1000 &
b0 *
1$
1#
#7900
0$
#8000
0#
#8500
b1001 &
b1 *
1$
1#
#8900
0$
#9000
0#
#9500
0'
1%
b1010 &
b11 *
1$
1#
#9900
0$
#10000
0#
#10500
0%
b1011 &
0)
1$
1#
#10900
0$
#11000
0#
#11500
b0 &
1$
1#
#11900
0$
#12000
0#
#12500
1(
b1 &
1$
1#
#12900
0$
#13000
0#
#13500
1'
0(
b10 &
1)
b0 *
1$
1#
#13900
0$
#14000
0#
#14500
b11 &
b1 *
1$
1#
#14900
0$
#15000
0#
#15500
b100 &
b11 *
1$
1#
#15900
0$
#16000
0#
#16500
0'
b101 &
b10 *
1$
1#
#16900
0$
#17000
0#
#17500
b110 &
b1 *
1$
1#
#17900
0$
#18000
0#
#18500
1'
b111 &
b10 *
1$
1#
#18900
0$
#19000
0#
#19500
b1000 &
b0 *
1$
1#
#19900
0$
#20000
0#
#20500
b1001 &
b1 *
1$
1#
#20900
0$
#21000
0#
#21500
0'
1%
b1010 &
b11 *
1$
1#
#21900
0$
#22000
0#
#22500
0%
b1011 &
0)
1$
1#
#22900
0$
#23000
0#
#23500
b0 &
1$
1#
#23900
0$
#24000
0#
#24500
1(
b1 &
1$
1#
#24900
0$
#25000
0#
#25500
1'
0(
b10 &
1)
b0 *
1$
1#
#25900
0$
#26000
0#
#26500
b11 &
b1 *
1$
1#
#26900
0$
#27000
0#
#27500
b100 &
b11 *
1$
1#
#27900
0$
#28000
0#
#28500
0'
b101 &
b10 *
1$
1#
#28900
0$
#29000
0#
#29500
b110 &
b1 *
1$
1#
#29900
0$
#30000
0#
#30500
1'
b111 &
b10 *
1$
1#
#30900
0$
#31000
0#
#31500
b1000 &
b0 *
1$
1#
#31900
0$
#32000
0#
#32500
b1001 &
b1 *
1$
1#
#32900
0$
#33000
0#
#33500
0'
1%
b1010 &
b11 *
1$
1#
#33900
0$
#34000
0#
#34500
0%
b1011 &
0)
1$
1#
#34900
0$
#35000
0#
#35500
b0 &
1$
1#
#35900
0$
#36000
0#
#36500
1(
b1 &
1$
1#
#36900
0$
#37000
0#
#37500
1'
0(
b10 &
1)
b0 *
1$
1#
#37900
0$
#38000
0#
#38500
b11 &
b1 *
1$
1#
#38900
0$
#39000
0#
#39500
b100 &
b11 *
1$
1#
#39900
0$
#40000
0#
#40500
0'
b101 &
b10 *
1$
1#
#40900
0$
#41000
0#
#41500
b110 &
b1 *
1$
1#
#41900
0$
#42000
0#
#42500
1'
b111 &
b10 *
1$
1#
#42900
0$
#43000
0#
#43500
b1000 &
b0 *
1$
1#
#43900
0$
#44000
0#
#44500
b1001 &
b1 *
1$
1#
#44900
0$
#45000
0#
#45500
0'
1%
b1010 &
b11 *
1$
1#
#45900
0$
#46000
0#
#46500
0%
b1011 &
0)
1$
1#
#46900
0$
#47000
0#
#47500
b0 &
1$
1#
#47900
0$
#48000
0#
#48500
1(
b1 &
1$
1#
#48900
0$
#49000
0#
#49500
1'
0(
b10 &
1)
b0 *
1$
1#
