tasks/02_04_SkidBUF/code/skidbuff.v
module skid_buff(
    input clk,
    input reset,

    input [7:0] m_data,
    input m_valid,
    input m_last,
    output reg m_ready,

    output reg [7:0] s_data,
    output reg s_valid,
    output reg s_last,
    input s_ready
);

//объявляем возможные состояния
//(0 - обычная работа, 1 - работа в режиме буферизации)
reg STATE = 1'b0;

//объявляем память для хранения данных
reg [7:0] mem_data = 8'b0;
reg mem_last = 1'b0;

always @(posedge clk or negedge reset) begin 
    
    //Проверяем reset
    if(!reset) begin
        mem_data <= 8'b0;
        mem_last <= 1'b0;
        m_ready <= 1'b0;
        s_data <= 8'b0;
        s_valid <= 1'b0;
        s_last <= 1'b0;
        STATE = 1'b0;
    end else begin
        
        //проверяем состояние текущее
        if (STATE == 1'b0) begin
            
            //проверяем ситуацию, где мы должны переключиться в другой режим
            if ((m_ready == 1'b1) && (m_valid == 1'b1) && (s_valid == 1'b1) && (s_ready == 1'b0)) begin
                //запоминаем данные
                mem_data <= m_data;
                mem_last <= m_last;

                //выставляем сигналы
                m_ready <= 1'b0;
                s_valid <= 1'b1;
                s_data <= 8'b0;
                s_last <= 1'b0;

                //меняем состояние
                STATE <= 1'b1;
            end else begin
                
                //нормальный режим работы
                s_data <= m_data;
                s_last <= m_last;
                s_valid <= m_valid;
                m_ready <= s_ready;
            end
        end else begin 
            
            //если ready у Slave установлен в 1, то выводим данные, а если нет,
            //то просто молчим, ожидая готовности
            if (s_ready == 1'b1) begin
                
                //выдаём данные на выход
                s_data <= mem_data;
                s_last <= mem_last;

                //обновляем состояние
                STATE <= 1'b0;
            end
        end
    end
end

endmodule // skid_buff

tasks/02_04_SkidBUF/testbenches/skidbuff_tb.v
// задаём временную шкалу
`timescale 10 ps/ 1 ps

module skid_buff_test;

//dump для GTKWAVE
initial begin
    $dumpfile("skidbuff_simulation.vcd");
    $dumpvars(0, skid_buff_test);
end

//объявляем и задаём входные сигналы
reg clk = 1'b0;
always #5 clk <= ~clk;

reg reset = 1'b0;
reg [7:0] m_data = 8'b0;
reg m_valid = 1'b0;
reg m_last = 1'b0;
reg s_ready = 1'b0;

// объявляем выходные сигналы
wire [7:0] s_data;
wire s_valid;
wire s_last;
wire m_ready;

//подключаем модуль
skid_buff DUT (
    .clk(clk),
    .reset(reset),
    .m_data(m_data),
    .m_valid(m_valid),
    .m_last(m_last),
    .m_ready(m_ready),
    .s_data(s_data),
    .s_valid(s_valid),
    .s_last(s_last),
    .s_ready(s_ready)
);

// Монитор для отслеживания всех сигналов
initial begin
    $monitor("At time %0t: clk=%b, reset=%b, m_data=%h, m_valid=%b, m_last=%b, m_ready=%b, s_data=%h, s_valid=%b, s_last=%b, s_ready=%b, STATE=%b, mem_data=%h, mem_last=%b", 
              $time, clk, reset, m_data, m_valid, m_last, m_ready, s_data, s_valid, s_last, s_ready, DUT.STATE, DUT.mem_data, DUT.mem_last);
end

// Генерация тестовых сигналов
initial begin
    // Инициализация
    $display("=== НАЧАЛО ТЕСТИРОВАНИЯ ===");
    #10 reset = 1'b1;
    #20 reset = 1'b0;
    #10 s_ready = 1'b1; // Slave готов к приему
    
    // ============ ПАКЕТ 1: Полное прохождение без прерываний ============
    $display("\n=== ПАКЕТ 1: Нормальная передача, s_ready всегда = 1 ===");
    
    // Байт 1.1
    #10 m_data = 8'h11; m_valid = 1'b1; m_last = 1'b0;
    #10;
    
    // Байт 1.2
    m_data = 8'h22; m_valid = 1'b1; m_last = 1'b0;
    #10;
    
    // Байт 1.3
    m_data = 8'h33; m_valid = 1'b1; m_last = 1'b0;
    #10;
    
    // Байт 1.4 (последний)
    m_data = 8'h44; m_valid = 1'b1; m_last = 1'b1;
    #10;
    
    // Завершаем передачу
    m_valid = 1'b0; m_last = 1'b0;
    #20;
    
    // ============ ПАКЕТ 2: Прерывание на 2 такта (s_ready = 0) ============
    $display("\n=== ПАКЕТ 2: Передача с прерыванием на 2 такта (s_ready = 0) ===");
    
    // Байт 2.1 - нормальная передача
    #10 m_data = 8'hAA; m_valid = 1'b1; m_last = 1'b0;
    #10;
    
    // Байт 2.2 - нормальная передача
    m_data = 8'hBB; m_valid = 1'b1; m_last = 1'b0;
    #10;
    
    // Байт 2.3 - здесь будет прерывание (s_ready = 0 на 2 такта)
    m_data = 8'hCC; m_valid = 1'b1; m_last = 1'b0;
    
    // Отключаем s_ready на 2 такта
    $display("--- Прерывание передачи: s_ready = 0 на 2 такта ---");
    s_ready = 1'b0;
    #10; // 1-й такт прерывания
    #10; // 2-й такт прерывания
    
    // Восстанавливаем s_ready
    s_ready = 1'b1;
    $display("--- Восстановление передачи: s_ready = 1 ---");
    #10; // Передача должна продолжиться из буфера
    
    // Байт 2.4 (последний)
    m_data = 8'hDD; m_valid = 1'b1; m_last = 1'b1;
    #10;
    
    // Завершаем передачу
    m_valid = 1'b0; m_last = 1'b0;
    #20;
    
    // ============ Дополнительная проверка: Сброс во время передачи ============
    $display("\n=== Дополнительная проверка: Сброс во время передачи ===");
    
    s_ready = 1'b0; // Создаем условие для буферизации
    #10 m_data = 8'hEE; m_valid = 1'b1; m_last = 1'b0;
    #10; // Переход в режим буферизации
    
    // Сброс во время буферизации
    $display("--- Сброс во время режима буферизации ---");
    #5 reset = 1'b1;
    #5 reset = 1'b0;
    s_ready = 1'b1;
    #20;
    
    $display("\n=== ТЕСТИРОВАНИЕ ЗАВЕРШЕНО ===");
    
    // Завершение симуляции
    #100 $finish;
end


endmodule

tasks/02_04_SkidBUF/simulation/files/skidbuff_simulation.vcd
$date
	Fri Feb 20 15:08:42 2026
$end
$version
	Icarus Verilog
$end
$timescale
	1ps
$end
$scope module skid_buff_test $end
$var wire 1 ! s_valid $end
$var wire 1 " s_last $end
$var wire 8 # s_data [7:0] $end
$var wire 1 $ m_ready $end
$var reg 1 % clk $end
$var reg 8 & m_data [7:0] $end
$var reg 1 ' m_last $end
$var reg 1 ( m_valid $end
$var reg 1 ) reset $end
$var reg 1 * s_ready $end
$scope module DUT $end
$var wire 1 % clk $end
$var wire 8 + m_data [7:0] $end
$var wire 1 ' m_last $end
$var wire 1 ( m_valid $end
$var wire 1 ) reset $end
$var wire 1 * s_ready $end
$var reg 1 , STATE $end
$var reg 1 $ m_ready $end
$var reg 8 - mem_data [7:0] $end
$var reg 1 . mem_last $end
$var reg 8 / s_data [7:0] $end
$var reg 1 " s_last $end
$var reg 1 ! s_valid $end
$upscope $end
$upscope $end
$enddefinitions $end
$comment Show the parameter values. $end
$dumpall
$end
#0
$dumpvars
b0 /
0.
b0 -
0,
b0 +
0*
0)
0(
0'
b0 &
0%
0$
b0 #
0"
0!
$end
#50
1%
#100
0%
1)
#150
1%
#200
0%
#250
1%
#300
0%
0)
#350
1%
#400
0%
1*
#450
1%
#500
0%
1(
b10001 &
b10001 +
#550
1%
#600
0%
b100010 &
b100010 +
#650
1%
#700
0%
b110011 &
b110011 +
#750
1%
#800
0%
1'
b1000100 &
b1000100 +
#850
1%
#900
0%
0'
0(
#950
1%
#1000
0%
#1050
1%
#1100
0%
#1150
1%
#1200
0%
1(
b10101010 &
b10101010 +
#1250
1%
#1300
0%
b10111011 &
b10111011 +
#1350
1%
#1400
0%
0*
b11001100 &
b11001100 +
#1450
1%
#1500
0%
#1550
1%
#1600
0%
1*
#1650
1%
#1700
0%
1'
b11011101 &
b11011101 +
#1750
1%
#1800
0%
0'
0(
#1850
1%
#1900
0%
#1950
1%
#2000
0%
0*
#2050
1%
#2100
0%
1(
b11101110 &
b11101110 +
#2150
1%
#2200
0%
#2250
1!
b11101110 #
b11101110 /
1%
1)
#2300
0!
b0 #
b0 /
0%
1*
0)
