fan-examples/syncRStrigger/syncRStrigger.v
module syncRStrigger(clk, R, S, Q, nQ);
	// объявляем входы
	input R, S, clk;

	// объявляем выходы и их окружение
	output Q, nQ;
	reg Q, nQ;

	always @(posedge clk) begin
		if (S == 1 && R == 0) begin
			Q <= 1;
			nQ <= 0;
		end
                if (S == 0 && R == 1) begin
                        Q <= 0;
                        nQ <= 1;
                end
                if (S == 1 && R == 1) begin
                        Q <= 1'bx;
                        nQ <= 1'bx;
                end
	end
endmodule //

fan-examples/syncRStrigger/syncRStrigger_tb.v
`timescale 1ns / 10ps
module syncRStrigger_test;
    // дамп файла для GtkWave
    initial begin
        $dumpfile("syncRStrigger_sim.vcd");
        $dumpvars(0, syncRStrigger_test);
    end
    
    // тактовый сигнал
    reg clk = 0;
    always #5 clk = !clk;

    // входные сигналы
    reg R = 0;
    always #7 R = !R;
    reg S = 0;
    always #6 S = !S;

    // выходные сигналы
    wire Q, nQ;

    // подключаем модуль
    syncRStrigger T1(R, S, clk, Q, nQ);

    // отслеживание сигналов
    initial begin
        $monitor("At time %t, out1=%b, out2=%b", $time, Q, nQ);
        #500 $finish;
    end
endmodule // syncRStrigger_test

fan-examples/syncRStrigger/syncRStrigger_sim.vcd
$date
	Wed Sep 10 11:26:04 2025
$end
$version
	Icarus Verilog
$end
$timescale
	10ps
$end
$scope module syncRStrigger_test $end
$var wire 1 ! nQ $end
$var wire 1 " Q $end
$var reg 1 # R $end
$var reg 1 $ S $end
$var reg 1 % clk $end
$scope module T1 $end
$var wire 1 $ R $end
$var wire 1 % S $end
$var wire 1 # clk $end
$var reg 1 " Q $end
$var reg 1 ! nQ $end
$upscope $end
$upscope $end
$enddefinitions $end
$comment Show the parameter values. $end
$dumpall
$end
#0
$dumpvars
0%
0$
0#
x"
x!
$end
#500
1%
#600
1$
#700
1#
#1000
0%
#1200
0$
#1400
0#
#1500
1%
#1800
1$
#2000
0%
#2100
1!
0"
1#
#2400
0$
#2500
1%
#2800
0#
#3000
0%
1$
#3500
x!
x"
1%
1#
#3600
0$
#4000
0%
#4200
1$
0#
#4500
1%
#4800
0$
#4900
0!
1"
1#
#5000
0%
#5400
1$
#5500
1%
#5600
0#
#6000
0%
0$
#6300
1#
#6500
1%
#6600
1$
#7000
0%
0#
#7200
0$
#7500
1%
#7700
1#
#7800
1$
#8000
0%
#8400
0$
0#
#8500
1%
#9000
0%
1$
#9100
1!
0"
1#
#9500
1%
#9600
0$
#9800
0#
#10000
0%
#10200
1$
#10500
x!
x"
1%
1#
#10800
0$
#11000
0%
#11200
0#
#11400
1$
#11500
1%
#11900
1#
#12000
0%
0$
#12500
1%
#12600
1$
0#
#13000
0%
#13200
0$
#13300
1#
#13500
1%
#13800
1$
#14000
0%
0#
#14400
0$
#14500
1%
#14700
0!
1"
1#
#15000
0%
1$
#15400
0#
#15500
1%
#15600
0$
#16000
0%
#16100
1#
#16200
1$
#16500
1%
#16800
0$
0#
#17000
0%
#17400
1$
#17500
x!
x"
1%
1#
#18000
0%
0$
#18200
0#
#18500
1%
#18600
1$
#18900
1#
#19000
0%
#19200
0$
#19500
1%
#19600
0#
#19800
1$
#20000
0%
#20300
1!
0"
1#
#20400
0$
#20500
1%
#21000
0%
1$
0#
#21500
1%
#21600
0$
#21700
0!
1"
1#
#22000
0%
#22200
1$
#22400
0#
#22500
1%
#22800
0$
#23000
0%
#23100
1#
#23400
1$
#23500
1%
#23800
0#
#24000
0%
0$
#24500
1%
1#
#24600
1$
#25000
0%
#25200
0$
0#
#25500
1%
#25800
1$
#25900
x!
x"
1#
#26000
0%
#26400
0$
#26500
1%
#26600
0#
#27000
0%
1$
#27300
1!
0"
1#
#27500
1%
#27600
0$
#28000
0%
0#
#28200
1$
#28500
1%
#28700
x!
x"
1#
#28800
0$
#29000
0%
#29400
1$
0#
#29500
1%
#30000
0%
0$
#30100
1#
#30500
1%
#30600
1$
#30800
0#
#31000
0%
#31200
0$
#31500
0!
1"
1%
1#
#31800
1$
#32000
0%
#32200
0#
#32400
0$
#32500
1%
#32900
1#
#33000
0%
1$
#33500
1%
#33600
0$
0#
#34000
0%
#34200
1$
#34300
1!
0"
1#
#34500
1%
#34800
0$
#35000
0%
0#
#35400
1$
#35500
1%
#35700
x!
x"
1#
#36000
0%
0$
#36400
0#
#36500
1%
#36600
1$
#37000
0%
#37100
1!
0"
1#
#37200
0$
#37500
1%
#37800
1$
0#
#38000
0%
#38400
0$
#38500
0!
1"
1%
1#
#39000
0%
1$
#39200
0#
#39500
1%
#39600
0$
#39900
1#
#40000
0%
#40200
1$
#40500
1%
#40600
0#
#40800
0$
#41000
0%
#41300
1#
#41400
1$
#41500
1%
#42000
0%
0$
0#
#42500
1%
#42600
1$
#42700
x!
x"
1#
#43000
0%
#43200
0$
#43400
0#
#43500
1%
#43800
1$
#44000
0%
#44100
1!
0"
1#
#44400
0$
#44500
1%
#44800
0#
#45000
0%
1$
#45500
x!
x"
1%
1#
#45600
0$
#46000
0%
#46200
1$
0#
#46500
1%
#46800
0$
#46900
0!
1"
1#
#47000
0%
#47400
1$
#47500
1%
#47600
0#
#48000
0%
0$
#48300
1#
#48500
1%
#48600
1$
#49000
0%
0#
#49200
0$
#49500
1%
#49700
1#
#49800
1$
