fan-examples/multiplexor_4_1/multiplexor_4_1.v
module multiplexor_4_1(D, X, F);

	//объявляем входы
	input  [3:0] D;
	input  [1:0] X;

	//объявляем выходы
	output F;
	
	assign F = D[X];
endmodule // multiplexor_4_1

fan-examples/multiplexor_4_1/multiplexor_4_1_tb.v
`timescale 1ns / 10ps
module multiplexor_4_1_test;
    // дамп файла для GtkWave
    initial begin
        $dumpfile("multiplexor_4_1_sim.vcd");
        $dumpvars(0, multiplexor_4_1_test);
    end
    
    // входные сигналы
    reg [1:0] X = 2'b00;
    always #5 X = X + 1;
    reg [3:0] D = 4'b1010;
    always #17 D = D ^ 4'b1111;

    // выходные сигналы
    wire F;

    // подключаем модуль
    multiplexor_4_1 MUX1(D, X, F);

    // отслеживание сигналов
    initial begin
        $monitor("At time %t, out1=%b", $time, F);
        #500 $finish;
    end
endmodule // multiplexor_4_1_test

fan-examples/multiplexor_4_1/multiplexor_4_1_sim.vcd
$date
	Wed Sep 10 12:25:35 2025
$end
$version
	Icarus Verilog
$end
$timescale
	10ps
$end
$scope module multiplexor_4_1_test $end
$var wire 1 ! F $end
$var reg 4 " D [3:0] $end
$var reg 2 # X [1:0] $end
$scope module MUX1 $end
$var wire 4 $ D [3:0] $end
$var wire 2 % X [1:0] $end
$var wire 1 ! F $end
$upscope $end
$upscope $end
$enddefinitions $end
$comment Show the parameter values. $end
$dumpall
$end
#0
$dumpvars
b0 %
b1010 $
b0 #
b1010 "
0!
$end
#500
1!
b1 #
b1 %
#1000
0!
b10 #
b10 %
#1500
1!
b11 #
b11 %
#1700
0!
b101 "
b101 $
#2000
1!
b0 #
b0 %
#2500
0!
b1 #
b1 %
#3000
1!
b10 #
b10 %
#3400
0!
b1010 "
b1010 $
#3500
1!
b11 #
b11 %
#4000
0!
b0 #
b0 %
#4500
1!
b1 #
b1 %
#5000
0!
b10 #
b10 %
#5100
1!
b101 "
b101 $
#5500
0!
b11 #
b11 %
#6000
1!
b0 #
b0 %
#6500
0!
b1 #
b1 %
#6800
1!
b1010 "
b1010 $
#7000
0!
b10 #
b10 %
#7500
1!
b11 #
b11 %
#8000
0!
b0 #
b0 %
#8500
b1 #
b1 %
0!
b101 "
b101 $
#9000
1!
b10 #
b10 %
#9500
0!
b11 #
b11 %
#10000
1!
b0 #
b0 %
#10200
0!
b1010 "
b1010 $
#10500
1!
b1 #
b1 %
#11000
0!
b10 #
b10 %
#11500
1!
b11 #
b11 %
#11900
0!
b101 "
b101 $
#12000
1!
b0 #
b0 %
#12500
0!
b1 #
b1 %
#13000
1!
b10 #
b10 %
#13500
0!
b11 #
b11 %
#13600
1!
b1010 "
b1010 $
#14000
0!
b0 #
b0 %
#14500
1!
b1 #
b1 %
#15000
0!
b10 #
b10 %
#15300
1!
b101 "
b101 $
#15500
0!
b11 #
b11 %
#16000
1!
b0 #
b0 %
#16500
0!
b1 #
b1 %
#17000
b10 #
b10 %
0!
b1010 "
b1010 $
#17500
1!
b11 #
b11 %
#18000
0!
b0 #
b0 %
#18500
1!
b1 #
b1 %
#18700
0!
b101 "
b101 $
#19000
1!
b10 #
b10 %
#19500
0!
b11 #
b11 %
#20000
1!
b0 #
b0 %
#20400
0!
b1010 "
b1010 $
#20500
1!
b1 #
b1 %
#21000
0!
b10 #
b10 %
#21500
1!
b11 #
b11 %
#22000
0!
b0 #
b0 %
#22100
1!
b101 "
b101 $
#22500
0!
b1 #
b1 %
#23000
1!
b10 #
b10 %
#23500
0!
b11 #
b11 %
#23800
1!
b1010 "
b1010 $
#24000
0!
b0 #
b0 %
#24500
1!
b1 #
b1 %
#25000
0!
b10 #
b10 %
#25500
b11 #
b11 %
0!
b101 "
b101 $
#26000
1!
b0 #
b0 %
#26500
0!
b1 #
b1 %
#27000
1!
b10 #
b10 %
#27200
0!
b1010 "
b1010 $
#27500
1!
b11 #
b11 %
#28000
0!
b0 #
b0 %
#28500
1!
b1 #
b1 %
#28900
0!
b101 "
b101 $
#29000
1!
b10 #
b10 %
#29500
0!
b11 #
b11 %
#30000
1!
b0 #
b0 %
#30500
0!
b1 #
b1 %
#30600
1!
b1010 "
b1010 $
#31000
0!
b10 #
b10 %
#31500
1!
b11 #
b11 %
#32000
0!
b0 #
b0 %
#32300
1!
b101 "
b101 $
#32500
0!
b1 #
b1 %
#33000
1!
b10 #
b10 %
#33500
0!
b11 #
b11 %
#34000
b0 #
b0 %
0!
b1010 "
b1010 $
#34500
1!
b1 #
b1 %
#35000
0!
b10 #
b10 %
#35500
1!
b11 #
b11 %
#35700
0!
b101 "
b101 $
#36000
1!
b0 #
b0 %
#36500
0!
b1 #
b1 %
#37000
1!
b10 #
b10 %
#37400
0!
b1010 "
b1010 $
#37500
1!
b11 #
b11 %
#38000
0!
b0 #
b0 %
#38500
1!
b1 #
b1 %
#39000
0!
b10 #
b10 %
#39100
1!
b101 "
b101 $
#39500
0!
b11 #
b11 %
#40000
1!
b0 #
b0 %
#40500
0!
b1 #
b1 %
#40800
1!
b1010 "
b1010 $
#41000
0!
b10 #
b10 %
#41500
1!
b11 #
b11 %
#42000
0!
b0 #
b0 %
#42500
b1 #
b1 %
0!
b101 "
b101 $
#43000
1!
b10 #
b10 %
#43500
0!
b11 #
b11 %
#44000
1!
b0 #
b0 %
#44200
0!
b1010 "
b1010 $
#44500
1!
b1 #
b1 %
#45000
0!
b10 #
b10 %
#45500
1!
b11 #
b11 %
#45900
0!
b101 "
b101 $
#46000
1!
b0 #
b0 %
#46500
0!
b1 #
b1 %
#47000
1!
b10 #
b10 %
#47500
0!
b11 #
b11 %
#47600
1!
b1010 "
b1010 $
#48000
0!
b0 #
b0 %
#48500
1!
b1 #
b1 %
#49000
0!
b10 #
b10 %
#49300
1!
b101 "
b101 $
#49500
0!
b11 #
b11 %
#50000
1!
b0 #
b0 %
