tasks/02_04_AXI-stream/code/AXI_master.v
module AXI_master(
    input clk,
    input reset_n,
    output reg [7:0] data,
    output valid,
    output reg last,
    input ready,
    //вход для данных
    input [63:0] data_in,
    //сигнал для записи данных в буфер
    input we
);

//буфер для хранения не более 8 байт данных
reg [63:0] data_buff = 64'b0;
reg [3:0] buff_count = 3'b0;

//флаг наличия рукопожатия
wire flag_handshake;

//завязываем рукопожатие на значение сигналов
assign flag_handshake = ready & valid;

//завязываем valid на запись и счётчик
assign valid = (buff_count > 0) & (~we);

//первый always для работы буфера
always @(posedge clk or negedge reset_n) begin 
    if(~reset_n) begin 
        data_buff <= 64'b0;
        buff_count <= 4'b0;
    end else begin
        if (we) begin 
            data_buff <= data_in;
            buff_count <= 4'b1001;
        end
        if (flag_handshake & (buff_count > 0)) begin
            if(buff_count > 1) data_buff <= {8'b0, data_buff[63:8]};
            buff_count <= buff_count - 1;
        end
    end       
end

//второй always для работы протокола
always @(posedge clk or negedge reset_n) begin 
    if(~reset_n) begin 
        data <= 8'b0;
        last <= 1'b0;
    end else 
        if(flag_handshake) begin
            if(buff_count == 2) last <= 1'b1;
            else last <= 1'b0;
            data <= data_buff[7:0];
        end else begin 
            last <= 1'b0;
            data <= 8'b0;
        end
end

endmodule

tasks/02_04_AXI-stream/testbenches/AXI_master_tb.v
// задаём временную шкалу
`timescale 10 ps/ 1 ps

module axi_master_test;

//dump для GTKWAVE
initial begin
    $dumpfile("AXI_master_simulation.vcd");
    $dumpvars(0, axi_master_test);
end

//объявляем и задаём входные сигналы
reg clk = 1'b0;
always #5 clk <= ~clk;

reg reset_n = 1'b0;
reg [63:0] data_in = 64'b0;  // 64-битная входная шина
reg we = 1'b0;                // сигнал записи в буфер
reg ready = 1'b0;             // готовность приемника

// объявляем выходные сигналы
wire [7:0] data;              // выходные данные
wire valid;                   // валидность данных
wire last;                    // признак последнего байта

//подключаем модуль AXI-master
AXI_master DUT (
    .clk(clk),
    .reset_n(reset_n),
    .data(data),
    .valid(valid),
    .last(last),
    .ready(ready),
    .data_in(data_in),
    .we(we)
);

// Функция для инициализации входных данных
task init_inputs;
    begin
        reset_n = 1'b0;
        we = 1'b0;
        ready = 1'b0;
        data_in = 64'b0;
    end
endtask

// Функция для загрузки данных в буфер
task load_data;
    input [63:0] data_value;  // 64-битное значение
    begin
        @(posedge clk);
        data_in <= data_value;
        we <= 1'b1;
        @(posedge clk);
        we <= 1'b0;
        $display("Загружены данные: %h", data_value);
    end
endtask

// Функция для формирования 64-битного значения из 8 байт (порядок как в вашем коде)
// data_buff[7:0] - первый передаваемый байт (data[7:0])
// data_buff[63:56] - последний передаваемый байт
function [63:0] pack_data;
    input [7:0] b0, b1, b2, b3, b4, b5, b6, b7; // b0 - первый передаваемый байт
    begin
        pack_data = {b7, b6, b5, b4, b3, b2, b1, b0}; // b7 в старшие разряды
    end
endfunction

// Монитор для отслеживания всех сигналов
initial begin
    $monitor("At time %0t: clk=%b, reset_n=%b, data=%h, valid=%b, last=%b, ready=%b, buff_count=%d, data_buff=%h",
              $time, clk, reset_n, data, valid, last, ready, DUT.buff_count, DUT.data_buff);
end

// Генерация тестовых сигналов
initial begin
    // Инициализация
    $display("=== НАЧАЛО ТЕСТИРОВАНИЯ AXI MASTER ===");
    init_inputs();

    // Снимаем reset
    #10 reset_n = 1'b1;
    #5 ready = 1'b1;
    #5;

    // ============ ТЕСТ 1: Передача 8 байт с ready = 1 всегда ============
    $display("\n=== ТЕСТ 1: Передача 8 байт (12 34 56 78 9A BC DE F0) с ready = 1 ===");
    $display("Порядок передачи: 12 -> 34 -> 56 -> 78 -> 9A -> BC -> DE -> F0");

    // Загружаем данные: первый байт 0x12, последний 0xF0
    // В data_buff: [63:56]=F0, [55:48]=DE, [47:40]=BC, [39:32]=9A, [31:24]=78, [23:16]=56, [15:8]=34, [7:0]=12
    load_data(pack_data(8'h01, 8'h02, 8'h03, 8'h04, 
                        8'h05, 8'h06, 8'h07, 8'h08));


    // Ждем завершения передачи (8 тактов)
    #90;

    // Проверяем, что буфер опустел
    if (DUT.buff_count == 0)
        $display("ТЕСТ 1 ПРОЙДЕН: Все данные переданы");
    else
        $display("ТЕСТ 1 НЕ ПРОЙДЕН: buff_count = %d", DUT.buff_count);

    #20;

    // ============ ТЕСТ 2: Передача с прерываниями ready ============
    $display("\n=== ТЕСТ 2: Передача 8 байт (11 22 33 44 55 66 77 88) с прерываниями ready ===");

    // Загружаем данные: первый байт 0x11, последний 0x88
    load_data(pack_data(8'h11, 8'h22, 8'h33, 8'h44,
                        8'h55, 8'h66, 8'h77, 8'h88));

    // Начинаем передачу с ready = 1
    ready = 1'b1;

    // Ждем передачи 3 байт
    repeat(3) @(posedge clk);

    // Опускаем ready на 5 тактов
    $display("--- Опускаем ready в 0 на 5 тактов ---");
    ready = 1'b0;
    #50; // 5 тактов

    // Снова поднимаем ready
    $display("--- Восстанавливаем ready = 1 ---");
    ready = 1'b1;

    // Ждем завершения передачи (осталось 5 байт)
    #60;

    // Проверяем передачу последнего байта
    if (DUT.buff_count == 0)
        $display("ТЕСТ 2 ПРОЙДЕН: Все данные переданы после прерывания");
    else
        $display("ТЕСТ 2 НЕ ПРОЙДЕН: buff_count = %d", DUT.buff_count);

    #20;

    // ============ ТЕСТ 3: Проверка last ============
    $display("\n=== ТЕСТ 3: Проверка сигнала last ===");

    // Загружаем данные: 4 байта A1 B2 C3 D4, остальные 0
    load_data(pack_data(8'hA1, 8'hB2, 8'hC3, 8'hD4, 8'h00, 8'h00, 8'h00, 8'h00));

    // Начинаем передачу с ready = 1
    ready = 1'b1;

    // Отслеживаем last в течение 8 тактов
    repeat(8) begin
        @(posedge clk);
        $display("data=%h, last=%b, buff_count=%d", data, last, DUT.buff_count);
    end

    #20;

    // ============ ТЕСТ 4: Попытка записи во время передачи ============
    $display("\n=== ТЕСТ 4: Попытка записи во время передачи (we должен игнорироваться при valid=1) ===");

    // Загружаем первые данные
    load_data(pack_data(8'h11, 8'h22, 8'h33, 8'h44, 8'h55, 8'h66, 8'h77, 8'h88));

    // Начинаем передачу
    ready = 1'b1;

    // Ждем передачи 2 байт
    @(posedge clk);
    @(posedge clk);

    // Пытаемся записать новые данные (должно игнорироваться, т.к. valid=1)
    $display("Попытка записи новых данных во время передачи (valid=%b)", valid);
    load_data(pack_data(8'hFF, 8'hEE, 8'hDD, 8'hCC, 8'hBB, 8'hAA, 8'h99, 8'h88));

    // Ждем завершения передачи
    #60;

    if (DUT.buff_count == 0)
        $display("ТЕСТ 4 ПРОЙДЕН: Запись во время передачи проигнорирована");
    else
        $display("ТЕСТ 4 НЕ ПРОЙДЕН: buff_count = %d", DUT.buff_count);

    #20;

    // ============ ТЕСТ 5: Сброс во время передачи ============
    $display("\n=== ТЕСТ 5: Сброс во время передачи ===");

    // Загружаем данные
    load_data(pack_data(8'h11, 8'h22, 8'h33, 8'h44, 8'h55, 8'h66, 8'h77, 8'h88));

    // Начинаем передачу
    ready = 1'b1;

    // Ждем передачи нескольких байт
    #30;

    // Сбрасываем модуль
    $display("--- Сброс reset_n = 0 ---");
    reset_n = 1'b0;
    #20;

    // Проверяем состояние после сброса
    $display("После сброса: data=%h, last=%b, buff_count=%d", data, last, DUT.buff_count);

    // Восстанавливаем
    $display("--- Восстановление reset_n = 1 ---");
    reset_n = 1'b1;

    // Проверяем, что данные не передаются
    #20;

    if (DUT.buff_count == 0 && DUT.data_buff == 64'b0 && last == 1'b0)
        $display("ТЕСТ 5 ПРОЙДЕН: Сброс работает корректно");
    else
        $display("ТЕСТ 5 НЕ ПРОЙДЕН: buff_count = %d, data_buff = %h, last = %b",
                 DUT.buff_count, DUT.data_buff, last);

    #20;

    $display("\n=== ТЕСТИРОВАНИЕ ЗАВЕРШЕНО ===");

    // Завершение симуляции
    #100 $finish;
end

// Дополнительный монитор для отслеживания каждого переданного байта
always @(posedge clk) begin
    if (valid && ready) begin
        $display("ПЕРЕДАЧА: Такт %0t, data=%h, last=%b, buff_count=%d", 
                  $time, data, last, DUT.buff_count);
    end
end

endmodule

tasks/02_04_AXI-stream/simulation/files/AXI_master_simulation.vcd
$date
	Fri Feb 27 17:27:27 2026
$end
$version
	Icarus Verilog
$end
$timescale
	1ps
$end
$scope module axi_master_test $end
$var wire 1 ! valid $end
$var wire 1 " last $end
$var wire 8 # data [7:0] $end
$var reg 1 $ clk $end
$var reg 64 % data_in [63:0] $end
$var reg 1 & ready $end
$var reg 1 ' reset_n $end
$var reg 1 ( we $end
$scope function pack_data $end
$var reg 8 ) b0 [7:0] $end
$var reg 8 * b1 [7:0] $end
$var reg 8 + b2 [7:0] $end
$var reg 8 , b3 [7:0] $end
$var reg 8 - b4 [7:0] $end
$var reg 8 . b5 [7:0] $end
$var reg 8 / b6 [7:0] $end
$var reg 8 0 b7 [7:0] $end
$upscope $end
$scope module DUT $end
$var wire 1 $ clk $end
$var wire 64 1 data_in [63:0] $end
$var wire 1 2 flag_handshake $end
$var wire 1 & ready $end
$var wire 1 ' reset_n $end
$var wire 1 ! valid $end
$var wire 1 ( we $end
$var reg 4 3 buff_count [3:0] $end
$var reg 8 4 data [7:0] $end
$var reg 64 5 data_buff [63:0] $end
$var reg 1 " last $end
$upscope $end
$scope task init_inputs $end
$upscope $end
$scope task load_data $end
$var reg 64 6 data_value [63:0] $end
$upscope $end
$upscope $end
$enddefinitions $end
$comment Show the parameter values. $end
$dumpall
$end
#0
$dumpvars
bx 6
b0 5
b0 4
b0 3
02
b0 1
bx 0
bx /
bx .
bx -
bx ,
bx +
bx *
bx )
0(
0'
0&
b0 %
0$
b0 #
0"
0!
$end
#50
1$
#100
0$
1'
#150
1$
1&
#200
0$
b100000000111000001100000010100000100000000110000001000000001 6
b1 )
b10 *
b11 +
b100 ,
b101 -
b110 .
b111 /
b1000 0
#250
1(
b100000000111000001100000010100000100000000110000001000000001 %
b100000000111000001100000010100000100000000110000001000000001 1
1$
#300
0$
#350
12
1!
b1001 3
b100000000111000001100000010100000100000000110000001000000001 5
0(
1$
#400
0$
#450
b1 #
b1 4
b1000 3
b1000000001110000011000000101000001000000001100000010 5
1$
#500
0$
#550
b111 3
b10000000011100000110000001010000010000000011 5
b10 #
b10 4
1$
#600
0$
#650
b11 #
b11 4
b110 3
b100000000111000001100000010100000100 5
1$
#700
0$
#750
b101 3
b1000000001110000011000000101 5
b100 #
b100 4
1$
#800
0$
#850
b101 #
b101 4
b100 3
b10000000011100000110 5
1$
#900
0$
#950
b11 3
b100000000111 5
b110 #
b110 4
1$
#1000
0$
#1050
b111 #
b111 4
b10 3
b1000 5
1$
#1100
0$
#1150
b1 3
b0 5
b1000 #
b1000 4
1"
1$
#1200
0$
#1250
02
0!
b0 #
b0 4
0"
b0 3
1$
#1300
0$
#1350
1$
#1400
0$
#1450
1(
b1000100001110111011001100101010101000100001100110010001000010001 %
b1000100001110111011001100101010101000100001100110010001000010001 1
1$
b1000100001110111011001100101010101000100001100110010001000010001 6
b10001 )
b100010 *
b110011 +
b1000100 ,
b1010101 -
b1100110 .
b1110111 /
b10001000 0
#1500
0$
#1550
12
1!
b1001 3
b1000100001110111011001100101010101000100001100110010001000010001 5
0(
1$
#1600
0$
#1650
b10001 #
b10001 4
b1000 3
b10001000011101110110011001010101010001000011001100100010 5
1$
#1700
0$
#1750
b111 3
b100010000111011101100110010101010100010000110011 5
b100010 #
b100010 4
1$
#1800
0$
#1850
b110011 #
b110011 4
b110 3
b1000100001110111011001100101010101000100 5
02
0&
1$
#1900
0$
#1950
b0 #
b0 4
1$
#2000
0$
#2050
1$
#2100
0$
#2150
1$
#2200
0$
#2250
1$
#2300
0$
#2350
b101 3
b10001000011101110110011001010101 5
b1000100 #
b1000100 4
1$
12
1&
#2400
0$
#2450
b1010101 #
b1010101 4
b100 3
b100010000111011101100110 5
1$
#2500
0$
#2550
b11 3
b1000100001110111 5
b1100110 #
b1100110 4
1$
#2600
0$
#2650
b1110111 #
b1110111 4
b10 3
b10001000 5
1$
#2700
0$
#2750
b1 3
b0 5
b10001000 #
b10001000 4
1"
1$
#2800
0$
#2850
02
0!
b0 #
b0 4
0"
b0 3
1$
#2900
0$
#2950
1$
#3000
0$
#3050
1$
#3100
0$
#3150
1(
b11010100110000111011001010100001 %
b11010100110000111011001010100001 1
1$
b11010100110000111011001010100001 6
b10100001 )
b10110010 *
b11000011 +
b11010100 ,
b0 -
b0 .
b0 /
b0 0
#3200
0$
#3250
12
1!
b1001 3
b11010100110000111011001010100001 5
0(
1$
#3300
0$
#3350
b1000 3
b110101001100001110110010 5
b10100001 #
b10100001 4
1$
#3400
0$
#3450
b10110010 #
b10110010 4
b111 3
b1101010011000011 5
1$
#3500
0$
#3550
b110 3
b11010100 5
b11000011 #
b11000011 4
1$
#3600
0$
#3650
b11010100 #
b11010100 4
b101 3
b0 5
1$
#3700
0$
#3750
b100 3
b0 #
b0 4
1$
#3800
0$
#3850
b11 3
1$
#3900
0$
#3950
b10 3
1$
#4000
0$
#4050
1"
b1 3
1$
#4100
0$
#4150
02
0!
b0 3
0"
1$
#4200
0$
#4250
1(
b1000100001110111011001100101010101000100001100110010001000010001 %
b1000100001110111011001100101010101000100001100110010001000010001 1
1$
b1000100001110111011001100101010101000100001100110010001000010001 6
b10001 )
b100010 *
b110011 +
b1000100 ,
b1010101 -
b1100110 .
b1110111 /
b10001000 0
#4300
0$
#4350
12
1!
b1001 3
b1000100001110111011001100101010101000100001100110010001000010001 5
0(
1$
#4400
0$
#4450
b10001 #
b10001 4
b1000 3
b10001000011101110110011001010101010001000011001100100010 5
1$
#4500
0$
#4550
b111 3
b100010000111011101100110010101010100010000110011 5
b100010 #
b100010 4
b1000100010011001101010101011101111001100110111011110111011111111 6
b11111111 )
b11101110 *
b11011101 +
b11001100 ,
b10111011 -
b10101010 .
b10011001 /
1$
#4600
0$
#4650
02
0!
b110011 #
b110011 4
b110 3
b1000100001110111011001100101010101000100 5
1(
b1000100010011001101010101011101111001100110111011110111011111111 %
b1000100010011001101010101011101111001100110111011110111011111111 1
1$
#4700
0$
#4750
12
1!
b1001 3
b1000100010011001101010101011101111001100110111011110111011111111 5
b0 #
b0 4
0(
1$
#4800
0$
#4850
b11111111 #
b11111111 4
b1000 3
b10001000100110011010101010111011110011001101110111101110 5
1$
#4900
0$
#4950
b111 3
b100010001001100110101010101110111100110011011101 5
b11101110 #
b11101110 4
1$
#5000
0$
#5050
b11011101 #
b11011101 4
b110 3
b1000100010011001101010101011101111001100 5
1$
#5100
0$
#5150
b101 3
b10001000100110011010101010111011 5
b11001100 #
b11001100 4
1$
#5200
0$
#5250
b10111011 #
b10111011 4
b100 3
b100010001001100110101010 5
1$
#5300
0$
#5350
b11 3
b1000100010011001 5
b10101010 #
b10101010 4
1$
#5400
0$
#5450
b10011001 #
b10011001 4
b10 3
b10001000 5
1$
#5500
0$
#5550
02
0!
b1 3
b0 5
b10001000 #
b10001000 4
1"
1(
b1000100001110111011001100101010101000100001100110010001000010001 %
b1000100001110111011001100101010101000100001100110010001000010001 1
1$
b1000100001110111011001100101010101000100001100110010001000010001 6
b10001 )
b100010 *
b110011 +
b1000100 ,
b1010101 -
b1100110 .
b1110111 /
#5600
0$
#5650
12
1!
b0 #
b0 4
0"
b1001 3
b1000100001110111011001100101010101000100001100110010001000010001 5
0(
1$
#5700
0$
#5750
b1000 3
b10001000011101110110011001010101010001000011001100100010 5
b10001 #
b10001 4
1$
#5800
0$
#5850
b100010 #
b100010 4
b111 3
b100010000111011101100110010101010100010000110011 5
1$
#5900
0$
#5950
02
0!
b0 3
b0 5
b0 #
b0 4
1$
0'
#6000
0$
#6050
1$
#6100
0$
#6150
1$
1'
