fan-examples/syncTtrigger/syncTtrigger.v
module syncTtrigger(clk, T, Q, nQ);
	//объявляем входы
	input clk, T;

	//объявляем выходы
	output Q, nQ;
	reg Q, nQ;
	reg tmp_Q = 1;

	always @(posedge clk) begin
		if (T) tmp_Q = !tmp_Q;
		Q <= tmp_Q;
		nQ <= !tmp_Q;
	end
endmodule // syncTtrigger

fan-examples/syncTtrigger/syncTtrigger_tb.v
`timescale 1ns / 10ps
module syncTtrigger_test;
    // дамп файла для GtkWave
    initial begin
        $dumpfile("syncTtrigger_sim.vcd");
        $dumpvars(0, syncTtrigger_test);
    end
    
    // тактовый сигнал
    reg clk = 0;
    always #5 clk = !clk;

    // входные сигналы
    reg T = 0;
    always #7 T = !T;

    // выходные сигналы
    wire Q, nQ;

    // подключаем модуль
    syncTtrigger T1(clk, T, Q, nQ);

    // отслеживание сигналов
    initial begin
        $monitor("At time %t, out1=%b, out2=%b", $time, Q, nQ);
        #500 $finish;
    end
endmodule // syncTtrigger_test

fan-examples/syncTtrigger/syncTtrigger_sim.vcd
$date
	Wed Sep 10 11:57:13 2025
$end
$version
	Icarus Verilog
$end
$timescale
	10ps
$end
$scope module syncTtrigger_test $end
$var wire 1 ! nQ $end
$var wire 1 " Q $end
$var reg 1 # T $end
$var reg 1 $ clk $end
$scope module T1 $end
$var wire 1 # T $end
$var wire 1 $ clk $end
$var reg 1 " Q $end
$var reg 1 ! nQ $end
$var reg 1 % tmp_Q $end
$upscope $end
$upscope $end
$enddefinitions $end
$comment Show the parameter values. $end
$dumpall
$end
#0
$dumpvars
1%
0$
0#
x"
x!
$end
#500
0!
1"
1$
#700
1#
#1000
0$
#1400
0#
#1500
1$
#2000
0$
#2100
1#
#2500
1!
0"
0%
1$
#2800
0#
#3000
0$
#3500
0!
1"
1%
1$
1#
#4000
0$
#4200
0#
#4500
1$
#4900
1#
#5000
0$
#5500
1!
0"
0%
1$
#5600
0#
#6000
0$
#6300
1#
#6500
0!
1"
1%
1$
#7000
0$
0#
#7500
1$
#7700
1#
#8000
0$
#8400
0#
#8500
1$
#9000
0$
#9100
1#
#9500
1!
0"
0%
1$
#9800
0#
#10000
0$
#10500
0!
1"
1%
1$
1#
#11000
0$
#11200
0#
#11500
1$
#11900
1#
#12000
0$
#12500
1!
0"
0%
1$
#12600
0#
#13000
0$
#13300
1#
#13500
0!
1"
1%
1$
#14000
0$
0#
#14500
1$
#14700
1#
#15000
0$
#15400
0#
#15500
1$
#16000
0$
#16100
1#
#16500
1!
0"
0%
1$
#16800
0#
#17000
0$
#17500
0!
1"
1%
1$
1#
#18000
0$
#18200
0#
#18500
1$
#18900
1#
#19000
0$
#19500
1!
0"
0%
1$
#19600
0#
#20000
0$
#20300
1#
#20500
0!
1"
1%
1$
#21000
0$
0#
#21500
1$
#21700
1#
#22000
0$
#22400
0#
#22500
1$
#23000
0$
#23100
1#
#23500
1!
0"
0%
1$
#23800
0#
#24000
0$
#24500
0!
1"
1%
1$
1#
#25000
0$
#25200
0#
#25500
1$
#25900
1#
#26000
0$
#26500
1!
0"
0%
1$
#26600
0#
#27000
0$
#27300
1#
#27500
0!
1"
1%
1$
#28000
0$
0#
#28500
1$
#28700
1#
#29000
0$
#29400
0#
#29500
1$
#30000
0$
#30100
1#
#30500
1!
0"
0%
1$
#30800
0#
#31000
0$
#31500
0!
1"
1%
1$
1#
#32000
0$
#32200
0#
#32500
1$
#32900
1#
#33000
0$
#33500
1!
0"
0%
1$
#33600
0#
#34000
0$
#34300
1#
#34500
0!
1"
1%
1$
#35000
0$
0#
#35500
1$
#35700
1#
#36000
0$
#36400
0#
#36500
1$
#37000
0$
#37100
1#
#37500
1!
0"
0%
1$
#37800
0#
#38000
0$
#38500
0!
1"
1%
1$
1#
#39000
0$
#39200
0#
#39500
1$
#39900
1#
#40000
0$
#40500
1!
0"
0%
1$
#40600
0#
#41000
0$
#41300
1#
#41500
0!
1"
1%
1$
#42000
0$
0#
#42500
1$
#42700
1#
#43000
0$
#43400
0#
#43500
1$
#44000
0$
#44100
1#
#44500
1!
0"
0%
1$
#44800
0#
#45000
0$
#45500
0!
1"
1%
1$
1#
#46000
0$
#46200
0#
#46500
1$
#46900
1#
#47000
0$
#47500
1!
0"
0%
1$
#47600
0#
#48000
0$
#48300
1#
#48500
0!
1"
1%
1$
#49000
0$
0#
#49500
1$
#49700
1#
