fan-examples/demultiplexor_1_4/demultiplexor_1_4.v
module demultiplexor_1_4(D, X, F);

	//объявляем входы
	input  D;
	input  [1:0] X;

	//объявляем выходы
	output [3:0] F;

	assign F[0] = (X == 0) ? D : 0;
	assign F[1] = (X == 1) ? D : 0;
	assign F[2] = (X == 2) ? D : 0;
	assign F[3] = (X == 3) ? D : 0;

endmodule // demultiplexor_1_4

fan-examples/demultiplexor_1_4/demultiplexor_1_4_tb.v
`timescale 1ns / 10ps
module demultiplexor_1_4_test;
    // дамп файла для GtkWave
    initial begin
        $dumpfile("demultiplexor_1_4_sim.vcd");
        $dumpvars(0, demultiplexor_1_4_test);
    end
    
    // входные сигналы
    reg [1:0] X = 2'b00;
    always #15 X = X + 1;
    reg D = 1;
    always #2 D = !D;

    // выходные сигналы
    wire [3:0] F;

    // подключаем модуль
    demultiplexor_1_4 DMX1(D, X, F);

    // отслеживание сигналов
    initial begin
        $monitor("At time %t, out1=%b", $time, F);
        #500 $finish;
    end
endmodule // demultiplexor_1_4_test

fan-examples/demultiplexor_1_4/demultiplexor_1_4_sim.vcd
$date
	Wed Sep 10 22:49:33 2025
$end
$version
	Icarus Verilog
$end
$timescale
	10ps
$end
$scope module demultiplexor_1_4_test $end
$var wire 4 ! F [3:0] $end
$var reg 1 " D $end
$var reg 2 # X [1:0] $end
$scope module DMX1 $end
$var wire 1 " D $end
$var wire 2 $ X [1:0] $end
$var wire 4 % F [3:0] $end
$upscope $end
$upscope $end
$enddefinitions $end
$comment Show the parameter values. $end
$dumpall
$end
#0
$dumpvars
b1 %
b0 $
b0 #
1"
b1 !
$end
#200
b0 !
b0 %
0"
#400
b1 !
b1 %
1"
#600
b0 !
b0 %
0"
#800
b1 !
b1 %
1"
#1000
b0 !
b0 %
0"
#1200
b1 !
b1 %
1"
#1400
b0 !
b0 %
0"
#1500
b1 #
b1 $
#1600
b10 !
b10 %
1"
#1800
b0 !
b0 %
0"
#2000
b10 !
b10 %
1"
#2200
b0 !
b0 %
0"
#2400
b10 !
b10 %
1"
#2600
b0 !
b0 %
0"
#2800
b10 !
b10 %
1"
#3000
b0 !
b0 %
0"
b10 #
b10 $
#3200
b100 !
b100 %
1"
#3400
b0 !
b0 %
0"
#3600
b100 !
b100 %
1"
#3800
b0 !
b0 %
0"
#4000
b100 !
b100 %
1"
#4200
b0 !
b0 %
0"
#4400
b100 !
b100 %
1"
#4500
b1000 !
b1000 %
b11 #
b11 $
#4600
b0 !
b0 %
0"
#4800
b1000 !
b1000 %
1"
#5000
b0 !
b0 %
0"
#5200
b1000 !
b1000 %
1"
#5400
b0 !
b0 %
0"
#5600
b1000 !
b1000 %
1"
#5800
b0 !
b0 %
0"
#6000
b1 !
b1 %
1"
b0 #
b0 $
#6200
b0 !
b0 %
0"
#6400
b1 !
b1 %
1"
#6600
b0 !
b0 %
0"
#6800
b1 !
b1 %
1"
#7000
b0 !
b0 %
0"
#7200
b1 !
b1 %
1"
#7400
b0 !
b0 %
0"
#7500
b1 #
b1 $
#7600
b10 !
b10 %
1"
#7800
b0 !
b0 %
0"
#8000
b10 !
b10 %
1"
#8200
b0 !
b0 %
0"
#8400
b10 !
b10 %
1"
#8600
b0 !
b0 %
0"
#8800
b10 !
b10 %
1"
#9000
b0 !
b0 %
0"
b10 #
b10 $
#9200
b100 !
b100 %
1"
#9400
b0 !
b0 %
0"
#9600
b100 !
b100 %
1"
#9800
b0 !
b0 %
0"
#10000
b100 !
b100 %
1"
#10200
b0 !
b0 %
0"
#10400
b100 !
b100 %
1"
#10500
b1000 !
b1000 %
b11 #
b11 $
#10600
b0 !
b0 %
0"
#10800
b1000 !
b1000 %
1"
#11000
b0 !
b0 %
0"
#11200
b1000 !
b1000 %
1"
#11400
b0 !
b0 %
0"
#11600
b1000 !
b1000 %
1"
#11800
b0 !
b0 %
0"
#12000
b1 !
b1 %
1"
b0 #
b0 $
#12200
b0 !
b0 %
0"
#12400
b1 !
b1 %
1"
#12600
b0 !
b0 %
0"
#12800
b1 !
b1 %
1"
#13000
b0 !
b0 %
0"
#13200
b1 !
b1 %
1"
#13400
b0 !
b0 %
0"
#13500
b1 #
b1 $
#13600
b10 !
b10 %
1"
#13800
b0 !
b0 %
0"
#14000
b10 !
b10 %
1"
#14200
b0 !
b0 %
0"
#14400
b10 !
b10 %
1"
#14600
b0 !
b0 %
0"
#14800
b10 !
b10 %
1"
#15000
b0 !
b0 %
0"
b10 #
b10 $
#15200
b100 !
b100 %
1"
#15400
b0 !
b0 %
0"
#15600
b100 !
b100 %
1"
#15800
b0 !
b0 %
0"
#16000
b100 !
b100 %
1"
#16200
b0 !
b0 %
0"
#16400
b100 !
b100 %
1"
#16500
b1000 !
b1000 %
b11 #
b11 $
#16600
b0 !
b0 %
0"
#16800
b1000 !
b1000 %
1"
#17000
b0 !
b0 %
0"
#17200
b1000 !
b1000 %
1"
#17400
b0 !
b0 %
0"
#17600
b1000 !
b1000 %
1"
#17800
b0 !
b0 %
0"
#18000
b1 !
b1 %
1"
b0 #
b0 $
#18200
b0 !
b0 %
0"
#18400
b1 !
b1 %
1"
#18600
b0 !
b0 %
0"
#18800
b1 !
b1 %
1"
#19000
b0 !
b0 %
0"
#19200
b1 !
b1 %
1"
#19400
b0 !
b0 %
0"
#19500
b1 #
b1 $
#19600
b10 !
b10 %
1"
#19800
b0 !
b0 %
0"
#20000
b10 !
b10 %
1"
#20200
b0 !
b0 %
0"
#20400
b10 !
b10 %
1"
#20600
b0 !
b0 %
0"
#20800
b10 !
b10 %
1"
#21000
b0 !
b0 %
0"
b10 #
b10 $
#21200
b100 !
b100 %
1"
#21400
b0 !
b0 %
0"
#21600
b100 !
b100 %
1"
#21800
b0 !
b0 %
0"
#22000
b100 !
b100 %
1"
#22200
b0 !
b0 %
0"
#22400
b100 !
b100 %
1"
#22500
b1000 !
b1000 %
b11 #
b11 $
#22600
b0 !
b0 %
0"
#22800
b1000 !
b1000 %
1"
#23000
b0 !
b0 %
0"
#23200
b1000 !
b1000 %
1"
#23400
b0 !
b0 %
0"
#23600
b1000 !
b1000 %
1"
#23800
b0 !
b0 %
0"
#24000
b1 !
b1 %
1"
b0 #
b0 $
#24200
b0 !
b0 %
0"
#24400
b1 !
b1 %
1"
#24600
b0 !
b0 %
0"
#24800
b1 !
b1 %
1"
#25000
b0 !
b0 %
0"
#25200
b1 !
b1 %
1"
#25400
b0 !
b0 %
0"
#25500
b1 #
b1 $
#25600
b10 !
b10 %
1"
#25800
b0 !
b0 %
0"
#26000
b10 !
b10 %
1"
#26200
b0 !
b0 %
0"
#26400
b10 !
b10 %
1"
#26600
b0 !
b0 %
0"
#26800
b10 !
b10 %
1"
#27000
b0 !
b0 %
0"
b10 #
b10 $
#27200
b100 !
b100 %
1"
#27400
b0 !
b0 %
0"
#27600
b100 !
b100 %
1"
#27800
b0 !
b0 %
0"
#28000
b100 !
b100 %
1"
#28200
b0 !
b0 %
0"
#28400
b100 !
b100 %
1"
#28500
b1000 !
b1000 %
b11 #
b11 $
#28600
b0 !
b0 %
0"
#28800
b1000 !
b1000 %
1"
#29000
b0 !
b0 %
0"
#29200
b1000 !
b1000 %
1"
#29400
b0 !
b0 %
0"
#29600
b1000 !
b1000 %
1"
#29800
b0 !
b0 %
0"
#30000
b1 !
b1 %
1"
b0 #
b0 $
#30200
b0 !
b0 %
0"
#30400
b1 !
b1 %
1"
#30600
b0 !
b0 %
0"
#30800
b1 !
b1 %
1"
#31000
b0 !
b0 %
0"
#31200
b1 !
b1 %
1"
#31400
b0 !
b0 %
0"
#31500
b1 #
b1 $
#31600
b10 !
b10 %
1"
#31800
b0 !
b0 %
0"
#32000
b10 !
b10 %
1"
#32200
b0 !
b0 %
0"
#32400
b10 !
b10 %
1"
#32600
b0 !
b0 %
0"
#32800
b10 !
b10 %
1"
#33000
b0 !
b0 %
0"
b10 #
b10 $
#33200
b100 !
b100 %
1"
#33400
b0 !
b0 %
0"
#33600
b100 !
b100 %
1"
#33800
b0 !
b0 %
0"
#34000
b100 !
b100 %
1"
#34200
b0 !
b0 %
0"
#34400
b100 !
b100 %
1"
#34500
b1000 !
b1000 %
b11 #
b11 $
#34600
b0 !
b0 %
0"
#34800
b1000 !
b1000 %
1"
#35000
b0 !
b0 %
0"
#35200
b1000 !
b1000 %
1"
#35400
b0 !
b0 %
0"
#35600
b1000 !
b1000 %
1"
#35800
b0 !
b0 %
0"
#36000
b1 !
b1 %
1"
b0 #
b0 $
#36200
b0 !
b0 %
0"
#36400
b1 !
b1 %
1"
#36600
b0 !
b0 %
0"
#36800
b1 !
b1 %
1"
#37000
b0 !
b0 %
0"
#37200
b1 !
b1 %
1"
#37400
b0 !
b0 %
0"
#37500
b1 #
b1 $
#37600
b10 !
b10 %
1"
#37800
b0 !
b0 %
0"
#38000
b10 !
b10 %
1"
#38200
b0 !
b0 %
0"
#38400
b10 !
b10 %
1"
#38600
b0 !
b0 %
0"
#38800
b10 !
b10 %
1"
#39000
b0 !
b0 %
0"
b10 #
b10 $
#39200
b100 !
b100 %
1"
#39400
b0 !
b0 %
0"
#39600
b100 !
b100 %
1"
#39800
b0 !
b0 %
0"
#40000
b100 !
b100 %
1"
#40200
b0 !
b0 %
0"
#40400
b100 !
b100 %
1"
#40500
b1000 !
b1000 %
b11 #
b11 $
#40600
b0 !
b0 %
0"
#40800
b1000 !
b1000 %
1"
#41000
b0 !
b0 %
0"
#41200
b1000 !
b1000 %
1"
#41400
b0 !
b0 %
0"
#41600
b1000 !
b1000 %
1"
#41800
b0 !
b0 %
0"
#42000
b1 !
b1 %
1"
b0 #
b0 $
#42200
b0 !
b0 %
0"
#42400
b1 !
b1 %
1"
#42600
b0 !
b0 %
0"
#42800
b1 !
b1 %
1"
#43000
b0 !
b0 %
0"
#43200
b1 !
b1 %
1"
#43400
b0 !
b0 %
0"
#43500
b1 #
b1 $
#43600
b10 !
b10 %
1"
#43800
b0 !
b0 %
0"
#44000
b10 !
b10 %
1"
#44200
b0 !
b0 %
0"
#44400
b10 !
b10 %
1"
#44600
b0 !
b0 %
0"
#44800
b10 !
b10 %
1"
#45000
b0 !
b0 %
0"
b10 #
b10 $
#45200
b100 !
b100 %
1"
#45400
b0 !
b0 %
0"
#45600
b100 !
b100 %
1"
#45800
b0 !
b0 %
0"
#46000
b100 !
b100 %
1"
#46200
b0 !
b0 %
0"
#46400
b100 !
b100 %
1"
#46500
b1000 !
b1000 %
b11 #
b11 $
#46600
b0 !
b0 %
0"
#46800
b1000 !
b1000 %
1"
#47000
b0 !
b0 %
0"
#47200
b1000 !
b1000 %
1"
#47400
b0 !
b0 %
0"
#47600
b1000 !
b1000 %
1"
#47800
b0 !
b0 %
0"
#48000
b1 !
b1 %
1"
b0 #
b0 $
#48200
b0 !
b0 %
0"
#48400
b1 !
b1 %
1"
#48600
b0 !
b0 %
0"
#48800
b1 !
b1 %
1"
#49000
b0 !
b0 %
0"
#49200
b1 !
b1 %
1"
#49400
b0 !
b0 %
0"
#49500
b1 #
b1 $
#49600
b10 !
b10 %
1"
#49800
b0 !
b0 %
0"
#50000
b10 !
b10 %
1"
