tasks/02_04_SkidBuffer/code/AXI_slave.v
module AXI_slave(
    input clk,
    input reset_n,
    input [7:0] data,
    input valid,
    input last,
    output reg ready,
    //выход для данных
    output reg [7:0] data_out,
    //сигнал остановки чтения
    input stop
);

//флаг наличия рукопожатия
wire flag_handshake;

//завязываем рукопожатие на значение сигналов
assign flag_handshake = ready & valid;

//завязываем valid на запись и счётчик
always @(posedge clk or negedge reset_n) begin
    ready <= ~stop & reset_n;
end

always @(posedge clk or negedge reset_n) begin
    if(~reset_n) 
        data_out <= 8'b0;
    else 
        if (flag_handshake) 
            data_out <= data;
        else
            data_out <= 8'b0;
end

endmodule // AXI_slave

tasks/02_04_SkidBuffer/code/AXI_master.v
module AXI_master(
    input clk,
    input reset_n,
    output reg [7:0] data,
    output reg valid,
    output reg last,
    input ready,
    //вход для данных
    input [63:0] data_in,
    //сигнал для записи данных в буфер
    input we
);

//буфер для хранения не более 8 байт данных
reg [63:0] data_buff = 64'b0;
reg [2:0] buff_count = 3'b0;

//флаг наличия рукопожатия
wire flag_handshake;

//завязываем рукопожатие на значение сигналов
assign flag_handshake = ready & valid;

//логика для valid
always @(posedge clk or negedge reset_n) begin 
    if (~reset_n) valid <= 1'b0;
    else if ((buff_count > 0) & ~we) begin 
        if (valid == 1'b0) begin 
            data <= data_buff[7:0];
            data_buff <= {8'b0, data_buff[63:8]};
        end
        valid <= 1'b1;
    end else valid <= 1'b0;
end 

//always для работы буфера
always @(posedge clk or negedge reset_n) begin 
    if(~reset_n) begin 
        data_buff <= 64'b0;
        buff_count <= 4'b0;
    end else begin
        if (we) begin 
            data_buff <= data_in;
            buff_count <= 3'b111;
        end
        if (flag_handshake & (buff_count > 0) & ~we) begin
            if(buff_count > 1) data_buff <= {8'b0, data_buff[63:8]};
            buff_count <= buff_count - 1;
        end
    end       
end

//второй always для работы протокола
always @(posedge clk or negedge reset_n) begin 
    if(~reset_n) begin 
        data <= 8'b0;
        last <= 1'b0;
    end else 
        if(flag_handshake) begin
            if(buff_count == 1) last <= 1'b1;
            else last <= 1'b0;
            data <= data_buff[7:0];
        end else last <= 1'b0;
end

endmodule

fan-examples/AXI-stream/testbenches/AXI_stream_tb.v
// задаём временную шкалу
`timescale 10 ps/ 1 ps

module AXI_stream_test;

//dump для GTKWAVE
initial begin
    $dumpfile("AXI_stream_simulation.vcd");
    $dumpvars(0, AXI_stream_test);
end

//объявляем и задаём входные сигналы
reg clk = 1'b0;
always #5 clk <= ~clk;

reg reset_n = 1'b0;
reg [63:0] data_in = 64'b0;  // 64-битная входная шина
reg we = 1'b0;                // сигнал записи в буфер master
reg stop = 1'b0;              // сигнал остановки slave

// объявляем провода для связи между модулями
wire [7:0] data;              // данные от master к slave
wire valid;                   // валидность данных от master
wire last;                    // признак последнего байта от master
wire ready;                   // готовность slave

// выход slave
wire [7:0] data_out;          // данные на выходе slave

//подключаем модуль AXI-master
AXI_master master (
    .clk(clk),
    .reset_n(reset_n),
    .data(data),
    .valid(valid),
    .last(last),
    .ready(ready),
    .data_in(data_in),
    .we(we)
);

//подключаем модуль AXI-slave
AXI_slave slave (
    .clk(clk),
    .reset_n(reset_n),
    .data(data),
    .valid(valid),
    .last(last),
    .ready(ready),
    .data_out(data_out),
    .stop(stop)
);

// Функция для инициализации входных данных
task init_inputs;
    begin
        reset_n = 1'b0;
        we = 1'b0;
        stop = 1'b0;
        data_in = 64'b0;
    end
endtask

// Функция для загрузки данных в буфер master
task load_data;
    input [63:0] data_value;  // 64-битное значение
    begin
        @(posedge clk);
        data_in <= data_value;
        we <= 1'b1;
        @(posedge clk);
        we <= 1'b0;
        $display("Загружены данные в master: %h", data_value);
    end
endtask

// Функция для формирования 64-битного значения из 8 байт
// Порядок: первый передаваемый байт - младший байт (data[7:0])
function [63:0] pack_data;
    input [7:0] b0, b1, b2, b3, b4, b5, b6, b7; // b0 - первый передаваемый байт
    begin
        pack_data = {b7, b6, b5, b4, b3, b2, b1, b0};
    end
endfunction

// Монитор для отслеживания всех сигналов
initial begin
    $monitor("At time %0t: clk=%b, reset_n=%b, data=%h, valid=%b, last=%b, ready=%b, data_out=%h, stop=%b, master_buff_count=%d, master_data_buff=%h",
              $time, clk, reset_n, data, valid, last, ready, data_out, stop, master.buff_count, master.data_buff);
end

// Проверка переданных данных на выходе slave
integer i;
reg [7:0] expected_data [0:7];
reg [63:0] test_packet;

initial begin
    // Формируем тестовый пакет 0102030405060708
    // Первый байт: 01, последний: 08
    test_packet = pack_data(8'h01, 8'h02, 8'h03, 8'h04, 8'h05, 8'h06, 8'h07, 8'h08);
    
    // Ожидаемые данные по порядку
    expected_data[0] = 8'h01;
    expected_data[1] = 8'h02;
    expected_data[2] = 8'h03;
    expected_data[3] = 8'h04;
    expected_data[4] = 8'h05;
    expected_data[5] = 8'h06;
    expected_data[6] = 8'h07;
    expected_data[7] = 8'h08;
    
    // Инициализация
    $display("=== НАЧАЛО ТЕСТИРОВАНИЯ AXI STREAM ===");
    $display("Тестовый пакет: 01 02 03 04 05 06 07 08\n");
    init_inputs();

    // Снимаем reset
    #10 reset_n = 1'b1;
    #5;

    // ============ ТЕСТ 1: Обычная передача ============
    $display("=== ТЕСТ 1: Обычная передача пакета 0102030405060708 ===");
    $display("Порядок передачи: 01 -> 02 -> 03 -> 04 -> 05 -> 06 -> 07 -> 08");

    // Загружаем данные в master
    load_data(test_packet);

    // Ждем завершения передачи (8 тактов + запас)
    #100;

    // Проверяем, что буфер master опустел
    if (master.buff_count == 0)
        $display("ТЕСТ 1: master.buff_count = 0 - OK");
    else
        $display("ТЕСТ 1: master.buff_count = %d - ОШИБКА", master.buff_count);

    #20;

    // ============ ТЕСТ 2: Передача прерывается сигналом stop ============
    $display("\n=== ТЕСТ 2: Передача с прерыванием от slave (stop) ===");

    // Загружаем данные
    load_data(test_packet);

    // Ждем передачи 3 байт
    repeat(3) @(posedge clk);

    // Активируем stop на 5 тактов
    $display("--- Активируем stop = 1 на 5 тактов ---");
    stop = 1'b1;
    #50; // 5 тактов

    // Деактивируем stop
    $display("--- Деактивируем stop = 0 ---");
    stop = 1'b0;

    // Ждем завершения передачи
    #60;

    if (master.buff_count == 0)
        $display("ТЕСТ 2: master.buff_count = 0 после stop - OK");
    else
        $display("ТЕСТ 2: master.buff_count = %d после stop - ОШИБКА", master.buff_count);

    #20;

    // ============ ТЕСТ 3: Передача прерывается записью новых данных в master ============
    $display("\n=== ТЕСТ 3: Передача прерывается записью новых данных в master ===");

    // Загружаем первые данные
    load_data(test_packet);

    // Ждем передачи 2 байт
    @(posedge clk);
    @(posedge clk);

    // Пытаемся записать новые данные во время передачи
    $display("Попытка записи новых данных во время передачи (valid=%b, ready=%b)", valid, ready);
    load_data(pack_data(8'h01, 8'h02, 8'h03, 8'h04, 8'h05, 8'h06, 8'h07, 8'h08));

    // Ждем завершения передачи
    #80;

    if (master.buff_count == 0)
        $display("ТЕСТ 3: master.buff_count = 0 после записи - OK (запись проигнорирована)");
    else
        $display("ТЕСТ 3: master.buff_count = %d после записи - ОШИБКА", master.buff_count);

    #20;

    // ============ ТЕСТ 4: Передача прерывается сбросом ============
    $display("\n=== ТЕСТ 4: Передача прерывается сбросом (reset_n) ===");

    // Загружаем данные
    load_data(test_packet);

    // Ждем передачи 3 байт
    repeat(3) @(posedge clk);

    // Сбрасываем модули
    $display("--- Сброс reset_n = 0 на 3 такта ---");
    reset_n = 1'b0;
    #30;

    // Проверяем состояние после сброса
    $display("После сброса: master.data_buff=%h, master.buff_count=%d, data_out=%h", 
             master.data_buff, master.buff_count, data_out);

    // Восстанавливаем
    $display("--- Восстановление reset_n = 1 ---");
    reset_n = 1'b1;

    // Проверяем, что данные не передаются и буферы сброшены
    #20;

    if (master.buff_count == 0 && master.data_buff == 64'b0 && data_out == 8'b0)
        $display("ТЕСТ 4: Сброс работает корректно - OK");
    else
        $display("ТЕСТ 4: ОШИБКА - buff_count=%d, data_buff=%h, data_out=%h", 
                 master.buff_count, master.data_buff, data_out);

    #20;

    // ============ ТЕСТ 5: Проверка данных на выходе slave ============
    $display("\n=== ТЕСТ 5: Проверка данных на выходе slave ===");

    // Загружаем данные
    load_data(test_packet);

    // Сбрасываем счетчик для проверки
    i = 0;

    // Ждем 8 тактов передачи и проверяем выходные данные
    repeat(8) begin
        @(posedge clk);
        if (valid && ready) begin
            if (data_out === expected_data[i]) begin
                $display("Байт %d: ожидалось %h, получено %h - OK", 
                         i+1, expected_data[i], data_out);
            end else begin
                $display("Байт %d: ОШИБКА - ожидалось %h, получено %h", 
                         i+1, expected_data[i], data_out);
            end
            i = i + 1;
        end
    end

    if (i == 8)
        $display("ТЕСТ 5: Все 8 байт переданы корректно - OK");
    else
        $display("ТЕСТ 5: ОШИБКА - передано только %d байт", i);

    #20;

    // ============ Дополнительная проверка сигнала last ============
    $display("\n=== Дополнительная проверка: Сигнал last ===");

    // Загружаем данные
    load_data(test_packet);

    // Отслеживаем last
    repeat(9) begin
        @(posedge clk);
        if (valid && ready) begin
            $display("data=%h, last=%b, master.buff_count=%d", data, last, master.buff_count);
        end
    end

    #20;

    $display("\n=== ТЕСТИРОВАНИЕ AXI STREAM ЗАВЕРШЕНО ===");

    // Завершение симуляции
    #100 $finish;
end

// Монитор для отслеживания каждого переданного байта
always @(posedge clk) begin
    if (valid && ready) begin
        $display("ПЕРЕДАЧА: Такт %0t, data=%h, data_out=%h, last=%b, master.buff_count=%d",
                  $time, data, data_out, last, master.buff_count);
    end
end

// Проверка сигнала last
always @(posedge clk) begin
    if (valid && ready && last) begin
        $display("LAST DETECTED: Такт %0t, это последний байт пакета", $time);
    end
end

endmodule

fan-examples/AXI-stream/simulation/files/AXI_stream_simulation.vcd
$date
	Mon Mar  2 11:47:25 2026
$end
$version
	Icarus Verilog
$end
$timescale
	1ps
$end
$scope module AXI_stream_test $end
$var wire 1 ! valid $end
$var wire 1 " ready $end
$var wire 1 # last $end
$var wire 8 $ data_out [7:0] $end
$var wire 8 % data [7:0] $end
$var reg 1 & clk $end
$var reg 64 ' data_in [63:0] $end
$var reg 1 ( reset_n $end
$var reg 1 ) stop $end
$var reg 64 * test_packet [63:0] $end
$var reg 1 + we $end
$var integer 32 , i [31:0] $end
$scope function pack_data $end
$var reg 8 - b0 [7:0] $end
$var reg 8 . b1 [7:0] $end
$var reg 8 / b2 [7:0] $end
$var reg 8 0 b3 [7:0] $end
$var reg 8 1 b4 [7:0] $end
$var reg 8 2 b5 [7:0] $end
$var reg 8 3 b6 [7:0] $end
$var reg 8 4 b7 [7:0] $end
$upscope $end
$scope module master $end
$var wire 1 & clk $end
$var wire 64 5 data_in [63:0] $end
$var wire 1 6 flag_handshake $end
$var wire 1 ( reset_n $end
$var wire 1 + we $end
$var wire 1 " ready $end
$var reg 3 7 buff_count [2:0] $end
$var reg 8 8 data [7:0] $end
$var reg 64 9 data_buff [63:0] $end
$var reg 1 # last $end
$var reg 1 ! valid $end
$upscope $end
$scope module slave $end
$var wire 1 & clk $end
$var wire 8 : data [7:0] $end
$var wire 1 ; flag_handshake $end
$var wire 1 # last $end
$var wire 1 ( reset_n $end
$var wire 1 ) stop $end
$var wire 1 ! valid $end
$var reg 8 < data_out [7:0] $end
$var reg 1 " ready $end
$upscope $end
$scope task init_inputs $end
$upscope $end
$scope task load_data $end
$var reg 64 = data_value [63:0] $end
$upscope $end
$upscope $end
$enddefinitions $end
$comment Show the parameter values. $end
$dumpall
$end
#0
$dumpvars
bx =
b0 <
0;
b0 :
b0 9
b0 8
b0 7
06
b0 5
b1000 4
b111 3
b110 2
b101 1
b100 0
b11 /
b10 .
b1 -
bx ,
0+
b100000000111000001100000010100000100000000110000001000000001 *
0)
0(
b0 '
0&
b0 %
b0 $
0#
0"
0!
$end
#50
1&
#100
0&
1(
#150
1"
1+
b100000000111000001100000010100000100000000110000001000000001 '
b100000000111000001100000010100000100000000110000001000000001 5
1&
b100000000111000001100000010100000100000000110000001000000001 =
#200
0&
#250
b111 7
b100000000111000001100000010100000100000000110000001000000001 9
0+
1&
#300
0&
#350
1;
16
1!
b1000000001110000011000000101000001000000001100000010 9
b1 %
b1 8
b1 :
1&
#400
0&
#450
b1 $
b1 <
b10 %
b10 8
b10 :
b110 7
b10000000011100000110000001010000010000000011 9
1&
#500
0&
#550
b101 7
b100000000111000001100000010100000100 9
b11 %
b11 8
b11 :
b10 $
b10 <
1&
#600
0&
#650
b11 $
b11 <
b100 %
b100 8
b100 :
b100 7
b1000000001110000011000000101 9
1&
#700
0&
#750
b11 7
b10000000011100000110 9
b101 %
b101 8
b101 :
b100 $
b100 <
1&
#800
0&
#850
b101 $
b101 <
b110 %
b110 8
b110 :
b10 7
b100000000111 9
1&
#900
0&
#950
b1 7
b1000 9
b111 %
b111 8
b111 :
b110 $
b110 <
1&
#1000
0&
#1050
b111 $
b111 <
b1000 %
b1000 8
b1000 :
1#
b0 7
1&
#1100
0&
#1150
0;
06
0!
0#
b1000 $
b1000 <
1&
#1200
0&
#1250
b0 $
b0 <
1&
#1300
0&
#1350
1&
#1400
0&
#1450
1+
1&
#1500
0&
#1550
b111 7
b100000000111000001100000010100000100000000110000001000000001 9
0+
1&
#1600
0&
#1650
1;
16
1!
b1000000001110000011000000101000001000000001100000010 9
b1 %
b1 8
b1 :
1&
#1700
0&
#1750
b110 7
b10000000011100000110000001010000010000000011 9
b10 %
b10 8
b10 :
b1 $
b1 <
1&
#1800
0&
#1850
0;
06
b10 $
b10 <
0"
b11 %
b11 8
b11 :
b101 7
b100000000111000001100000010100000100 9
1)
1&
#1900
0&
#1950
b0 $
b0 <
1&
#2000
0&
#2050
1&
#2100
0&
#2150
1&
#2200
0&
#2250
1&
#2300
0&
#2350
1;
16
1"
1&
0)
#2400
0&
#2450
b11 $
b11 <
b100 %
b100 8
b100 :
b100 7
b1000000001110000011000000101 9
1&
#2500
0&
#2550
b11 7
b10000000011100000110 9
b101 %
b101 8
b101 :
b100 $
b100 <
1&
#2600
0&
#2650
b101 $
b101 <
b110 %
b110 8
b110 :
b10 7
b100000000111 9
1&
#2700
0&
#2750
b1 7
b1000 9
b111 %
b111 8
b111 :
b110 $
b110 <
1&
#2800
0&
#2850
b111 $
b111 <
b1000 %
b1000 8
b1000 :
1#
b0 7
1&
#2900
0&
#2950
0;
06
0!
0#
b1000 $
b1000 <
1&
#3000
0&
#3050
b0 $
b0 <
1&
#3100
0&
#3150
1+
1&
#3200
0&
#3250
b111 7
b100000000111000001100000010100000100000000110000001000000001 9
0+
1&
#3300
0&
#3350
1;
16
1!
b1000000001110000011000000101000001000000001100000010 9
b1 %
b1 8
b1 :
1&
#3400
0&
#3450
b1 $
b1 <
b10 %
b10 8
b10 :
b110 7
b10000000011100000110000001010000010000000011 9
1&
#3500
0&
#3550
b101 7
b100000000111000001100000010100000100 9
b11 %
b11 8
b11 :
b10 $
b10 <
1+
1&
#3600
0&
#3650
0;
06
b11 $
b11 <
b100 %
b100 8
b100 :
b111 7
b100000000111000001100000010100000100000000110000001000000001 9
0!
0+
1&
#3700
0&
#3750
1;
16
1!
b1000000001110000011000000101000001000000001100000010 9
b1 %
b1 8
b1 :
b0 $
b0 <
1&
#3800
0&
#3850
b1 $
b1 <
b10 %
b10 8
b10 :
b110 7
b10000000011100000110000001010000010000000011 9
1&
#3900
0&
#3950
b101 7
b100000000111000001100000010100000100 9
b11 %
b11 8
b11 :
b10 $
b10 <
1&
#4000
0&
#4050
b11 $
b11 <
b100 %
b100 8
b100 :
b100 7
b1000000001110000011000000101 9
1&
#4100
0&
#4150
b11 7
b10000000011100000110 9
b101 %
b101 8
b101 :
b100 $
b100 <
1&
#4200
0&
#4250
b101 $
b101 <
b110 %
b110 8
b110 :
b10 7
b100000000111 9
1&
#4300
0&
#4350
b1 7
b1000 9
b111 %
b111 8
b111 :
b110 $
b110 <
1&
#4400
0&
#4450
b111 $
b111 <
b1000 %
b1000 8
b1000 :
1#
b0 7
1&
#4500
0&
#4550
0;
06
0!
0#
b1000 $
b1000 <
1&
#4600
0&
#4650
b0 $
b0 <
1+
1&
#4700
0&
#4750
b111 7
b100000000111000001100000010100000100000000110000001000000001 9
0+
1&
#4800
0&
#4850
1;
16
1!
b1000000001110000011000000101000001000000001100000010 9
b1 %
b1 8
b1 :
1&
#4900
0&
#4950
b110 7
b10000000011100000110000001010000010000000011 9
b10 %
b10 8
b10 :
b1 $
b1 <
1&
#5000
0&
#5050
0;
06
b0 $
b0 <
0"
b0 %
b0 8
b0 :
b0 7
b0 9
0!
0(
1&
#5100
0&
#5150
1&
#5200
0&
#5250
1&
#5300
0&
#5350
1"
1&
1(
#5400
0&
#5450
1&
#5500
0&
#5550
1&
#5600
0&
#5650
1&
#5700
0&
#5750
1+
1&
#5800
0&
#5850
b111 7
b100000000111000001100000010100000100000000110000001000000001 9
0+
b0 ,
1&
#5900
0&
#5950
1;
16
1!
b1000000001110000011000000101000001000000001100000010 9
b1 %
b1 8
b1 :
1&
#6000
0&
#6050
b1 $
b1 <
b10 %
b10 8
b10 :
b110 7
b10000000011100000110000001010000010000000011 9
b1 ,
1&
#6100
0&
#6150
b101 7
b100000000111000001100000010100000100 9
b11 %
b11 8
b11 :
b10 $
b10 <
b10 ,
1&
#6200
0&
#6250
b11 $
b11 <
b100 %
b100 8
b100 :
b100 7
b1000000001110000011000000101 9
b11 ,
1&
#6300
0&
#6350
b11 7
b10000000011100000110 9
b101 %
b101 8
b101 :
b100 $
b100 <
b100 ,
1&
#6400
0&
#6450
b101 $
b101 <
b110 %
b110 8
b110 :
b10 7
b100000000111 9
b101 ,
1&
#6500
0&
#6550
b1 7
b1000 9
b111 %
b111 8
b111 :
b110 $
b110 <
b110 ,
1&
#6600
0&
#6650
b111 $
b111 <
b1000 %
b1000 8
b1000 :
1#
b0 7
b111 ,
1&
#6700
0&
#6750
0;
06
0!
0#
b1000 $
b1000 <
1&
#6800
0&
#6850
b0 $
b0 <
1+
1&
#6900
0&
#6950
b111 7
b100000000111000001100000010100000100000000110000001000000001 9
0+
1&
#7000
0&
#7050
1;
16
1!
b1000000001110000011000000101000001000000001100000010 9
b1 %
b1 8
b1 :
1&
#7100
0&
#7150
b110 7
b10000000011100000110000001010000010000000011 9
b10 %
b10 8
b10 :
b1 $
b1 <
1&
#7200
0&
#7250
b10 $
b10 <
b11 %
b11 8
b11 :
b101 7
b100000000111000001100000010100000100 9
1&
#7300
0&
#7350
b100 7
b1000000001110000011000000101 9
b100 %
b100 8
b100 :
b11 $
b11 <
1&
#7400
0&
#7450
b100 $
b100 <
b101 %
b101 8
b101 :
b11 7
b10000000011100000110 9
1&
#7500
0&
#7550
b10 7
b100000000111 9
b110 %
b110 8
b110 :
b101 $
b101 <
1&
#7600
0&
#7650
b110 $
b110 <
b111 %
b111 8
b111 :
b1 7
b1000 9
1&
#7700
0&
#7750
b0 7
b1000 %
b1000 8
b1000 :
1#
b111 $
b111 <
1&
#7800
0&
#7850
0;
06
b1000 $
b1000 <
0#
0!
1&
#7900
0&
#7950
b0 $
b0 <
1&
