tasks/01_03_LU_cache/code/NOR.v
module NOR #(
    parameter WIDTH = 8
)(
    input [WIDTH - 1:0] in,
    output out 
);

assign out = ~(|in) ? 1 : 0;

endmodule // NOR

tasks/task_03_LU_cache/code/XOR.v
module XOR #(
    parameter WIDTH = 8
)
(
    input [WIDTH - 1:0] in_1,
    input [WIDTH - 1:0] in_2,
    output [WIDTH - 1:0] out
);

assign out = in_1 ^ in_2;

endmodule // XOR

tasks/task_03_LU_cache/code/memory_cell.v
`include "XOR.v"
`include "NOR.v"

module memory_cell #(
    parameter CELL_SIZE = 8,
    parameter CELL_ADDR = 0,
    parameter ADDR_SIZE = 3
)(
    input clk,
    input reset,
    input wen,
    input priority_wen,
    input [CELL_SIZE - 1:0] input_data,
    input [CELL_SIZE - 1:0] check_data,
    input [ADDR_SIZE - 1:0] input_addr,
    output eq,
    output [ADDR_SIZE - 1:0] output_addr,
    output reg [CELL_SIZE - 1:0] output_data = 0
);

//объявляем и сохраняем адрес ячейки
reg [ADDR_SIZE - 1:0] cell_addr = CELL_ADDR;

//объявляем и задаём вспомагательные сигналы
wire [CELL_SIZE - 1:0] temp_data;

XOR #(
    .WIDTH(CELL_SIZE)
) DD1 (
    .in_1(check_data),
    .in_2(output_data),
    .out(temp_data)
);

NOR #(
    .WIDTH(CELL_SIZE)
) DD2 (
    .in(temp_data),
    .out(eq)
);

//передача адреса
assign output_addr = eq ? cell_addr : 0;

always @(posedge clk or negedge reset) begin 
    //проверяем reset
    if (!(reset)) output_data <= 0;
    else if (((wen) && (cell_addr <= input_addr)) || priority_wen) output_data <= input_data; 
end

endmodule // memory_cell

tasks/task_03_LU_cache/code/LU_cache.v
`include "memory_cell.v"

module LU_cache #(
    parameter CELL_SIZE = 8,
    parameter CELL_COUNT = 8,
    parameter CELL_ADDR_SIZE = 3
)
(
    input clk,
    input reset,
    input [CELL_SIZE - 1:0] data_in,
    input new_data,
    output [CELL_COUNT - 1:0][CELL_SIZE - 1:0] data_out
);

//объявляем служебные сигналы
wire [CELL_ADDR_SIZE - 1:0] addr; //шина адреса
wire [CELL_COUNT - 1:0][CELL_ADDR_SIZE-1:0] addr_array;
wire eq;
wire [CELL_COUNT - 1:0] eq_array;
wire priority_wen;

//подключаем модули
genvar i;
generate 
    for (i = 0; i < CELL_COUNT; i = i + 1) begin : memory_cel_modules
        if (i == 0) begin
            memory_cell #(
                .CELL_SIZE(CELL_SIZE),
                .ADDR_SIZE(CELL_ADDR_SIZE),
                .CELL_ADDR(i)
            ) CELL (
                .clk(clk),
                .reset(reset),
                .wen(new_data),
                .priority_wen(priority_wen),
                .input_data(data_in),
                .check_data(data_in),
                .input_addr(addr),
                .eq(eq_array[i]),
                .output_addr(addr_array[i]),
                .output_data(data_out[i])
            );
        end else begin
            memory_cell #(
                .CELL_SIZE(CELL_SIZE),
                .ADDR_SIZE(CELL_ADDR_SIZE),
                .CELL_ADDR(i)
            ) CELL (
                .clk(clk),
                .reset(reset),
                .wen(new_data),
                .priority_wen(priority_wen),
                .input_data(data_out[i-1]),
                .check_data(data_in),
                .input_addr(addr),
                .eq(eq_array[i]),
                .output_addr(addr_array[i]),
                .output_data(data_out[i])
            );
        end
    end
endgenerate

//связываем нужные сигналы
assign priority_wen = (!eq & new_data) ? 1 : 0;

assign eq = |eq_array;

// Создаем блок ИЛИ для каждого бита
genvar bit_idx;
generate
    for (bit_idx = 0; bit_idx < CELL_ADDR_SIZE; bit_idx = bit_idx + 1) begin : or_bit
        // Создаем провод для всех входов ИЛИ для этого бита
        wire [CELL_COUNT-1:0] or_inputs;
        
        // Собираем значения бита от всех ячеек
        for (i = 0; i < CELL_COUNT; i = i + 1) begin : collect_bits
            assign or_inputs[i] = addr_array[i][bit_idx];
        end
        
        // Реализуем ИЛИ через побитовое ИЛИ (|)
        assign addr[bit_idx] = |or_inputs;
    end
endgenerate
endmodule // LU_cache

tasks/01_03_LU_cache/testbenches/LU_cache_tb.v
// задаём временную шкалу
`timescale 10 ps/ 1 ps

module LU_cache_test;

//dump для GTKWAVE
initial begin
    $dumpfile("LU_cache_simulation.vcd");
    $dumpvars(0, LU_cache_test);
end

//объявляем и задаём входные сигналы
reg clk = 1'b0;
always #5 clk <= ~clk;


reg reset = 1'b1;
reg new_data = 1'b0;

reg [7:0] x = 275;
initial begin
    #5 x = 9;
    new_data = 1'b1;
    #1 new_data = 1'b0;
    #9 x = 1;
    new_data = 1'b1;
    #1 new_data = 1'b0;
    #9 x = 2;
    new_data = 1'b1;
    #1 new_data = 1'b0;
    #9 x = 4;
    new_data = 1'b1;
    #1 new_data = 1'b0;
    #9 x = 5;
    new_data = 1'b1;
    #1 new_data = 1'b0;
    #9 x = 6;
    new_data = 1'b1;
    #1 new_data = 1'b0;
    #9 x = 7;
    new_data = 1'b1;
    #1 new_data = 1'b0;
    #9 x = 8;
    new_data = 1'b1;
    #1 new_data = 1'b0;
    #9 x = 1;
    new_data = 1'b1;
    #1 new_data = 1'b0;
    #9 x = 5;
    new_data = 1'b1;
    #1 new_data = 1'b0;
    #19 x = 9;
    new_data = 1'b1;
    #1 new_data = 1'b0;
    #9 x = 3;
    new_data = 1'b1;
    #1 new_data = 1'b0;
    #9 x = 7;
    new_data = 1'b1;
    #1 new_data = 1'b0;
end

// объявляем выходные сигналы
wire [7:0][7:0] output_data;

//подключаем модуль
LU_cache #(
    .CELL_SIZE(8),
    .CELL_COUNT(8),
    .CELL_ADDR_SIZE(3)
) CACHE (
    .clk(clk),
    .reset(reset),
    .data_in(x),
    .new_data(new_data),
    .data_out(output_data)
);

//включаем мониторнг сигналов
initial  begin
    #5000 $finish;
end

endmodule // memory_cell_test

tasks/task_03_LU_cache/simulation/files/LU_cache_simulation.vcd
$date
	Mon Dec  1 23:54:11 2025
$end
$version
	Icarus Verilog
$end
$timescale
	1ps
$end
$scope module LU_cache_test $end
$var wire 64 ! output_data [63:0] $end
$var reg 1 " clk $end
$var reg 1 # new_data $end
$var reg 1 $ reset $end
$var reg 8 % x [7:0] $end
$scope module CACHE $end
$var wire 1 " clk $end
$var wire 8 & data_in [7:0] $end
$var wire 1 # new_data $end
$var wire 1 $ reset $end
$var wire 1 ' priority_wen $end
$var wire 8 ( eq_array [7:0] $end
$var wire 1 ) eq $end
$var wire 64 * data_out [63:0] $end
$var wire 24 + addr_array [23:0] $end
$var wire 3 , addr [2:0] $end
$var parameter 32 - CELL_ADDR_SIZE $end
$var parameter 32 . CELL_COUNT $end
$var parameter 32 / CELL_SIZE $end
$scope begin memory_cel_modules[0] $end
$var parameter 2 0 i $end
$scope begin genblk1 $end
$scope module CELL $end
$var wire 8 1 check_data [7:0] $end
$var wire 1 " clk $end
$var wire 3 2 input_addr [2:0] $end
$var wire 8 3 input_data [7:0] $end
$var wire 1 ' priority_wen $end
$var wire 1 $ reset $end
$var wire 1 # wen $end
$var wire 8 4 temp_data [7:0] $end
$var wire 3 5 output_addr [2:0] $end
$var wire 1 6 eq $end
$var parameter 32 7 ADDR_SIZE $end
$var parameter 32 8 CELL_ADDR $end
$var parameter 32 9 CELL_SIZE $end
$var reg 3 : cell_addr [2:0] $end
$var reg 8 ; output_data [7:0] $end
$scope module DD1 $end
$var wire 8 < in_1 [7:0] $end
$var wire 8 = in_2 [7:0] $end
$var wire 8 > out [7:0] $end
$var parameter 32 ? WIDTH $end
$upscope $end
$scope module DD2 $end
$var wire 8 @ in [7:0] $end
$var wire 1 6 out $end
$var parameter 32 A WIDTH $end
$upscope $end
$upscope $end
$upscope $end
$upscope $end
$scope begin memory_cel_modules[1] $end
$var parameter 2 B i $end
$scope begin genblk1 $end
$scope module CELL $end
$var wire 8 C check_data [7:0] $end
$var wire 1 " clk $end
$var wire 3 D input_addr [2:0] $end
$var wire 8 E input_data [7:0] $end
$var wire 1 ' priority_wen $end
$var wire 1 $ reset $end
$var wire 1 # wen $end
$var wire 8 F temp_data [7:0] $end
$var wire 3 G output_addr [2:0] $end
$var wire 1 H eq $end
$var parameter 32 I ADDR_SIZE $end
$var parameter 32 J CELL_ADDR $end
$var parameter 32 K CELL_SIZE $end
$var reg 3 L cell_addr [2:0] $end
$var reg 8 M output_data [7:0] $end
$scope module DD1 $end
$var wire 8 N in_1 [7:0] $end
$var wire 8 O in_2 [7:0] $end
$var wire 8 P out [7:0] $end
$var parameter 32 Q WIDTH $end
$upscope $end
$scope module DD2 $end
$var wire 8 R in [7:0] $end
$var wire 1 H out $end
$var parameter 32 S WIDTH $end
$upscope $end
$upscope $end
$upscope $end
$upscope $end
$scope begin memory_cel_modules[2] $end
$var parameter 3 T i $end
$scope begin genblk1 $end
$scope module CELL $end
$var wire 8 U check_data [7:0] $end
$var wire 1 " clk $end
$var wire 3 V input_addr [2:0] $end
$var wire 8 W input_data [7:0] $end
$var wire 1 ' priority_wen $end
$var wire 1 $ reset $end
$var wire 1 # wen $end
$var wire 8 X temp_data [7:0] $end
$var wire 3 Y output_addr [2:0] $end
$var wire 1 Z eq $end
$var parameter 32 [ ADDR_SIZE $end
$var parameter 32 \ CELL_ADDR $end
$var parameter 32 ] CELL_SIZE $end
$var reg 3 ^ cell_addr [2:0] $end
$var reg 8 _ output_data [7:0] $end
$scope module DD1 $end
$var wire 8 ` in_1 [7:0] $end
$var wire 8 a in_2 [7:0] $end
$var wire 8 b out [7:0] $end
$var parameter 32 c WIDTH $end
$upscope $end
$scope module DD2 $end
$var wire 8 d in [7:0] $end
$var wire 1 Z out $end
$var parameter 32 e WIDTH $end
$upscope $end
$upscope $end
$upscope $end
$upscope $end
$scope begin memory_cel_modules[3] $end
$var parameter 3 f i $end
$scope begin genblk1 $end
$scope module CELL $end
$var wire 8 g check_data [7:0] $end
$var wire 1 " clk $end
$var wire 3 h input_addr [2:0] $end
$var wire 8 i input_data [7:0] $end
$var wire 1 ' priority_wen $end
$var wire 1 $ reset $end
$var wire 1 # wen $end
$var wire 8 j temp_data [7:0] $end
$var wire 3 k output_addr [2:0] $end
$var wire 1 l eq $end
$var parameter 32 m ADDR_SIZE $end
$var parameter 32 n CELL_ADDR $end
$var parameter 32 o CELL_SIZE $end
$var reg 3 p cell_addr [2:0] $end
$var reg 8 q output_data [7:0] $end
$scope module DD1 $end
$var wire 8 r in_1 [7:0] $end
$var wire 8 s in_2 [7:0] $end
$var wire 8 t out [7:0] $end
$var parameter 32 u WIDTH $end
$upscope $end
$scope module DD2 $end
$var wire 8 v in [7:0] $end
$var wire 1 l out $end
$var parameter 32 w WIDTH $end
$upscope $end
$upscope $end
$upscope $end
$upscope $end
$scope begin memory_cel_modules[4] $end
$var parameter 4 x i $end
$scope begin genblk1 $end
$scope module CELL $end
$var wire 8 y check_data [7:0] $end
$var wire 1 " clk $end
$var wire 3 z input_addr [2:0] $end
$var wire 8 { input_data [7:0] $end
$var wire 1 ' priority_wen $end
$var wire 1 $ reset $end
$var wire 1 # wen $end
$var wire 8 | temp_data [7:0] $end
$var wire 3 } output_addr [2:0] $end
$var wire 1 ~ eq $end
$var parameter 32 !" ADDR_SIZE $end
$var parameter 32 "" CELL_ADDR $end
$var parameter 32 #" CELL_SIZE $end
$var reg 3 $" cell_addr [2:0] $end
$var reg 8 %" output_data [7:0] $end
$scope module DD1 $end
$var wire 8 &" in_1 [7:0] $end
$var wire 8 '" in_2 [7:0] $end
$var wire 8 (" out [7:0] $end
$var parameter 32 )" WIDTH $end
$upscope $end
$scope module DD2 $end
$var wire 8 *" in [7:0] $end
$var wire 1 ~ out $end
$var parameter 32 +" WIDTH $end
$upscope $end
$upscope $end
$upscope $end
$upscope $end
$scope begin memory_cel_modules[5] $end
$var parameter 4 ," i $end
$scope begin genblk1 $end
$scope module CELL $end
$var wire 8 -" check_data [7:0] $end
$var wire 1 " clk $end
$var wire 3 ." input_addr [2:0] $end
$var wire 8 /" input_data [7:0] $end
$var wire 1 ' priority_wen $end
$var wire 1 $ reset $end
$var wire 1 # wen $end
$var wire 8 0" temp_data [7:0] $end
$var wire 3 1" output_addr [2:0] $end
$var wire 1 2" eq $end
$var parameter 32 3" ADDR_SIZE $end
$var parameter 32 4" CELL_ADDR $end
$var parameter 32 5" CELL_SIZE $end
$var reg 3 6" cell_addr [2:0] $end
$var reg 8 7" output_data [7:0] $end
$scope module DD1 $end
$var wire 8 8" in_1 [7:0] $end
$var wire 8 9" in_2 [7:0] $end
$var wire 8 :" out [7:0] $end
$var parameter 32 ;" WIDTH $end
$upscope $end
$scope module DD2 $end
$var wire 8 <" in [7:0] $end
$var wire 1 2" out $end
$var parameter 32 =" WIDTH $end
$upscope $end
$upscope $end
$upscope $end
$upscope $end
$scope begin memory_cel_modules[6] $end
$var parameter 4 >" i $end
$scope begin genblk1 $end
$scope module CELL $end
$var wire 8 ?" check_data [7:0] $end
$var wire 1 " clk $end
$var wire 3 @" input_addr [2:0] $end
$var wire 8 A" input_data [7:0] $end
$var wire 1 ' priority_wen $end
$var wire 1 $ reset $end
$var wire 1 # wen $end
$var wire 8 B" temp_data [7:0] $end
$var wire 3 C" output_addr [2:0] $end
$var wire 1 D" eq $end
$var parameter 32 E" ADDR_SIZE $end
$var parameter 32 F" CELL_ADDR $end
$var parameter 32 G" CELL_SIZE $end
$var reg 3 H" cell_addr [2:0] $end
$var reg 8 I" output_data [7:0] $end
$scope module DD1 $end
$var wire 8 J" in_1 [7:0] $end
$var wire 8 K" in_2 [7:0] $end
$var wire 8 L" out [7:0] $end
$var parameter 32 M" WIDTH $end
$upscope $end
$scope module DD2 $end
$var wire 8 N" in [7:0] $end
$var wire 1 D" out $end
$var parameter 32 O" WIDTH $end
$upscope $end
$upscope $end
$upscope $end
$upscope $end
$scope begin memory_cel_modules[7] $end
$var parameter 4 P" i $end
$scope begin genblk1 $end
$scope module CELL $end
$var wire 8 Q" check_data [7:0] $end
$var wire 1 " clk $end
$var wire 3 R" input_addr [2:0] $end
$var wire 8 S" input_data [7:0] $end
$var wire 1 ' priority_wen $end
$var wire 1 $ reset $end
$var wire 1 # wen $end
$var wire 8 T" temp_data [7:0] $end
$var wire 3 U" output_addr [2:0] $end
$var wire 1 V" eq $end
$var parameter 32 W" ADDR_SIZE $end
$var parameter 32 X" CELL_ADDR $end
$var parameter 32 Y" CELL_SIZE $end
$var reg 3 Z" cell_addr [2:0] $end
$var reg 8 [" output_data [7:0] $end
$scope module DD1 $end
$var wire 8 \" in_1 [7:0] $end
$var wire 8 ]" in_2 [7:0] $end
$var wire 8 ^" out [7:0] $end
$var parameter 32 _" WIDTH $end
$upscope $end
$scope module DD2 $end
$var wire 8 `" in [7:0] $end
$var wire 1 V" out $end
$var parameter 32 a" WIDTH $end
$upscope $end
$upscope $end
$upscope $end
$upscope $end
$scope begin or_bit[0] $end
$var wire 8 b" or_inputs [7:0] $end
$var parameter 2 c" bit_idx $end
$scope begin collect_bits[0] $end
$var parameter 2 d" i $end
$upscope $end
$scope begin collect_bits[1] $end
$var parameter 2 e" i $end
$upscope $end
$scope begin collect_bits[2] $end
$var parameter 3 f" i $end
$upscope $end
$scope begin collect_bits[3] $end
$var parameter 3 g" i $end
$upscope $end
$scope begin collect_bits[4] $end
$var parameter 4 h" i $end
$upscope $end
$scope begin collect_bits[5] $end
$var parameter 4 i" i $end
$upscope $end
$scope begin collect_bits[6] $end
$var parameter 4 j" i $end
$upscope $end
$scope begin collect_bits[7] $end
$var parameter 4 k" i $end
$upscope $end
$upscope $end
$scope begin or_bit[1] $end
$var wire 8 l" or_inputs [7:0] $end
$var parameter 2 m" bit_idx $end
$scope begin collect_bits[0] $end
$var parameter 2 n" i $end
$upscope $end
$scope begin collect_bits[1] $end
$var parameter 2 o" i $end
$upscope $end
$scope begin collect_bits[2] $end
$var parameter 3 p" i $end
$upscope $end
$scope begin collect_bits[3] $end
$var parameter 3 q" i $end
$upscope $end
$scope begin collect_bits[4] $end
$var parameter 4 r" i $end
$upscope $end
$scope begin collect_bits[5] $end
$var parameter 4 s" i $end
$upscope $end
$scope begin collect_bits[6] $end
$var parameter 4 t" i $end
$upscope $end
$scope begin collect_bits[7] $end
$var parameter 4 u" i $end
$upscope $end
$upscope $end
$scope begin or_bit[2] $end
$var wire 8 v" or_inputs [7:0] $end
$var parameter 3 w" bit_idx $end
$scope begin collect_bits[0] $end
$var parameter 2 x" i $end
$upscope $end
$scope begin collect_bits[1] $end
$var parameter 2 y" i $end
$upscope $end
$scope begin collect_bits[2] $end
$var parameter 3 z" i $end
$upscope $end
$scope begin collect_bits[3] $end
$var parameter 3 {" i $end
$upscope $end
$scope begin collect_bits[4] $end
$var parameter 4 |" i $end
$upscope $end
$scope begin collect_bits[5] $end
$var parameter 4 }" i $end
$upscope $end
$scope begin collect_bits[6] $end
$var parameter 4 ~" i $end
$upscope $end
$scope begin collect_bits[7] $end
$var parameter 4 !# i $end
$upscope $end
$upscope $end
$upscope $end
$upscope $end
$enddefinitions $end
$comment Show the parameter values. $end
$dumpall
b111 !#
b110 ~"
b101 }"
b100 |"
b11 {"
b10 z"
b1 y"
b0 x"
b10 w"
b111 u"
b110 t"
b101 s"
b100 r"
b11 q"
b10 p"
b1 o"
b0 n"
b1 m"
b111 k"
b110 j"
b101 i"
b100 h"
b11 g"
b10 f"
b1 e"
b0 d"
b0 c"
b1000 a"
b1000 _"
b1000 Y"
b111 X"
b11 W"
b111 P"
b1000 O"
b1000 M"
b1000 G"
b110 F"
b11 E"
b110 >"
b1000 ="
b1000 ;"
b1000 5"
b101 4"
b11 3"
b101 ,"
b1000 +"
b1000 )"
b1000 #"
b100 ""
b11 !"
b100 x
b1000 w
b1000 u
b1000 o
b11 n
b11 m
b11 f
b1000 e
b1000 c
b1000 ]
b10 \
b11 [
b10 T
b1000 S
b1000 Q
b1000 K
b1 J
b11 I
b1 B
b1000 A
b1000 ?
b1000 9
b0 8
b11 7
b0 0
b1000 /
b1000 .
b11 -
$end
#0
$dumpvars
b0 v"
b0 l"
b0 b"
b10011 `"
b10011 ^"
b0 ]"
b10011 \"
b0 ["
b111 Z"
0V"
b0 U"
b10011 T"
b0 S"
b0 R"
b10011 Q"
b10011 N"
b10011 L"
b0 K"
b10011 J"
b0 I"
b110 H"
0D"
b0 C"
b10011 B"
b0 A"
b0 @"
b10011 ?"
b10011 <"
b10011 :"
b0 9"
b10011 8"
b0 7"
b101 6"
02"
b0 1"
b10011 0"
b0 /"
b0 ."
b10011 -"
b10011 *"
b10011 ("
b0 '"
b10011 &"
b0 %"
b100 $"
0~
b0 }
b10011 |
b0 {
b0 z
b10011 y
b10011 v
b10011 t
b0 s
b10011 r
b0 q
b11 p
0l
b0 k
b10011 j
b0 i
b0 h
b10011 g
b10011 d
b10011 b
b0 a
b10011 `
b0 _
b10 ^
0Z
b0 Y
b10011 X
b0 W
b0 V
b10011 U
b10011 R
b10011 P
b0 O
b10011 N
b0 M
b1 L
0H
b0 G
b10011 F
b0 E
b0 D
b10011 C
b10011 @
b10011 >
b0 =
b10011 <
b0 ;
b0 :
06
b0 5
b10011 4
b10011 3
b0 2
b10011 1
b0 ,
b0 +
b0 *
0)
b0 (
0'
b10011 &
b10011 %
1$
0#
0"
b0 !
$end
#50
1)
b1 (
16
b1001 E
b1001 !
b1001 *
b1001 ;
b1001 =
1"
0'
b0 4
b0 >
b0 @
b1001 F
b1001 P
b1001 R
b1001 X
b1001 b
b1001 d
b1001 j
b1001 t
b1001 v
b1001 |
b1001 ("
b1001 *"
b1001 0"
b1001 :"
b1001 <"
b1001 B"
b1001 L"
b1001 N"
b1001 T"
b1001 ^"
b1001 `"
1#
b1001 %
b1001 &
b1001 1
b1001 3
b1001 <
b1001 C
b1001 N
b1001 U
b1001 `
b1001 g
b1001 r
b1001 y
b1001 &"
b1001 -"
b1001 8"
b1001 ?"
b1001 J"
b1001 Q"
b1001 \"
#60
0#
#100
0"
#150
b1001 W
b1 E
b1001 M
b1001 O
b100100000001 !
b100100000001 *
b1 ;
b1 =
1"
0'
1)
b1 (
16
b0 4
b0 >
b0 @
b1000 F
b1000 P
b1000 R
b1 X
b1 b
b1 d
b1 j
b1 t
b1 v
b1 |
b1 ("
b1 *"
b1 0"
b1 :"
b1 <"
b1 B"
b1 L"
b1 N"
b1 T"
b1 ^"
b1 `"
1#
b1 %
b1 &
b1 1
b1 3
b1 <
b1 C
b1 N
b1 U
b1 `
b1 g
b1 r
b1 y
b1 &"
b1 -"
b1 8"
b1 ?"
b1 J"
b1 Q"
b1 \"
#160
0#
#200
0"
#250
b10 E
b1 W
b1001 i
b10 ;
b10 =
b1 M
b1 O
b10010000000100000010 !
b10010000000100000010 *
b1001 _
b1001 a
1"
0'
1)
b1 (
16
b0 4
b0 >
b0 @
b11 F
b11 P
b11 R
b1011 X
b1011 b
b1011 d
b10 j
b10 t
b10 v
b10 |
b10 ("
b10 *"
b10 0"
b10 :"
b10 <"
b10 B"
b10 L"
b10 N"
b10 T"
b10 ^"
b10 `"
1#
b10 %
b10 &
b10 1
b10 3
b10 <
b10 C
b10 N
b10 U
b10 `
b10 g
b10 r
b10 y
b10 &"
b10 -"
b10 8"
b10 ?"
b10 J"
b10 Q"
b10 \"
#260
0#
#300
0"
#350
b1001 {
b1 i
b10 W
b100 E
b1001 q
b1001 s
b1 _
b1 a
b10 M
b10 O
b1001000000010000001000000100 !
b1001000000010000001000000100 *
b100 ;
b100 =
1"
0'
1)
b1 (
16
b0 4
b0 >
b0 @
b110 F
b110 P
b110 R
b101 X
b101 b
b101 d
b1101 j
b1101 t
b1101 v
b100 |
b100 ("
b100 *"
b100 0"
b100 :"
b100 <"
b100 B"
b100 L"
b100 N"
b100 T"
b100 ^"
b100 `"
1#
b100 %
b100 &
b100 1
b100 3
b100 <
b100 C
b100 N
b100 U
b100 `
b100 g
b100 r
b100 y
b100 &"
b100 -"
b100 8"
b100 ?"
b100 J"
b100 Q"
b100 \"
#360
0#
#400
0"
#450
b101 E
b100 W
b10 i
b1 {
b1001 /"
b101 ;
b101 =
b100 M
b100 O
b10 _
b10 a
b1 q
b1 s
b100100000001000000100000010000000101 !
b100100000001000000100000010000000101 *
b1001 %"
b1001 '"
1"
0'
1)
b1 (
16
b0 4
b0 >
b0 @
b1 F
b1 P
b1 R
b111 X
b111 b
b111 d
b100 j
b100 t
b100 v
b1100 |
b1100 ("
b1100 *"
b101 0"
b101 :"
b101 <"
b101 B"
b101 L"
b101 N"
b101 T"
b101 ^"
b101 `"
1#
b101 %
b101 &
b101 1
b101 3
b101 <
b101 C
b101 N
b101 U
b101 `
b101 g
b101 r
b101 y
b101 &"
b101 -"
b101 8"
b101 ?"
b101 J"
b101 Q"
b101 \"
#460
0#
#500
0"
#550
b1001 A"
b1 /"
b10 {
b100 i
b101 W
b110 E
b1001 7"
b1001 9"
b1 %"
b1 '"
b10 q
b10 s
b100 _
b100 a
b101 M
b101 O
b10010000000100000010000001000000010100000110 !
b10010000000100000010000001000000010100000110 *
b110 ;
b110 =
1"
0'
1)
b1 (
16
b0 4
b0 >
b0 @
b11 F
b11 P
b11 R
b10 X
b10 b
b10 d
b100 j
b100 t
b100 v
b111 |
b111 ("
b111 *"
b1111 0"
b1111 :"
b1111 <"
b110 B"
b110 L"
b110 N"
b110 T"
b110 ^"
b110 `"
1#
b110 %
b110 &
b110 1
b110 3
b110 <
b110 C
b110 N
b110 U
b110 `
b110 g
b110 r
b110 y
b110 &"
b110 -"
b110 8"
b110 ?"
b110 J"
b110 Q"
b110 \"
#560
0#
#600
0"
#650
b111 E
b110 W
b101 i
b100 {
b10 /"
b1 A"
b1001 S"
b111 ;
b111 =
b110 M
b110 O
b101 _
b101 a
b100 q
b100 s
b10 %"
b10 '"
b1 7"
b1 9"
b1001000000010000001000000100000001010000011000000111 !
b1001000000010000001000000100000001010000011000000111 *
b1001 I"
b1001 K"
1"
0'
1)
b1 (
16
b0 4
b0 >
b0 @
b1 F
b1 P
b1 R
b10 X
b10 b
b10 d
b11 j
b11 t
b11 v
b101 |
b101 ("
b101 *"
b110 0"
b110 :"
b110 <"
b1110 B"
b1110 L"
b1110 N"
b111 T"
b111 ^"
b111 `"
1#
b111 %
b111 &
b111 1
b111 3
b111 <
b111 C
b111 N
b111 U
b111 `
b111 g
b111 r
b111 y
b111 &"
b111 -"
b111 8"
b111 ?"
b111 J"
b111 Q"
b111 \"
#660
0#
#700
0"
#750
b1 S"
b10 A"
b100 /"
b101 {
b110 i
b111 W
b1000 E
b1001 ["
b1001 ]"
b1 I"
b1 K"
b10 7"
b10 9"
b100 %"
b100 '"
b101 q
b101 s
b110 _
b110 a
b111 M
b111 O
b100100000001000000100000010000000101000001100000011100001000 !
b100100000001000000100000010000000101000001100000011100001000 *
b1000 ;
b1000 =
1"
0'
1)
b1 (
16
b0 4
b0 >
b0 @
b1111 F
b1111 P
b1111 R
b1110 X
b1110 b
b1110 d
b1101 j
b1101 t
b1101 v
b1100 |
b1100 ("
b1100 *"
b1010 0"
b1010 :"
b1010 <"
b1001 B"
b1001 L"
b1001 N"
b1 T"
b1 ^"
b1 `"
1#
b1000 %
b1000 &
b1000 1
b1000 3
b1000 <
b1000 C
b1000 N
b1000 U
b1000 `
b1000 g
b1000 r
b1000 y
b1000 &"
b1000 -"
b1000 8"
b1000 ?"
b1000 J"
b1000 Q"
b1000 \"
#760
0#
#800
0"
#850
1)
b1 E
b1000 W
b111 i
b110 {
b101 /"
b100 A"
b10 S"
b1 ;
b1 =
b1000 M
b1000 O
b111 _
b111 a
b110 q
b110 s
b101 %"
b101 '"
b100 7"
b100 9"
b100100000010000001000000010100000110000001110000100000000001 !
b100100000010000001000000010100000110000001110000100000000001 *
b10 I"
b10 K"
1"
b0 l"
b0 ,
b0 2
b0 D
b0 V
b0 h
b0 z
b0 ."
b0 @"
b0 R"
b0 v"
b0 +
b0 C"
16
b1 (
0D"
b0 4
b0 >
b0 @
b1001 F
b1001 P
b1001 R
b110 X
b110 b
b110 d
b111 j
b111 t
b111 v
b100 |
b100 ("
b100 *"
b101 0"
b101 :"
b101 <"
b11 B"
b11 L"
b11 N"
b1000 T"
b1000 ^"
b1000 `"
1#
b1 %
b1 &
b1 1
b1 3
b1 <
b1 C
b1 N
b1 U
b1 `
b1 g
b1 r
b1 y
b1 &"
b1 -"
b1 8"
b1 ?"
b1 J"
b1 Q"
b1 \"
#860
0#
#900
0"
#950
b110 /"
b111 {
b1000 i
b1 W
b101 E
b110 %"
b110 '"
b111 q
b111 s
b1000 _
b1000 a
b1 M
b1 O
b100100000010000001000000011000000111000010000000000100000101 !
b100100000010000001000000011000000111000010000000000100000101 *
b101 ;
b101 =
1"
b0 ,
b0 2
b0 D
b0 V
b0 h
b0 z
b0 ."
b0 @"
b0 R"
b0 v"
b0 +
b0 }
16
b1 (
0~
b0 4
b0 >
b0 @
b100 F
b100 P
b100 R
b1101 X
b1101 b
b1101 d
b10 j
b10 t
b10 v
b11 |
b11 ("
b11 *"
b1 0"
b1 :"
b1 <"
b111 B"
b111 L"
b111 N"
b1100 T"
b1100 ^"
b1100 `"
1#
b101 %
b101 &
b101 1
b101 3
b101 <
b101 C
b101 N
b101 U
b101 `
b101 g
b101 r
b101 y
b101 &"
b101 -"
b101 8"
b101 ?"
b101 J"
b101 Q"
b101 \"
#960
0#
#1000
0"
#1050
1"
#1100
0"
#1150
b100 S"
b110 A"
b111 /"
b1000 {
b1 i
b101 W
b1001 E
b10 ["
b10 ]"
b100 I"
b100 K"
b110 7"
b110 9"
b111 %"
b111 '"
b1000 q
b1000 s
b1 _
b1 a
b101 M
b101 O
b1000000100000001100000011100001000000000010000010100001001 !
b1000000100000001100000011100001000000000010000010100001001 *
b1001 ;
b1001 =
1"
b0 b"
b0 l"
b0 ,
b0 2
b0 D
b0 V
b0 h
b0 z
b0 ."
b0 @"
b0 R"
b0 v"
b0 +
b0 U"
16
b1 (
0V"
b0 4
b0 >
b0 @
b1100 F
b1100 P
b1100 R
b1000 X
b1000 b
b1000 d
b1 j
b1 t
b1 v
b1110 |
b1110 ("
b1110 *"
b1111 0"
b1111 :"
b1111 <"
b1101 B"
b1101 L"
b1101 N"
b1011 T"
b1011 ^"
b1011 `"
1#
b1001 %
b1001 &
b1001 1
b1001 3
b1001 <
b1001 C
b1001 N
b1001 U
b1001 `
b1001 g
b1001 r
b1001 y
b1001 &"
b1001 -"
b1001 8"
b1001 ?"
b1001 J"
b1001 Q"
b1001 \"
#1160
0#
#1200
0"
#1250
b11 E
b1001 W
b101 i
b1 {
b1000 /"
b111 A"
b110 S"
b11 ;
b11 =
b1001 M
b1001 O
b101 _
b101 a
b1 q
b1 s
b1000 %"
b1000 '"
b111 7"
b111 9"
b110 I"
b110 K"
b10000000110000001110000100000000001000001010000100100000011 !
b10000000110000001110000100000000001000001010000100100000011 *
b100 ["
b100 ]"
1"
0'
1)
b1 (
16
b0 4
b0 >
b0 @
b1010 F
b1010 P
b1010 R
b110 X
b110 b
b110 d
b10 j
b10 t
b10 v
b1011 |
b1011 ("
b1011 *"
b100 0"
b100 :"
b100 <"
b101 B"
b101 L"
b101 N"
b111 T"
b111 ^"
b111 `"
1#
b11 %
b11 &
b11 1
b11 3
b11 <
b11 C
b11 N
b11 U
b11 `
b11 g
b11 r
b11 y
b11 &"
b11 -"
b11 8"
b11 ?"
b11 J"
b11 Q"
b11 \"
#1260
0#
#1300
0"
