tasks/01_03_LU_cache/code/NOR.v
module NOR #(
    parameter WIDTH = 8
)(
    input [WIDTH - 1:0] in,
    output out 
);

assign out = ~(|in) ? 1 : 0;

endmodule // NOR

tasks/task_03_LU_cache/testbenches/NOR_tb.v
// задаём временную шкалу
`timescale 10ps / 1ps

module NOR_test;
    // дамп файла для GtkWave
    initial begin
        $dumpfile("NOR_simulation.vcd");
        $dumpvars(0, NOR_test);
    end
    
    // объявляем и задаём входные сигналы
    parameter CELL_SIZE = 3;

    reg [CELL_SIZE - 1:0] x = 3'b0;

    always begin
        #2 x = x + 1;
    end 

    // подключаем и задаём выходные сигналы
    wire out;

    // подключаем модуль
    NOR #(
        .WIDTH(CELL_SIZE)
    ) DD1 (
        .in(x),
        .out(out)
    );

    // отслеживание сигналов
    initial begin
        $monitor("At time %t, , in : %b, out %b", $time, x, out);
        #40 $finish;
    end

endmodule // XOR_test

tasks/task_03_LU_cache/simulation/files/NOR_simulation.vcd
$date
	Mon Dec  1 23:58:19 2025
$end
$version
	Icarus Verilog
$end
$timescale
	1ps
$end
$scope module NOR_test $end
$var wire 1 ! out $end
$var parameter 32 " CELL_SIZE $end
$var reg 3 # x [2:0] $end
$scope module DD1 $end
$var wire 3 $ in [2:0] $end
$var wire 1 ! out $end
$var parameter 32 % WIDTH $end
$upscope $end
$upscope $end
$enddefinitions $end
$comment Show the parameter values. $end
$dumpall
b11 %
b11 "
$end
#0
$dumpvars
b0 $
b0 #
1!
$end
#20
0!
b1 #
b1 $
#40
b10 #
b10 $
#60
b11 #
b11 $
#80
b100 #
b100 $
#100
b101 #
b101 $
#120
b110 #
b110 $
#140
b111 #
b111 $
#160
1!
b0 #
b0 $
#180
0!
b1 #
b1 $
#200
b10 #
b10 $
#220
b11 #
b11 $
#240
b100 #
b100 $
#260
b101 #
b101 $
#280
b110 #
b110 $
#300
b111 #
b111 $
#320
1!
b0 #
b0 $
#340
0!
b1 #
b1 $
#360
b10 #
b10 $
#380
b11 #
b11 $
#400
b100 #
b100 $
